Workbook
Name Slicer_Income_Group: #N/A
Name Slicer_Region: #N/A

Sheet Index
B2: GLOBAL ARMS TRANSFERS & DEFENSE POLICY (2000–2024)
B3: Workbook Navigation Index & Analytical Directory | Master Dataset Architecture
B5: Sheet Name | C5: Description
B6: Imports_Raw | C6: Raw World Bank / SIPRI arms imports records
B7: Exports_Raw | C7: Raw World Bank / SIPRI arms exports records
B8: Clean_Data | C8: 3,985 dyadic observations, enriched metadata, net trade calculations
B9: Analysis | C9: Macro KPIs, Top 10 rankings, regional balances, 25-yr supplier trajectory
B10: Dashboard | C10: Three-panel visual dashboard (trends, volumes, regional diverging balances)
B11: Pivot_Table | C11: Income tier cross-tabulation with dynamic region slicers
B12: Data_Dictionary | C12: Complete variable schemas, indicators, and methodology notes

Sheet Imports_Raw
A1: Data Source | B1: World Development Indicators
A3: Last Updated Date | B3: 46303
A5: Country Name | B5: Country Code | C5: Indicator Name | D5: Indicator Code | E5: 1960 | F5: 1961 | G5: 1962 | H5: 1963 | I5: 1964 | J5: 1965 | K5: 1966 | L5: 1967 | M5: 1968 | N5: 1969 | O5: 1970 | P5: 1971 | Q5: 1972 | R5: 1973 | S5: 1974 | T5: 1975 | U5: 1976 | V5: 1977 | W5: 1978 | X5: 1979 | Y5: 1980 | Z5: 1981 | AA5: 1982 | AB5: 1983 | AC5: 1984 | AD5: 1985 | AE5: 1986 | AF5: 1987 | AG5: 1988 | AH5: 1989 | AI5: 1990 | AJ5: 1991 | AK5: 1992 | AL5: 1993 | AM5: 1994 | AN5: 1995 | AO5: 1996 | AP5: 1997 | AQ5: 1998 | AR5: 1999 | AS5: 2000 | AT5: 2001 | AU5: 2002 | AV5: 2003 | AW5: 2004 | AX5: 2005 | AY5: 2006 | AZ5: 2007 | BA5: 2008 | BB5: 2009 | BC5: 2010 | BD5: 2011 | BE5: 2012 | BF5: 2013 | BG5: 2014 | BH5: 2015 | BI5: 2016 | BJ5: 2017 | BK5: 2018 | BL5: 2019 | BM5: 2020 | BN5: 2021 | BO5: 2022 | BP5: 2023 | BQ5: 2024 | BR5: 2025
A6: Aruba | B6: ABW | C6: Arms imports (SIPRI trend indicator values) | D6: MS.MIL.MPRT.KD
A7: Africa Eastern and Southern | B7: AFE | C7: Arms imports (SIPRI trend indicator values) | D7: MS.MIL.MPRT.KD | E7: 71000000 | G7: 327000000 | H7: 628000000 | I7: 431000000 | J7: 503000000 | K7: 768000000 | L7: 466000000 | M7: 305000000 | N7: 471000000 | O7: 1236000000 | P7: 874000000 | Q7: 582000000 | R7: 728000000 | S7: 799000000 | T7: 1427000000 | U7: 1260000000 | V7: 2173000000 | W7: 2628000000 | X7: 1048000000 | Y7: 1181000000 | Z7: 1650000000 | AA7: 1372000000 | AB7: 1386000000 | AC7: 1132000000 | AD7: 1077000000 | AE7: 1552000000 | AF7: 1877000000 | AG7: 1269000000 | AH7: 323000000 | AI7: 273000000 | AJ7: 224000000 | AL7: 401000000 | AM7: 413000000 | AN7: 97000000 | AO7: 312000000 | AP7: 350000000 | AS7: 522000000 | AT7: 403000000 | AX7: 598000000 | AY7: 1035000000 | AZ7: 1081000000 | BA7: 768000000 | BB7: 420000000 | BD7: 1131000000 | BE7: 988000000 | BF7: 563000000 | BG7: 308000000 | BH7: 330000000 | BO7: 259000000 | BP7: 166000000 | BR7: 420000000
A8: Afghanistan | B8: AFG | C8: Arms imports (SIPRI trend indicator values) | D8: MS.MIL.MPRT.KD | E8: 39000000 | F8: 55000000 | G8: 64000000 | H8: 40000000 | I8: 56000000 | J8: 91000000 | K8: 198000000 | L8: 230000000 | M8: 145000000 | N8: 166000000 | O8: 120000000 | P8: 25000000 | S8: 47000000 | T8: 137000000 | U8: 230000000 | V8: 75000000 | W8: 156000000 | X8: 449000000 | Y8: 632000000 | Z8: 553000000 | AA8: 455000000 | AB8: 269000000 | AC8: 394000000 | AD8: 158000000 | AE8: 210000000 | AF8: 489000000 | AG8: 927000000 | AH8: 1820000000 | AI8: 1612000000 | AJ8: 1236000000 | AU8: 34000000 | AX8: 33000000 | AY8: 3000000 | AZ8: 40000000 | BA8: 148000000 | BB8: 326000000 | BC8: 365000000 | BD8: 632000000 | BE8: 518000000 | BF8: 253000000 | BG8: 323000000 | BH8: 131000000 | BI8: 170000000 | BJ8: 235000000 | BK8: 312000000 | BL8: 379000000 | BM8: 231000000 | BN8: 65000000
A9: Africa Western and Central | B9: AFW | C9: Arms imports (SIPRI trend indicator values) | D9: MS.MIL.MPRT.KD | E9: 51000000 | F9: 136000000 | G9: 41000000 | H9: 28000000 | I9: 56000000 | J9: 119000000 | K9: 195000000 | L9: 92000000 | M9: 89000000 | N9: 113000000 | O9: 57000000 | P9: 155000000 | Q9: 135000000 | R9: 93000000 | S9: 162000000 | U9: 442000000 | V9: 304000000 | W9: 427000000 | X9: 416000000 | Y9: 709000000 | Z9: 609000000 | AA9: 854000000 | AB9: 226000000 | AC9: 673000000 | AD9: 611000000 | AE9: 372000000 | AF9: 217000000 | AG9: 159000000 | AH9: 194000000 | AI9: 146000000 | AM9: 136000000 | AP9: 85000000 | AS9: 111000000 | AT9: 56000000 | AU9: 84000000 | AV9: 159000000 | AW9: 83000000 | AY9: 102000000 | AZ9: 181000000 | BA9: 164000000 | BB9: 219000000 | BC9: 367000000 | BD9: 253000000 | BE9: 224000000 | BF9: 342000000 | BG9: 580000000 | BH9: 265000000 | BI9: 223000000 | BJ9: 157000000 | BK9: 159000000 | BL9: 189000000 | BM9: 205000000 | BN9: 499000000 | BO9: 324000000 | BP9: 587000000 | BQ9: 433000000 | BR9: 163000000
A10: Angola | B10: AGO | C10: Arms imports (SIPRI trend indicator values) | D10: MS.MIL.MPRT.KD | S10: 1000000 | T10: 233000000 | U10: 192000000 | V10: 134000000 | W10: 133000000 | X10: 116000000 | Y10: 116000000 | Z10: 264000000 | AA10: 344000000 | AB10: 589000000 | AC10: 501000000 | AD10: 536000000 | AE10: 710000000 | AF10: 1193000000 | AG10: 971000000 | AH10: 152000000 | AI10: 140000000 | AL10: 123000000 | AM10: 113000000 | AN10: 1000000 | AO10: 44000000 | AP10: 7000000 | AQ10: 150000000 | AR10: 360000000 | AS10: 149000000 | AT10: 157000000 | AU10: 148000000 | AV10: 48000000 | AW10: 8000000 | AX10: 38000000 | AY10: 7000000 | AZ10: 35000000 | BA10: 29000000 | BB10: 20000000 | BF10: 31000000 | BG10: 2000000 | BH10: 49000000 | BI10: 156000000 | BJ10: 113000000 | BK10: 274000000 | BL10: 170000000 | BM10: 51000000 | BO10: 46000000 | BP10: 15000000 | BQ10: 16000000 | BR10: 84000000
A11: Albania | B11: ALB | C11: Arms imports (SIPRI trend indicator values) | D11: MS.MIL.MPRT.KD | E11: 69000000 | F11: 74000000 | G11: 42000000 | H11: 12000000 | I11: 8000000 | J11: 140000000 | K11: 74000000 | L11: 163000000 | M11: 265000000 | N11: 297000000 | O11: 250000000 | P11: 332000000 | Q11: 134000000 | R11: 106000000 | S11: 137000000 | T11: 53000000 | U11: 5000000 | V11: 7000000 | W11: 5000000 | AN11: 26000000 | AV11: 2000000 | AX11: 7000000 | AZ11: 5000000 | BE11: 15000000 | BF11: 7000000 | BG11: 7000000 | BH11: 7000000 | BJ11: 1000000 | BK11: 1000000 | BL11: 5000000 | BM11: 12000000 | BN11: 1000000 | BP11: 1000000 | BQ11: 38000000 | BR11: 23000000
A12: Andorra | B12: AND | C12: Arms imports (SIPRI trend indicator values) | D12: MS.MIL.MPRT.KD
A13: Arab World | B13: ARB | C13: Arms imports (SIPRI trend indicator values) | D13: MS.MIL.MPRT.KD | E13: 581000000 | F13: 831000000 | G13: 1302000000 | H13: 1244000000 | I13: 1585000000 | J13: 1994000000 | K13: 3500000000 | L13: 4714000000 | M13: 3360000000 | N13: 3774000000 | O13: 4563000000 | P13: 3880000000 | Q13: 6573000000 | R13: 9290000000 | S13: 9119000000 | T13: 6348000000 | U13: 5998000000 | V13: 9678000000 | W13: 11448000000 | X13: 11375000000 | Y13: 11924000000 | Z13: 13660000000 | AA13: 16619000000 | AB13: 13760000000 | AC13: 12620000000 | AD13: 10621000000 | AE13: 10284000000 | AF13: 10073000000 | AG13: 5539000000 | AH13: 5810000000 | AI13: 6492000000 | AJ13: 4401000000 | AK13: 3752000000 | AL13: 5286000000 | AM13: 4188000000 | AN13: 4778000000 | AO13: 5332000000 | AP13: 6086000000 | AQ13: 4929000000 | AR13: 3466000000 | AS13: 2744000000 | AT13: 2105000000 | AU13: 2901000000 | AV13: 2379000000 | AW13: 4076000000 | AX13: 4497000000 | AY13: 4198000000 | AZ13: 3237000000 | BA13: 4160000000 | BB13: 4126000000 | BC13: 5446000000 | BD13: 7377000000 | BE13: 6034000000 | BF13: 7185000000 | BG13: 7631000000 | BH13: 10490000000 | BI13: 12782000000 | BJ13: 11766000000 | BK13: 9651000000 | BL13: 8120000000 | BM13: 6474000000 | BN13: 8071000000 | BO13: 10869000000 | BP13: 7241000000 | BQ13: 5605000000 | BR13: 6625000000
A14: United Arab Emirates | B14: ARE | C14: Arms imports (SIPRI trend indicator values) | D14: MS.MIL.MPRT.KD | M14: 13000000 | N14: 12000000 | O14: 67000000 | P14: 24000000 | Q14: 28000000 | R14: 88000000 | S14: 100000000 | T14: 145000000 | U14: 275000000 | V14: 310000000 | W14: 230000000 | X14: 39000000 | Y14: 213000000 | Z14: 420000000 | AA14: 155000000 | AB14: 163000000 | AC14: 310000000 | AD14: 145000000 | AE14: 132000000 | AF14: 195000000 | AG14: 45000000 | AH14: 663000000 | AI14: 561000000 | AJ14: 237000000 | AK14: 205000000 | AL14: 582000000 | AM14: 571000000 | AN14: 426000000 | AO14: 481000000 | AP14: 690000000 | AQ14: 757000000 | AR14: 441000000 | AS14: 244000000 | AT14: 186000000 | AU14: 223000000 | AV14: 676000000 | AW14: 1145000000 | AX14: 2072000000 | AY14: 1925000000 | AZ14: 819000000 | BA14: 730000000 | BB14: 604000000 | BC14: 650000000 | BD14: 1217000000 | BE14: 1139000000 | BF14: 2324000000 | BG14: 736000000 | BH14: 1691000000 | BI14: 1491000000 | BJ14: 909000000 | BK14: 1165000000 | BL14: 750000000 | BM14: 660000000 | BN14: 577000000 | BO14: 756000000 | BP14: 918000000 | BQ14: 1086000000 | BR14: 868000000
A15: Argentina | B15: ARG | C15: Arms imports (SIPRI trend indicator values) | D15: MS.MIL.MPRT.KD | E15: 111000000 | F15: 205000000 | G15: 47000000 | H15: 29000000 | I15: 19000000 | J15: 7000000 | K15: 93000000 | L15: 143000000 | M15: 430000000 | N15: 230000000 | O15: 257000000 | P15: 363000000 | Q15: 402000000 | R15: 248000000 | S15: 450000000 | T15: 268000000 | U15: 499000000 | V15: 204000000 | W15: 434000000 | X15: 451000000 | Y15: 445000000 | Z15: 833000000 | AA15: 406000000 | AB15: 1309000000 | AC15: 724000000 | AD15: 485000000 | AE15: 219000000 | AF15: 217000000 | AG15: 71000000 | AH15: 6000000 | AI15: 159000000 | AK15: 27000000 | AM15: 209000000 | AN15: 43000000 | AO15: 21000000 | AP15: 105000000 | AQ15: 171000000 | AR15: 276000000 | AS15: 208000000 | AT15: 6000000 | AU15: 15000000 | AV15: 11000000 | AW15: 161000000 | AX15: 3000000 | AY15: 9000000 | AZ15: 24000000 | BA15: 21000000 | BB15: 15000000 | BC15: 11000000 | BD15: 16000000 | BE15: 5000000 | BF15: 13000000 | BG15: 6000000 | BH15: 18000000 | BI15: 17000000 | BJ15: 47000000 | BK15: 19000000 | BL15: 51000000 | BM15: 7000000 | BN15: 77000000 | BO15: 50000000 | BP15: 22000000 | BQ15: 45000000 | BR15: 108000000
A16: Armenia | B16: ARM | C16: Arms imports (SIPRI trend indicator values) | D16: MS.MIL.MPRT.KD | AL16: 2000000 | AM16: 181000000 | AN16: 47000000 | AO16: 68000000 | AR16: 2000000 | AW16: 118000000 | AZ16: 1000000 | BB16: 46000000 | BC16: 52000000 | BD16: 5000000 | BF16: 52000000 | BI16: 112000000 | BJ16: 22000000 | BL16: 248000000 | BN16: 32000000 | BO16: 29000000 | BP16: 7000000 | BQ16: 32000000 | BR16: 21000000
A17: American Samoa | B17: ASM | C17: Arms imports (SIPRI trend indicator values) | D17: MS.MIL.MPRT.KD
A18: Antigua and Barbuda | B18: ATG | C18: Arms imports (SIPRI trend indicator values) | D18: MS.MIL.MPRT.KD | BO18: 0 | BP18: 0
A19: Australia | B19: AUS | C19: Arms imports (SIPRI trend indicator values) | D19: MS.MIL.MPRT.KD | E19: 116000000 | F19: 155000000 | G19: 460000000 | H19: 369000000 | I19: 539000000 | J19: 920000000 | K19: 707000000 | L19: 770000000 | M19: 557000000 | N19: 702000000 | O19: 230000000 | P19: 310000000 | Q19: 63000000 | R19: 713000000 | S19: 898000000 | T19: 108000000 | U19: 91000000 | V19: 278000000 | W19: 1029000000 | X19: 197000000 | Y19: 409000000 | Z19: 449000000 | AA19: 134000000 | AB19: 637000000 | AC19: 635000000 | AD19: 510000000 | AE19: 815000000 | AF19: 594000000 | AG19: 745000000 | AH19: 695000000 | AI19: 356000000 | AJ19: 219000000 | AK19: 364000000 | AL19: 448000000 | AM19: 262000000 | AN19: 64000000 | AO19: 597000000 | AP19: 35000000 | AQ19: 542000000 | AR19: 678000000 | AS19: 326000000 | AT19: 1215000000 | AU19: 638000000 | AV19: 765000000 | AW19: 447000000 | AX19: 458000000 | AY19: 721000000 | AZ19: 618000000 | BA19: 430000000 | BB19: 805000000 | BC19: 1558000000 | BD19: 1582000000 | BE19: 787000000 | BF19: 220000000 | BG19: 848000000 | BH19: 1445000000 | BI19: 1012000000 | BJ19: 1664000000 | BK19: 1553000000 | BL19: 1159000000 | BM19: 1632000000 | BN19: 1218000000 | BO19: 809000000 | BP19: 376000000 | BQ19: 1077000000 | BR19: 826000000
A20: Austria | B20: AUT | C20: Arms imports (SIPRI trend indicator values) | D20: MS.MIL.MPRT.KD | E20: 16000000 | F20: 27000000 | G20: 56000000 | H20: 201000000 | I20: 74000000 | J20: 78000000 | K20: 61000000 | L20: 48000000 | M20: 1000000 | N20: 12000000 | O20: 99000000 | P20: 123000000 | Q20: 93000000 | R20: 38000000 | S20: 32000000 | T20: 12000000 | U20: 12000000 | W20: 8000000 | X20: 72000000 | Y20: 177000000 | Z20: 73000000 | AA20: 97000000 | AB20: 145000000 | AC20: 13000000 | AD20: 28000000 | AE20: 19000000 | AF20: 7000000 | AG20: 117000000 | AH20: 84000000 | AI20: 5000000 | AJ20: 6000000 | AK20: 5000000 | AL20: 8000000 | AM20: 52000000 | AN20: 30000000 | AO20: 9000000 | AP20: 190000000 | AQ20: 247000000 | AR20: 48000000 | AS20: 25000000 | AT20: 15000000 | AU20: 81000000 | AV20: 41000000 | AW20: 56000000 | AX20: 26000000 | AY20: 5000000 | AZ20: 269000000 | BA20: 190000000 | BB20: 286000000 | BC20: 5000000 | BD20: 6000000 | BE20: 6000000 | BF20: 5000000 | BG20: 2000000 | BH20: 1000000 | BI20: 13000000 | BJ20: 10000000 | BK20: 6000000 | BL20: 18000000 | BM20: 14000000 | BN20: 34000000 | BO20: 5000000 | BP20: 17000000 | BQ20: 13000000 | BR20: 29000000
A21: Azerbaijan | B21: AZE | C21: Arms imports (SIPRI trend indicator values) | D21: MS.MIL.MPRT.KD | AL21: 50000000 | AM21: 25000000 | AS21: 3000000 | AU21: 89000000 | AW21: 4000000 | AX21: 63000000 | AY21: 168000000 | AZ21: 213000000 | BA21: 34000000 | BB21: 147000000 | BC21: 163000000 | BD21: 569000000 | BE21: 397000000 | BF21: 398000000 | BG21: 642000000 | BH21: 351000000 | BI21: 287000000 | BJ21: 290000000 | BK21: 375000000 | BL21: 44000000 | BM21: 51000000 | BO21: 9000000 | BP21: 3000000 | BQ21: 75000000 | BR21: 463000000
A22: Burundi | B22: BDI | C22: Arms imports (SIPRI trend indicator values) | D22: MS.MIL.MPRT.KD | K22: 9000000 | L22: 2000000 | N22: 3000000 | R22: 0 | Y22: 1000000 | Z22: 5000000 | AA22: 3000000 | AB22: 11000000 | AC22: 2000000 | AH22: 6000000 | AI22: 6000000 | AQ22: 12000000 | AT22: 1000000 | AU22: 3000000 | BB22: 1000000 | BC22: 2000000 | BE22: 5000000 | BH22: 1000000 | BI22: 3000000 | BL22: 2000000
A23: Belgium | B23: BEL | C23: Arms imports (SIPRI trend indicator values) | D23: MS.MIL.MPRT.KD | E23: 92000000 | F23: 132000000 | G23: 188000000 | H23: 575000000 | I23: 652000000 | J23: 521000000 | K23: 116000000 | L23: 39000000 | M23: 220000000 | N23: 240000000 | O23: 514000000 | P23: 499000000 | Q23: 492000000 | R23: 562000000 | S23: 113000000 | T23: 130000000 | U23: 184000000 | V23: 187000000 | W23: 409000000 | X23: 779000000 | Y23: 565000000 | Z23: 515000000 | AA23: 433000000 | AB23: 580000000 | AC23: 575000000 | AD23: 287000000 | AE23: 91000000 | AF23: 91000000 | AG23: 407000000 | AH23: 203000000 | AI23: 314000000 | AJ23: 125000000 | AK23: 48000000 | AL23: 73000000 | AM23: 47000000 | AN23: 16000000 | AO23: 3000000 | AP23: 50000000 | AQ23: 55000000 | AR23: 58000000 | AS23: 36000000 | AT23: 30000000 | AU23: 48000000 | AV23: 21000000 | AW23: 15000000 | AX23: 3000000 | AY23: 15000000 | AZ23: 171000000 | BA23: 191000000 | BB23: 87000000 | BC23: 40000000 | BD23: 27000000 | BE23: 33000000 | BF23: 48000000 | BG23: 99000000 | BH23: 52000000 | BI23: 4000000 | BJ23: 7000000 | BK23: 1000000 | BL23: 9000000 | BM23: 90000000 | BN23: 255000000 | BO23: 170000000 | BP23: 12000000 | BQ23: 508000000 | BR23: 430000000
A24: Benin | B24: BEN | C24: Arms imports (SIPRI trend indicator values) | D24: MS.MIL.MPRT.KD | F24: 2000000 | G24: 1000000 | I24: 2000000 | K24: 1000000 | O24: 0 | P24: 2000000 | R24: 1000000 | W24: 26000000 | X24: 6000000 | AA24: 10000000 | AB24: 3000000 | AC24: 1000000 | AD24: 3000000 | AF24: 1000000 | AG24: 0 | AH24: 0 | AU24: 7000000 | AZ24: 3000000 | BB24: 1000000 | BC24: 0 | BD24: 0 | BE24: 20000000 | BF24: 3000000 | BI24: 1000000 | BM24: 1000000 | BO24: 3000000 | BP24: 12000000 | BQ24: 7000000 | BR24: 4000000
A25: Burkina Faso | B25: BFA | C25: Arms imports (SIPRI trend indicator values) | D25: MS.MIL.MPRT.KD | F25: 1000000 | I25: 1000000 | J25: 0 | K25: 0 | M25: 0 | N25: 1000000 | O25: 1000000 | P25: 1000000 | T25: 14000000 | U25: 8000000 | V25: 9000000 | Y25: 0 | Z25: 9000000 | AA25: 1000000 | AB25: 16000000 | AC25: 9000000 | AD25: 2000000 | AE25: 3000000 | AG25: 12000000 | AJ25: 4000000 | AL25: 7000000 | AR25: 0 | AX25: 12000000 | AY25: 4000000 | AZ25: 4000000 | BB25: 3000000 | BC25: 0 | BD25: 16000000 | BE25: 3000000 | BH25: 5000000 | BI25: 7000000 | BJ25: 2000000 | BK25: 24000000 | BL25: 7000000 | BM25: 3000000 | BN25: 26000000 | BO25: 12000000 | BP25: 19000000 | BQ25: 37000000 | BR25: 34000000
A26: Bangladesh | B26: BGD | C26: Arms imports (SIPRI trend indicator values) | D26: MS.MIL.MPRT.KD | P26: 10000000 | Q26: 2000000 | R26: 76000000 | S26: 44000000 | T26: 39000000 | U26: 70000000 | V26: 62000000 | W26: 45000000 | X26: 1000000 | Y26: 55000000 | Z26: 72000000 | AA26: 128000000 | AB26: 109000000 | AC26: 9000000 | AD26: 124000000 | AE26: 4000000 | AF26: 1000000 | AG26: 242000000 | AH26: 302000000 | AI26: 199000000 | AJ26: 79000000 | AK26: 113000000 | AL26: 49000000 | AM26: 61000000 | AN26: 123000000 | AO26: 7000000 | AP26: 26000000 | AQ26: 1000000 | AR26: 184000000 | AS26: 200000000 | AT26: 274000000 | AU26: 37000000 | AV26: 8000000 | AW26: 32000000 | AX26: 10000000 | AY26: 221000000 | AZ26: 82000000 | BA26: 12000000 | BC26: 36000000 | BD26: 120000000 | BE26: 199000000 | BF26: 648000000 | BG26: 207000000 | BH26: 638000000 | BI26: 455000000 | BJ26: 334000000 | BK26: 161000000 | BL26: 713000000 | BM26: 70000000 | BN26: 60000000 | BO26: 331000000 | BP26: 74000000 | BQ26: 70000000 | BR26: 32000000
A27: Bulgaria | B27: BGR | C27: Arms imports (SIPRI trend indicator values) | D27: MS.MIL.MPRT.KD | E27: 482000000 | F27: 522000000 | G27: 493000000 | H27: 553000000 | I27: 326000000 | J27: 372000000 | K27: 218000000 | L27: 329000000 | M27: 256000000 | N27: 533000000 | O27: 771000000 | P27: 407000000 | Q27: 460000000 | R27: 274000000 | S27: 302000000 | T27: 390000000 | U27: 368000000 | V27: 492000000 | W27: 876000000 | X27: 323000000 | Y27: 580000000 | Z27: 984000000 | AA27: 610000000 | AB27: 754000000 | AC27: 945000000 | AD27: 619000000 | AE27: 932000000 | AF27: 449000000 | AG27: 253000000 | AH27: 314000000 | AI27: 755000000 | AJ27: 339000000 | AK27: 42000000 | AL27: 1000000 | AM27: 1000000 | AN27: 1000000 | AO27: 122000000 | AR27: 7000000 | AV27: 2000000 | AW27: 13000000 | AX27: 132000000 | AY27: 22000000 | AZ27: 48000000 | BA27: 117000000 | BB27: 119000000 | BC27: 8000000 | BD27: 29000000 | BE27: 5000000 | BH27: 4000000 | BL27: 2000000 | BM27: 44000000 | BN27: 1000000 | BO27: 3000000 | BR27: 540000000
A28: Bahrain | B28: BHR | C28: Arms imports (SIPRI trend indicator values) | D28: MS.MIL.MPRT.KD | P28: 0 | Q28: 7000000 | R28: 0 | S28: 1000000 | V28: 2000000 | W28: 12000000 | X28: 10000000 | Y28: 22000000 | Z28: 40000000 | AA28: 55000000 | AB28: 10000000 | AC28: 129000000 | AD28: 55000000 | AE28: 133000000 | AF28: 249000000 | AG28: 135000000 | AH28: 66000000 | AI28: 362000000 | AJ28: 68000000 | AK28: 51000000 | AL28: 1000000 | AM28: 8000000 | AN28: 71000000 | AO28: 51000000 | AP28: 197000000 | AQ28: 8000000 | AS28: 299000000 | AT28: 28000000 | AU28: 52000000 | AV28: 1000000 | AW28: 10000000 | AX28: 66000000 | AY28: 63000000 | AZ28: 27000000 | BA28: 21000000 | BC28: 98000000 | BD28: 4000000 | BE28: 24000000 | BF28: 69000000 | BG28: 1000000 | BH28: 17000000 | BI28: 30000000 | BJ28: 27000000 | BK28: 72000000 | BL28: 21000000 | BM28: 27000000 | BN28: 184000000 | BO28: 259000000 | BP28: 294000000 | BQ28: 850000000 | BR28: 30000000
A29: Bahamas, The | B29: BHS | C29: Arms imports (SIPRI trend indicator values) | D29: MS.MIL.MPRT.KD | W29: 11000000 | AE29: 33000000 | AI29: 2000000 | AJ29: 3000000 | AS29: 33000000 | AX29: 3000000 | BB29: 1000000 | BG29: 30000000 | BH29: 16000000 | BI29: 20000000 | BJ29: 12000000
A30: Bosnia and Herzegovina | B30: BIH | C30: Arms imports (SIPRI trend indicator values) | D30: MS.MIL.MPRT.KD | AL30: 6000000 | AM30: 6000000 | AO30: 58000000 | AP30: 78000000 | AQ30: 2000000 | AR30: 25000000 | BJ30: 0 | BL30: 0 | BM30: 0 | BN30: 12000000 | BR30: 1000000
A31: Belarus | B31: BLR | C31: Arms imports (SIPRI trend indicator values) | D31: MS.MIL.MPRT.KD | AQ31: 41000000 | AR31: 41000000 | AX31: 6000000 | AY31: 140000000 | BB31: 3000000 | BD31: 75000000 | BE31: 75000000 | BF31: 75000000 | BG31: 66000000 | BH31: 98000000 | BI31: 120000000 | BJ31: 158000000 | BK31: 142000000 | BL31: 333000000 | BM31: 13000000 | BN31: 69000000 | BO31: 215000000 | BP31: 178000000 | BQ31: 399000000 | BR31: 466000000
A32: Belize | B32: BLZ | C32: Arms imports (SIPRI trend indicator values) | D32: MS.MIL.MPRT.KD | AC32: 0 | AO32: 0 | AS32: 1000000 | BI32: 2000000 | BP32: 1000000
A33: Bermuda | B33: BMU | C33: Arms imports (SIPRI trend indicator values) | D33: MS.MIL.MPRT.KD
A34: Bolivia | B34: BOL | C34: Arms imports (SIPRI trend indicator values) | D34: MS.MIL.MPRT.KD | E34: 6000000 | F34: 4000000 | G34: 2000000 | H34: 4000000 | I34: 2000000 | J34: 2000000 | K34: 1000000 | L34: 14000000 | M34: 17000000 | N34: 1000000 | O34: 2000000 | P34: 2000000 | Q34: 12000000 | R34: 16000000 | S34: 23000000 | T34: 17000000 | U34: 16000000 | V34: 1000000 | W34: 11000000 | X34: 53000000 | Y34: 40000000 | Z34: 28000000 | AA34: 2000000 | AD34: 18000000 | AE34: 15000000 | AG34: 56000000 | AH34: 66000000 | AJ34: 11000000 | AK34: 25000000 | AL34: 16000000 | AM34: 9000000 | AN34: 2000000 | AR34: 9000000 | AS34: 19000000 | AV34: 5000000 | AW34: 1000000 | AX34: 1000000 | AY34: 9000000 | AZ34: 2000000 | BA34: 3000000 | BB34: 6000000 | BC34: 1000000 | BD34: 25000000 | BE34: 12000000 | BF34: 1000000 | BG34: 46000000 | BI34: 27000000 | BJ34: 7000000 | BK34: 2000000 | BL34: 34000000 | BM34: 26000000 | BQ34: 0
A35: Brazil | B35: BRA | C35: Arms imports (SIPRI trend indicator values) | D35: MS.MIL.MPRT.KD | E35: 236000000 | F35: 212000000 | G35: 62000000 | H35: 127000000 | I35: 25000000 | J35: 149000000 | K35: 57000000 | L35: 218000000 | M35: 236000000 | N35: 108000000 | O35: 217000000 | P35: 171000000 | Q35: 520000000 | R35: 598000000 | S35: 256000000 | T35: 538000000 | U35: 551000000 | V35: 525000000 | W35: 832000000 | X35: 375000000 | Y35: 338000000 | Z35: 61000000 | AA35: 72000000 | AB35: 88000000 | AC35: 123000000 | AD35: 82000000 | AE35: 139000000 | AF35: 234000000 | AG35: 125000000 | AH35: 742000000 | AI35: 140000000 | AJ35: 161000000 | AK35: 98000000 | AL35: 66000000 | AM35: 311000000 | AN35: 267000000 | AO35: 547000000 | AP35: 476000000 | AQ35: 200000000 | AR35: 308000000 | AS35: 86000000 | AT35: 573000000 | AU35: 221000000 | AV35: 110000000 | AW35: 85000000 | AX35: 223000000 | AY35: 178000000 | AZ35: 188000000 | BA35: 178000000 | BB35: 135000000 | BC35: 256000000 | BD35: 231000000 | BE35: 317000000 | BF35: 217000000 | BG35: 201000000 | BH35: 202000000 | BI35: 111000000 | BJ35: 96000000 | BK35: 258000000 | BL35: 125000000 | BM35: 134000000 | BN35: 240000000 | BO35: 469000000 | BP35: 193000000 | BQ35: 450000000 | BR35: 462000000
A36: Barbados | B36: BRB | C36: Arms imports (SIPRI trend indicator values) | D36: MS.MIL.MPRT.KD | Z36: 9000000 | AC36: 1000000 | AZ36: 10000000 | BA36: 10000000 | BB36: 10000000
A37: Brunei Darussalam | B37: BRN | C37: Arms imports (SIPRI trend indicator values) | D37: MS.MIL.MPRT.KD | J37: 5000000 | K37: 1000000 | L37: 18000000 | M37: 1000000 | O37: 5000000 | P37: 18000000 | Q37: 1000000 | R37: 1000000 | S37: 15000000 | T37: 1000000 | U37: 0 | W37: 46000000 | X37: 64000000 | Z37: 8000000 | AA37: 12000000 | AB37: 85000000 | AC37: 60000000 | AE37: 13000000 | AI37: 4000000 | AJ37: 4000000 | AO37: 17000000 | AP37: 31000000 | AQ37: 7000000 | AR37: 4000000 | AT37: 5000000 | AU37: 1000000 | AV37: 0 | AW37: 0 | AX37: 1000000 | AY37: 1000000 | BB37: 33000000 | BC37: 33000000 | BD37: 229000000 | BE37: 20000000 | BF37: 15000000 | BG37: 121000000 | BH37: 36000000 | BP37: 11000000 | BQ37: 28000000
A38: Bhutan | B38: BTN | C38: Arms imports (SIPRI trend indicator values) | D38: MS.MIL.MPRT.KD | M38: 1000000 | AW38: 0 | BH38: 1000000 | BI38: 1000000 | BN38: 5000000
A39: Botswana | B39: BWA | C39: Arms imports (SIPRI trend indicator values) | D39: MS.MIL.MPRT.KD | V39: 1000000 | W39: 1000000 | X39: 7000000 | Y39: 2000000 | Z39: 11000000 | AD39: 5000000 | AF39: 26000000 | AG39: 40000000 | AH39: 4000000 | AI39: 22000000 | AJ39: 2000000 | AK39: 2000000 | AL39: 11000000 | AN39: 12000000 | AO39: 32000000 | AP39: 71000000 | AQ39: 2000000 | AS39: 54000000 | AT39: 15000000 | AU39: 1000000 | AV39: 11000000 | AW39: 10000000 | BB39: 10000000 | BC39: 10000000 | BE39: 6000000 | BF39: 8000000 | BI39: 5000000 | BK39: 5000000 | BL39: 7000000 | BM39: 76000000 | BN39: 16000000 | BO39: 11000000 | BP39: 1000000 | BQ39: 11000000
A40: Central African Republic | B40: CAF | C40: Arms imports (SIPRI trend indicator values) | D40: MS.MIL.MPRT.KD | F40: 2000000 | J40: 1000000 | K40: 2000000 | M40: 3000000 | P40: 2000000 | R40: 0 | W40: 0 | Y40: 0 | Z40: 1000000 | AA40: 3000000 | AB40: 6000000 | AC40: 1000000 | AD40: 6000000 | AG40: 2000000 | AK40: 1000000 | AY40: 9000000 | BA40: 0 | BD40: 7000000 | BK40: 2000000 | BM40: 1000000 | BN40: 44000000 | BO40: 2000000 | BP40: 43000000
A41: Canada | B41: CAN | C41: Arms imports (SIPRI trend indicator values) | D41: MS.MIL.MPRT.KD | E41: 171000000 | F41: 1576000000 | G41: 1220000000 | H41: 1012000000 | I41: 742000000 | J41: 563000000 | K41: 306000000 | L41: 237000000 | M41: 336000000 | N41: 516000000 | O41: 623000000 | P41: 457000000 | Q41: 376000000 | R41: 78000000 | S41: 229000000 | T41: 195000000 | U41: 53000000 | V41: 90000000 | W41: 130000000 | X41: 193000000 | Y41: 442000000 | Z41: 453000000 | AA41: 277000000 | AB41: 649000000 | AC41: 654000000 | AD41: 848000000 | AE41: 849000000 | AF41: 787000000 | AG41: 712000000 | AH41: 37000000 | AI41: 157000000 | AJ41: 767000000 | AK41: 407000000 | AL41: 196000000 | AM41: 473000000 | AN41: 405000000 | AO41: 419000000 | AP41: 353000000 | AQ41: 111000000 | AR41: 143000000 | AS41: 529000000 | AT41: 520000000 | AU41: 418000000 | AV41: 140000000 | AW41: 341000000 | AX41: 106000000 | AY41: 97000000 | AZ41: 478000000 | BA41: 423000000 | BB41: 104000000 | BC41: 242000000 | BD41: 356000000 | BE41: 207000000 | BF41: 202000000 | BG41: 316000000 | BH41: 408000000 | BI41: 246000000 | BJ41: 354000000 | BK41: 185000000 | BL41: 187000000 | BM41: 248000000 | BN41: 357000000 | BO41: 214000000 | BP41: 73000000 | BQ41: 198000000 | BR41: 83000000
A42: Central Europe and the Baltics | B42: CEB | C42: Arms imports (SIPRI trend indicator values) | D42: MS.MIL.MPRT.KD | E42: 2091000000 | F42: 1996000000 | G42: 1652000000 | H42: 2179000000 | I42: 3066000000 | J42: 2721000000 | K42: 1773000000 | L42: 1839000000 | M42: 2045000000 | N42: 2373000000 | O42: 2215000000 | P42: 2126000000 | Q42: 2038000000 | R42: 2316000000 | S42: 2589000000 | T42: 2409000000 | U42: 2142000000 | V42: 2257000000 | W42: 3051000000 | X42: 2607000000 | Y42: 2603000000 | Z42: 2405000000 | AA42: 1946000000 | AB42: 1750000000 | AC42: 1961000000 | AD42: 2103000000 | AE42: 2856000000 | AF42: 1776000000 | AG42: 1435000000 | AH42: 1179000000 | AI42: 1595000000 | AJ42: 505000000 | AK42: 440000000 | AL42: 1165000000 | AM42: 226000000 | AN42: 522000000 | AO42: 541000000 | AR42: 360000000 | AS42: 233000000 | AT42: 254000000 | AU42: 369000000 | AV42: 541000000 | AW42: 694000000 | AX42: 1330000000 | AY42: 896000000 | AZ42: 1419000000 | BA42: 1064000000 | BB42: 505000000 | BC42: 453000000 | BD42: 443000000 | BE42: 328000000 | BF42: 287000000 | BG42: 327000000 | BI42: 357000000 | BJ42: 352000000 | BK42: 205000000 | BL42: 354000000 | BM42: 607000000 | BN42: 378000000 | BO42: 868000000 | BP42: 2461000000 | BQ42: 3002000000 | BR42: 4370000000
A43: Switzerland | B43: CHE | C43: Arms imports (SIPRI trend indicator values) | D43: MS.MIL.MPRT.KD | E43: 218000000 | F43: 37000000 | G43: 4000000 | H43: 52000000 | I43: 263000000 | J43: 228000000 | K43: 373000000 | L43: 177000000 | M43: 199000000 | N43: 166000000 | O43: 142000000 | P43: 153000000 | Q43: 192000000 | R43: 123000000 | S43: 64000000 | T43: 136000000 | U43: 142000000 | V43: 4000000 | W43: 217000000 | X43: 226000000 | Y43: 272000000 | Z43: 289000000 | AA43: 175000000 | AB43: 442000000 | AC43: 404000000 | AD43: 341000000 | AE43: 108000000 | AF43: 151000000 | AG43: 179000000 | AH43: 318000000 | AI43: 433000000 | AJ43: 469000000 | AK43: 381000000 | AL43: 98000000 | AM43: 114000000 | AN43: 93000000 | AO43: 187000000 | AP43: 375000000 | AQ43: 428000000 | AR43: 499000000 | AS43: 15000000 | AT43: 60000000 | AU43: 58000000 | AV43: 117000000 | AW43: 203000000 | AX43: 168000000 | AY43: 83000000 | AZ43: 108000000 | BA43: 15000000 | BB43: 36000000 | BC43: 38000000 | BD43: 24000000 | BE43: 2000000 | BG43: 5000000 | BH43: 10000000 | BI43: 70000000 | BO43: 15000000 | BP43: 33000000
A44: Channel Islands | B44: CHI | C44: Arms imports (SIPRI trend indicator values) | D44: MS.MIL.MPRT.KD
A45: Chile | B45: CHL | C45: Arms imports (SIPRI trend indicator values) | D45: MS.MIL.MPRT.KD | E45: 308000000 | F45: 38000000 | G45: 19000000 | H45: 123000000 | I45: 38000000 | J45: 49000000 | K45: 74000000 | L45: 150000000 | M45: 62000000 | N45: 13000000 | O45: 77000000 | P45: 185000000 | Q45: 51000000 | R45: 278000000 | S45: 272000000 | T45: 196000000 | U45: 387000000 | V45: 72000000 | W45: 192000000 | X45: 147000000 | Y45: 150000000 | Z45: 147000000 | AA45: 339000000 | AB45: 135000000 | AC45: 513000000 | AD45: 28000000 | AE45: 173000000 | AF45: 155000000 | AG45: 84000000 | AH45: 133000000 | AI45: 132000000 | AJ45: 102000000 | AK45: 179000000 | AL45: 84000000 | AM45: 81000000 | AN45: 330000000 | AO45: 163000000 | AP45: 280000000 | AQ45: 80000000 | AR45: 206000000 | AS45: 230000000 | AT45: 60000000 | AU45: 75000000 | AV45: 188000000 | AW45: 64000000 | AX45: 446000000 | AY45: 1097000000 | AZ45: 659000000 | BA45: 395000000 | BB45: 329000000 | BC45: 474000000 | BD45: 326000000 | BE45: 61000000 | BF45: 55000000 | BG45: 135000000 | BH45: 135000000 | BI45: 70000000 | BJ45: 49000000 | BK45: 74000000 | BL45: 16000000 | BM45: 304000000 | BN45: 66000000 | BO45: 207000000 | BP45: 9000000 | BQ45: 14000000 | BR45: 14000000
A46: China | B46: CHN | C46: Arms imports (SIPRI trend indicator values) | D46: MS.MIL.MPRT.KD | E46: 2357000000 | F46: 952000000 | G46: 415000000 | H46: 450000000 | I46: 485000000 | J46: 257000000 | K46: 225000000 | L46: 144000000 | M46: 180000000 | O46: 1000000 | P46: 1000000 | Q46: 1000000 | R46: 1000000 | S46: 1000000 | T46: 1000000 | U46: 1000000 | V46: 72000000 | W46: 83000000 | X46: 8000000 | Y46: 4000000 | AA46: 5000000 | AB46: 16000000 | AC46: 62000000 | AD46: 104000000 | AE46: 11000000 | AF46: 47000000 | AG46: 97000000 | AH46: 163000000 | AI46: 267000000 | AJ46: 439000000 | AK46: 1184000000 | AL46: 1230000000 | AM46: 304000000 | AN46: 701000000 | AO46: 1496000000 | AP46: 940000000 | AQ46: 375000000 | AR46: 1722000000 | AS46: 2473000000 | AT46: 2755000000 | AU46: 2830000000 | AV46: 2326000000 | AW46: 3236000000 | AX46: 3467000000 | AY46: 2831000000 | AZ46: 1699000000 | BA46: 1784000000 | BB46: 1382000000 | BC46: 940000000 | BD46: 1033000000 | BE46: 1542000000 | BF46: 1221000000 | BG46: 1033000000 | BH46: 1190000000 | BI46: 1209000000 | BJ46: 1546000000 | BK46: 2254000000 | BL46: 1571000000 | BM46: 775000000 | BN46: 685000000 | BO46: 646000000 | BP46: 428000000 | BQ46: 71000000 | BR46: 207000000
A47: Cote d'Ivoire | B47: CIV | C47: Arms imports (SIPRI trend indicator values) | D47: MS.MIL.MPRT.KD | F47: 3000000 | G47: 1000000 | H47: 1000000 | K47: 2000000 | L47: 3000000 | M47: 26000000 | N47: 2000000 | O47: 7000000 | P47: 17000000 | Q47: 1000000 | S47: 18000000 | V47: 22000000 | W47: 15000000 | X47: 38000000 | Y47: 56000000 | Z47: 19000000 | AC47: 9000000 | AH47: 2000000 | AK47: 0 | AN47: 2000000 | AP47: 0 | AR47: 2000000 | AS47: 0 | AU47: 32000000 | AV47: 61000000 | AW47: 9000000 | BG47: 6000000 | BH47: 5000000 | BI47: 5000000 | BJ47: 14000000 | BK47: 10000000 | BL47: 15000000 | BM47: 3000000 | BN47: 7000000 | BO47: 22000000 | BP47: 70000000 | BQ47: 7000000 | BR47: 15000000
A48: Cameroon | B48: CMR | C48: Arms imports (SIPRI trend indicator values) | D48: MS.MIL.MPRT.KD | F48: 0 | H48: 2000000 | I48: 0 | J48: 2000000 | K48: 2000000 | L48: 3000000 | M48: 3000000 | P48: 8000000 | Q48: 1000000 | R48: 15000000 | U48: 29000000 | V48: 73000000 | X48: 1000000 | Z48: 28000000 | AA48: 113000000 | AB48: 5000000 | AC48: 125000000 | AD48: 16000000 | AE48: 11000000 | AF48: 5000000 | AG48: 2000000 | AH48: 3000000 | AI48: 8000000 | AK48: 3000000 | AO48: 5000000 | AP48: 6000000 | AQ48: 9000000 | AR48: 4000000 | AT48: 6000000 | AU48: 10000000 | AX48: 5000000 | AY48: 3000000 | BA48: 1000000 | BC48: 10000000 | BE48: 9000000 | BF48: 139000000 | BG48: 124000000 | BH48: 10000000 | BI48: 23000000 | BJ48: 8000000 | BK48: 2000000 | BL48: 4000000 | BM48: 2000000 | BN48: 4000000 | BO48: 2000000 | BP48: 2000000
A49: Congo, Dem. Rep. | B49: COD | C49: Arms imports (SIPRI trend indicator values) | D49: MS.MIL.MPRT.KD | E49: 2000000 | F49: 9000000 | G49: 13000000 | H49: 32000000 | I49: 64000000 | J49: 23000000 | K49: 27000000 | L49: 16000000 | M49: 7000000 | N49: 28000000 | O49: 19000000 | P49: 165000000 | Q49: 15000000 | R49: 5000000 | S49: 9000000 | T49: 445000000 | U49: 134000000 | V49: 28000000 | W49: 38000000 | X49: 15000000 | Y49: 10000000 | Z49: 12000000 | AA49: 15000000 | AB49: 5000000 | AC49: 16000000 | AD49: 1000000 | AE49: 1000000 | AF49: 36000000 | AG49: 1000000 | AI49: 4000000 | AK49: 2000000 | AN49: 0 | AO49: 61000000 | AP49: 6000000 | AQ49: 10000000 | AR49: 46000000 | AS49: 89000000 | AT49: 11000000 | AU49: 18000000 | AX49: 26000000 | AY49: 24000000 | BA49: 18000000 | BB49: 37000000 | BC49: 156000000 | BE49: 15000000 | BF49: 1000000 | BH49: 3000000 | BI49: 43000000 | BK49: 1000000 | BM49: 9000000 | BP49: 27000000 | BQ49: 40000000 | BR49: 44000000
A50: Congo, Rep. | B50: COG | C50: Arms imports (SIPRI trend indicator values) | D50: MS.MIL.MPRT.KD | E50: 1000000 | F50: 1000000 | H50: 0 | J50: 0 | L50: 1000000 | M50: 1000000 | N50: 23000000 | O50: 9000000 | P50: 27000000 | Q50: 2000000 | S50: 7000000 | T50: 2000000 | U50: 4000000 | W50: 35000000 | X50: 26000000 | Y50: 17000000 | Z50: 3000000 | AA50: 11000000 | AB50: 25000000 | AC50: 25000000 | AD50: 3000000 | AG50: 28000000 | AH50: 44000000 | AI50: 44000000 | AJ50: 18000000 | AP50: 27000000 | AQ50: 2000000 | AR50: 2000000 | AS50: 0 | AV50: 8000000 | AW50: 7000000 | AX50: 4000000 | AY50: 1000000 | AZ50: 0 | BB50: 4000000 | BC50: 32000000 | BD50: 5000000 | BE50: 26000000 | BF50: 35000000 | BG50: 6000000 | BH50: 2000000 | BK50: 0 | BL50: 3000000 | BN50: 3000000 | BQ50: 9000000
A51: Colombia | B51: COL | C51: Arms imports (SIPRI trend indicator values) | D51: MS.MIL.MPRT.KD | E51: 5000000 | F51: 66000000 | G51: 6000000 | H51: 32000000 | I51: 9000000 | J51: 18000000 | K51: 32000000 | L51: 15000000 | M51: 32000000 | N51: 121000000 | O51: 8000000 | P51: 40000000 | Q51: 171000000 | R51: 163000000 | S51: 5000000 | T51: 291000000 | U51: 10000000 | V51: 8000000 | W51: 12000000 | X51: 36000000 | Y51: 12000000 | Z51: 28000000 | AA51: 18000000 | AB51: 300000000 | AC51: 660000000 | AD51: 7000000 | AE51: 6000000 | AF51: 4000000 | AG51: 37000000 | AH51: 218000000 | AI51: 13000000 | AJ51: 72000000 | AK51: 36000000 | AL51: 68000000 | AM51: 42000000 | AN51: 35000000 | AO51: 49000000 | AP51: 193000000 | AQ51: 160000000 | AR51: 44000000 | AS51: 68000000 | AT51: 268000000 | AU51: 173000000 | AV51: 145000000 | AW51: 18000000 | AX51: 18000000 | AY51: 54000000 | AZ51: 237000000 | BA51: 110000000 | BB51: 263000000 | BC51: 259000000 | BD51: 145000000 | BE51: 200000000 | BF51: 173000000 | BG51: 170000000 | BH51: 193000000 | BI51: 18000000 | BJ51: 91000000 | BK51: 16000000 | BL51: 22000000 | BM51: 80000000 | BN51: 45000000 | BO51: 50000000 | BP51: 3000000 | BQ51: 12000000 | BR51: 22000000
A52: Comoros | B52: COM | C52: Arms imports (SIPRI trend indicator values) | D52: MS.MIL.MPRT.KD | U52: 1000000 | V52: 1000000 | AF52: 1000000 | BA52: 6000000 | BE52: 1000000 | BR52: 0
A53: Cabo Verde | B53: CPV | C53: Arms imports (SIPRI trend indicator values) | D53: MS.MIL.MPRT.KD | U53: 2000000 | X53: 18000000 | AA53: 26000000 | AK53: 7000000 | AQ53: 9000000 | AS53: 1000000 | BB53: 2000000 | BE53: 10000000 | BL53: 3000000
A54: Costa Rica | B54: CRI | C54: Arms imports (SIPRI trend indicator values) | D54: MS.MIL.MPRT.KD | H54: 1000000 | K54: 0 | R54: 1000000 | T54: 3000000 | W54: 6000000 | X54: 2000000 | Y54: 0 | AC54: 0 | AD54: 1000000 | AE54: 1000000 | AH54: 2000000 | AL54: 3000000 | BK54: 0 | BL54: 8000000
A55: Caribbean small states | B55: CSS | C55: Arms imports (SIPRI trend indicator values) | D55: MS.MIL.MPRT.KD | J55: 11000000 | K55: 0 | Z55: 29000000
A56: Cuba | B56: CUB | C56: Arms imports (SIPRI trend indicator values) | D56: MS.MIL.MPRT.KD | E56: 153000000 | F56: 524000000 | G56: 1337000000 | H56: 288000000 | I56: 252000000 | J56: 135000000 | K56: 232000000 | L56: 163000000 | M56: 155000000 | N56: 155000000 | O56: 155000000 | P56: 162000000 | Q56: 452000000 | R56: 420000000 | S56: 408000000 | T56: 200000000 | U56: 316000000 | V56: 609000000 | W56: 503000000 | X56: 410000000 | Y56: 349000000 | Z56: 960000000 | AA56: 960000000 | AB56: 778000000 | AC56: 426000000 | AD56: 352000000 | AE56: 281000000 | AF56: 75000000 | AG56: 167000000 | AH56: 94000000 | AI56: 169000000 | AJ56: 159000000 | AW56: 8000000
A57: Curacao | B57: CUW | C57: Arms imports (SIPRI trend indicator values) | D57: MS.MIL.MPRT.KD
A58: Cayman Islands | B58: CYM | C58: Arms imports (SIPRI trend indicator values) | D58: MS.MIL.MPRT.KD
A59: Cyprus | B59: CYP | C59: Arms imports (SIPRI trend indicator values) | D59: MS.MIL.MPRT.KD | I59: 18000000 | J59: 22000000 | R59: 9000000 | AA59: 5000000 | AB59: 19000000 | AC59: 24000000 | AD59: 34000000 | AE59: 41000000 | AF59: 33000000 | AG59: 123000000 | AH59: 28000000 | AI59: 82000000 | AJ59: 94000000 | AK59: 26000000 | AL59: 10000000 | AM59: 37000000 | AN59: 34000000 | AO59: 171000000 | AP59: 98000000 | AQ59: 7000000 | AR59: 113000000 | AS59: 4000000 | AT59: 180000000 | AU59: 66000000 | AV59: 6000000 | AW59: 16000000 | AX59: 18000000 | AY59: 22000000 | AZ59: 16000000 | BC59: 44000000 | BD59: 41000000 | BE59: 6000000 | BJ59: 30000000 | BL59: 20000000 | BM59: 31000000 | BN59: 12000000 | BP59: 8000000 | BQ59: 120000000 | BR59: 28000000
A60: Czechia | B60: CZE | C60: Arms imports (SIPRI trend indicator values) | D60: MS.MIL.MPRT.KD | AN60: 1000000 | AO60: 35000000 | AP60: 9000000 | AQ60: 0 | AR60: 1000000 | AS60: 13000000 | AT60: 57000000 | AU60: 42000000 | AV60: 94000000 | AW60: 6000000 | AX60: 600000000 | AY60: 46000000 | AZ60: 10000000 | BA60: 25000000 | BB60: 26000000 | BC60: 50000000 | BD60: 112000000 | BE60: 44000000 | BF60: 18000000 | BI60: 7000000 | BK60: 7000000 | BL60: 1000000 | BM60: 8000000 | BN60: 32000000 | BO60: 69000000 | BP60: 148000000 | BQ60: 58000000 | BR60: 19000000
A61: Germany | B61: DEU | C61: Arms imports (SIPRI trend indicator values) | D61: MS.MIL.MPRT.KD | E61: 2036000000 | F61: 2093000000 | G61: 2501000000 | H61: 3312000000 | I61: 3828000000 | J61: 3515000000 | K61: 3387000000 | L61: 1385000000 | M61: 1249000000 | N61: 1233000000 | O61: 1257000000 | P61: 2240000000 | Q61: 796000000 | R61: 1721000000 | S61: 2141000000 | T61: 1831000000 | U61: 1357000000 | V61: 1012000000 | W61: 661000000 | X61: 65000000 | Y61: 150000000 | Z61: 261000000 | AA61: 453000000 | AB61: 434000000 | AC61: 412000000 | AD61: 130000000 | AE61: 322000000 | AF61: 340000000 | AG61: 447000000 | AH61: 701000000 | AI61: 757000000 | AJ61: 750000000 | AK61: 716000000 | AL61: 529000000 | AM61: 417000000 | AN61: 222000000 | AO61: 244000000 | AP61: 60000000 | AQ61: 618000000 | AR61: 129000000 | AS61: 113000000 | AT61: 133000000 | AU61: 71000000 | AV61: 70000000 | AW61: 245000000 | AX61: 206000000 | AY61: 413000000 | AZ61: 46000000 | BA61: 277000000 | BB61: 329000000 | BC61: 301000000 | BD61: 79000000 | BE61: 140000000 | BF61: 103000000 | BG61: 77000000 | BH61: 119000000 | BI61: 55000000 | BJ61: 43000000 | BK61: 14000000 | BL61: 38000000 | BM61: 105000000 | BN61: 235000000 | BO61: 269000000 | BP61: 203000000 | BQ61: 240000000 | BR61: 1632000000
A62: Djibouti | B62: DJI | C62: Arms imports (SIPRI trend indicator values) | D62: MS.MIL.MPRT.KD | V62: 3000000 | W62: 6000000 | X62: 36000000 | Y62: 5000000 | Z62: 6000000 | AA62: 3000000 | AB62: 3000000 | AD62: 1000000 | AE62: 8000000 | AF62: 1000000 | AJ62: 1000000 | AK62: 19000000 | AL62: 6000000 | AN62: 2000000 | AS62: 1000000 | AU62: 3000000 | AW62: 4000000 | AX62: 7000000 | BE62: 6000000 | BF62: 5000000 | BG62: 15000000 | BH62: 4000000 | BI62: 11000000 | BL62: 11000000 | BM62: 1000000 | BN62: 46000000 | BO62: 19000000 | BP62: 0
A63: Dominica | B63: DMA | C63: Arms imports (SIPRI trend indicator values) | D63: MS.MIL.MPRT.KD
A64: Denmark | B64: DNK | C64: Arms imports (SIPRI trend indicator values) | D64: MS.MIL.MPRT.KD | E64: 142000000 | F64: 335000000 | G64: 61000000 | H64: 137000000 | I64: 491000000 | J64: 455000000 | K64: 66000000 | L64: 72000000 | M64: 77000000 | N64: 19000000 | O64: 212000000 | P64: 384000000 | Q64: 156000000 | S64: 39000000 | T64: 89000000 | U64: 389000000 | V64: 391000000 | W64: 360000000 | X64: 55000000 | Y64: 480000000 | Z64: 477000000 | AA64: 470000000 | AB64: 231000000 | AC64: 70000000 | AD64: 88000000 | AE64: 16000000 | AF64: 99000000 | AG64: 98000000 | AH64: 187000000 | AI64: 131000000 | AJ64: 156000000 | AK64: 72000000 | AL64: 51000000 | AM64: 88000000 | AN64: 134000000 | AO64: 75000000 | AP64: 77000000 | AQ64: 120000000 | AR64: 74000000 | AS64: 50000000 | AT64: 148000000 | AU64: 39000000 | AV64: 48000000 | AW64: 232000000 | AX64: 117000000 | AY64: 86000000 | AZ64: 133000000 | BA64: 98000000 | BB64: 134000000 | BC64: 22000000 | BD64: 6000000 | BE64: 103000000 | BF64: 34000000 | BG64: 176000000 | BH64: 42000000 | BI64: 103000000 | BJ64: 53000000 | BK64: 54000000 | BL64: 55000000 | BM64: 63000000 | BN64: 264000000 | BO64: 214000000 | BP64: 280000000 | BQ64: 440000000 | BR64: 278000000
A65: Dominican Republic | B65: DOM | C65: Arms imports (SIPRI trend indicator values) | D65: MS.MIL.MPRT.KD | E65: 9000000 | F65: 15000000 | G65: 0 | H65: 7000000 | I65: 5000000 | J65: 10000000 | K65: 9000000 | L65: 1000000 | M65: 1000000 | N65: 0 | O65: 1000000 | P65: 2000000 | Q65: 7000000 | R65: 0 | T65: 2000000 | U65: 12000000 | Y65: 9000000 | Z65: 5000000 | AA65: 36000000 | AC65: 25000000 | AD65: 2000000 | AE65: 0 | AG65: 3000000 | AO65: 4000000 | AQ65: 6000000 | AR65: 1000000 | AS65: 13000000 | AT65: 5000000 | AU65: 0 | AV65: 9000000 | AW65: 36000000 | AX65: 2000000 | BB65: 10000000 | BC65: 51000000 | BD65: 12000000 | BH65: 1000000 | BI65: 0 | BM65: 4000000 | BO65: 5000000 | BP65: 9000000 | BQ65: 10000000 | BR65: 13000000
A66: Algeria | B66: DZA | C66: Arms imports (SIPRI trend indicator values) | D66: MS.MIL.MPRT.KD | F66: 7000000 | G66: 63000000 | H66: 90000000 | I66: 181000000 | J66: 354000000 | K66: 439000000 | L66: 525000000 | M66: 58000000 | N66: 79000000 | O66: 14000000 | P66: 14000000 | Q66: 180000000 | R66: 110000000 | S66: 13000000 | T66: 56000000 | U66: 130000000 | V66: 1052000000 | W66: 1267000000 | X66: 1823000000 | Y66: 1337000000 | Z66: 1381000000 | AA66: 1352000000 | AB66: 700000000 | AC66: 660000000 | AD66: 368000000 | AE66: 163000000 | AF66: 384000000 | AG66: 319000000 | AH66: 455000000 | AI66: 737000000 | AJ66: 1039000000 | AK66: 23000000 | AL66: 22000000 | AM66: 197000000 | AN66: 312000000 | AO66: 83000000 | AP66: 37000000 | AQ66: 98000000 | AR66: 388000000 | AS66: 405000000 | AT66: 539000000 | AU66: 252000000 | AV66: 204000000 | AW66: 251000000 | AX66: 159000000 | AY66: 340000000 | AZ66: 507000000 | BA66: 1522000000 | BB66: 1076000000 | BC66: 831000000 | BD66: 1133000000 | BE66: 662000000 | BF66: 361000000 | BG66: 715000000 | BH66: 897000000 | BI66: 2916000000 | BJ66: 1158000000 | BK66: 1278000000 | BL66: 167000000 | BM66: 601000000 | BN66: 164000000 | BO66: 450000000 | BP66: 394000000 | BQ66: 205000000 | BR66: 108000000
A67: East Asia & Pacific (excluding high income) | B67: EAP | C67: Arms imports (SIPRI trend indicator values) | D67: MS.MIL.MPRT.KD | E67: 3416000000 | F67: 2083000000 | G67: 1952000000 | H67: 1290000000 | I67: 1884000000 | J67: 1745000000 | K67: 2584000000 | L67: 2516000000 | M67: 2902000000 | N67: 1825000000 | O67: 2233000000 | S67: 2076000000 | T67: 1692000000 | U67: 1556000000 | V67: 1104000000 | W67: 1338000000 | X67: 2716000000 | Y67: 3095000000 | Z67: 2783000000 | AA67: 1742000000 | AB67: 2358000000 | AC67: 1983000000 | AD67: 2225000000 | AE67: 2080000000 | AF67: 1878000000 | AG67: 1989000000 | AH67: 1613000000 | AI67: 1552000000 | AJ67: 1610000000 | AK67: 1947000000 | AL67: 2177000000 | AM67: 2033000000 | AN67: 3067000000 | AO67: 3165000000 | AP67: 3050000000 | AQ67: 1066000000 | AR67: 3157000000 | AS67: 2844000000 | AT67: 3245000000 | AU67: 3476000000 | AV67: 3167000000 | AW67: 4052000000 | AX67: 4093000000 | AY67: 3467000000 | AZ67: 3021000000 | BA67: 2835000000 | BB67: 3333000000 | BC67: 1777000000 | BD67: 3325000000 | BE67: 3377000000 | BF67: 3301000000 | BG67: 3762000000 | BH67: 3290000000 | BI67: 3613000000 | BJ67: 4505000000 | BK67: 4313000000 | BL67: 2807000000 | BM67: 1921000000 | BN67: 2100000000 | BO67: 1717000000 | BP67: 1479000000 | BQ67: 944000000 | BR67: 2610000000
A68: Early-demographic dividend | B68: EAR | C68: Arms imports (SIPRI trend indicator values) | D68: MS.MIL.MPRT.KD | E68: 2823000000 | G68: 3598000000 | H68: 3952000000 | I68: 4556000000 | J68: 5348000000 | K68: 7047000000 | L68: 7564000000 | M68: 7759000000 | N68: 8487000000 | O68: 8447000000 | P68: 11913000000 | Q68: 13318000000 | R68: 15852000000 | S68: 15570000000 | T68: 15331000000 | U68: 15593000000 | V68: 20765000000 | W68: 19382000000 | X68: 14810000000 | Y68: 17012000000 | Z68: 19361000000 | AA68: 20416000000 | AB68: 17060000000 | AC68: 13626000000 | AD68: 13090000000 | AE68: 15748000000 | AF68: 15877000000 | AG68: 11765000000 | AH68: 10212000000 | AI68: 11244000000 | AJ68: 10545000000 | AK68: 8622000000 | AL68: 10731000000 | AM68: 9697000000 | AN68: 8153000000 | AO68: 7438000000 | AP68: 10087000000 | AQ68: 10432000000 | AR68: 9463000000 | AS68: 6325000000 | AT68: 5193000000 | AU68: 6980000000 | AV68: 6439000000 | AW68: 7750000000 | AX68: 6525000000 | AY68: 7518000000 | AZ68: 9375000000 | BA68: 8654000000 | BB68: 8027000000 | BC68: 10523000000 | BD68: 12247000000 | BE68: 12356000000 | BF68: 14258000000 | BG68: 12661000000 | BH68: 13382000000 | BI68: 15366000000 | BJ68: 15043000000 | BK68: 11364000000 | BL68: 11568000000 | BM68: 9916000000 | BN68: 10767000000 | BO68: 11082000000 | BP68: 9609000000 | BQ68: 6906000000 | BR68: 11091000000
A69: East Asia & Pacific | B69: EAS | C69: Arms imports (SIPRI trend indicator values) | D69: MS.MIL.MPRT.KD | E69: 5035000000 | F69: 2905000000 | G69: 2894000000 | H69: 2437000000 | I69: 4818000000 | J69: 4962000000 | K69: 4934000000 | L69: 4532000000 | M69: 4731000000 | N69: 4328000000 | O69: 3918000000 | P69: 5236000000 | Q69: 3660000000 | R69: 4656000000 | S69: 4844000000 | T69: 4707000000 | U69: 4421000000 | V69: 4366000000 | W69: 4542000000 | X69: 6055000000 | Y69: 6294000000 | Z69: 6396000000 | AA69: 5026000000 | AB69: 6333000000 | AC69: 5810000000 | AD69: 6239000000 | AE69: 6731000000 | AF69: 6079000000 | AG69: 7217000000 | AH69: 7035000000 | AI69: 6798000000 | AJ69: 6747000000 | AK69: 6256000000 | AL69: 7129000000 | AM69: 5369000000 | AN69: 7965000000 | AO69: 8203000000 | AP69: 10846000000 | AQ69: 9301000000 | AR69: 9077000000 | AS69: 6434000000 | AT69: 6293000000 | AU69: 5613000000 | AV69: 5502000000 | AW69: 6744000000 | AX69: 6961000000 | AY69: 6899000000 | AZ69: 6412000000 | BA69: 7066000000 | BB69: 7454000000 | BC69: 6411000000 | BD69: 8084000000 | BE69: 6687000000 | BF69: 5459000000 | BG69: 7021000000 | BH69: 6158000000 | BI69: 6730000000 | BJ69: 8472000000 | BK69: 8320000000 | BL69: 7108000000 | BM69: 6195000000 | BN69: 5559000000 | BO69: 5264000000 | BP69: 4042000000 | BQ69: 5068000000 | BR69: 5828000000
A70: Europe & Central Asia (excluding high income) | B70: ECA | C70: Arms imports (SIPRI trend indicator values) | D70: MS.MIL.MPRT.KD | E70: 650000000 | F70: 396000000 | G70: 308000000 | H70: 598000000 | I70: 847000000 | J70: 743000000 | K70: 599000000 | L70: 756000000 | M70: 683000000 | N70: 925000000 | O70: 646000000 | P70: 1273000000 | Q70: 1228000000 | R70: 896000000 | S70: 1416000000 | T70: 693000000 | U70: 363000000 | V70: 300000000 | W70: 989000000 | X70: 917000000 | Y70: 486000000 | Z70: 726000000 | AA70: 478000000 | AB70: 503000000 | AC70: 549000000 | AD70: 678000000 | AE70: 472000000 | AF70: 1429000000 | AG70: 1628000000 | AH70: 1026000000 | AI70: 1241000000 | AJ70: 1285000000 | AK70: 1884000000 | AL70: 2390000000 | AN70: 1755000000 | AQ70: 2712000000 | AR70: 1979000000 | AS70: 1329000000 | AW70: 488000000 | AX70: 1294000000 | AY70: 990000000 | BB70: 1079000000 | BC70: 821000000 | BD70: 1745000000 | BE70: 2186000000 | BF70: 1523000000 | BG70: 2421000000 | BH70: 1644000000 | BI70: 1632000000 | BJ70: 1339000000 | BK70: 1530000000 | BL70: 1823000000 | BM70: 721000000 | BN70: 1130000000 | BO70: 3807000000 | BP70: 5858000000 | BQ70: 6954000000 | BR70: 3913000000
A71: Europe & Central Asia | B71: ECS | C71: Arms imports (SIPRI trend indicator values) | D71: MS.MIL.MPRT.KD | E71: 7432000000 | F71: 6743000000 | G71: 6818000000 | H71: 10339000000 | I71: 14338000000 | J71: 12069000000 | K71: 9202000000 | L71: 8757000000 | M71: 8568000000 | N71: 10456000000 | O71: 7799000000 | P71: 10578000000 | Q71: 9482000000 | R71: 8472000000 | S71: 9513000000 | T71: 9712000000 | U71: 8528000000 | V71: 7274000000 | W71: 9745000000 | X71: 8187000000 | Y71: 8775000000 | Z71: 9252000000 | AA71: 8359000000 | AB71: 7826000000 | AC71: 7348000000 | AD71: 6242000000 | AE71: 6969000000 | AF71: 6524000000 | AG71: 8655000000 | AH71: 7988000000 | AI71: 7482000000 | AJ71: 7898000000 | AK71: 8754000000 | AL71: 7740000000 | AM71: 7227000000 | AN71: 5423000000 | AO71: 5535000000 | AP71: 5849000000 | AQ71: 8565000000 | AR71: 6544000000 | AS71: 6338000000 | AT71: 4712000000 | AU71: 3849000000 | AV71: 5522000000 | AW71: 4477000000 | AX71: 4529000000 | AY71: 5717000000 | AZ71: 7869000000 | BA71: 5352000000 | BB71: 5717000000 | BC71: 4578000000 | BD71: 4478000000 | BE71: 4672000000 | BF71: 3914000000 | BG71: 4285000000 | BH71: 4287000000 | BI71: 4294000000 | BJ71: 4331000000 | BK71: 3771000000 | BL71: 4192000000 | BM71: 4130000000 | BN71: 5032000000 | BO71: 9008000000 | BP71: 11378000000 | BQ71: 14482000000 | BR71: 14574000000
A72: Ecuador | B72: ECU | C72: Arms imports (SIPRI trend indicator values) | D72: MS.MIL.MPRT.KD | E72: 66000000 | H72: 3000000 | I72: 3000000 | J72: 29000000 | K72: 9000000 | L72: 21000000 | M72: 5000000 | N72: 1000000 | O72: 5000000 | P72: 85000000 | Q72: 41000000 | R72: 15000000 | S72: 22000000 | T72: 42000000 | U72: 226000000 | V72: 582000000 | W72: 224000000 | X72: 110000000 | Y72: 289000000 | Z72: 122000000 | AA72: 291000000 | AB72: 360000000 | AC72: 322000000 | AD72: 23000000 | AE72: 30000000 | AF72: 26000000 | AG72: 26000000 | AH72: 20000000 | AI72: 3000000 | AJ72: 136000000 | AK72: 4000000 | AL72: 18000000 | AM72: 17000000 | AN72: 39000000 | AO72: 29000000 | AP72: 103000000 | AQ72: 31000000 | AR72: 27000000 | AS72: 9000000 | AT72: 41000000 | AU72: 1000000 | AX72: 39000000 | AY72: 47000000 | AZ72: 2000000 | BA72: 102000000 | BB72: 77000000 | BC72: 90000000 | BD72: 70000000 | BE72: 89000000 | BF72: 12000000 | BG72: 56000000 | BH72: 27000000 | BI72: 26000000 | BJ72: 20000000 | BK72: 5000000 | BL72: 3000000 | BM72: 21000000 | BN72: 16000000 | BO72: 9000000 | BP72: 7000000 | BQ72: 19000000 | BR72: 30000000
A73: Egypt, Arab Rep. | B73: EGY | C73: Arms imports (SIPRI trend indicator values) | D73: MS.MIL.MPRT.KD | E73: 164000000 | F73: 544000000 | G73: 685000000 | H73: 741000000 | I73: 851000000 | J73: 962000000 | K73: 1540000000 | L73: 2241000000 | M73: 1276000000 | N73: 1242000000 | O73: 1983000000 | P73: 1982000000 | Q73: 3255000000 | R73: 2607000000 | S73: 1108000000 | T73: 566000000 | U73: 159000000 | V73: 410000000 | W73: 136000000 | X73: 631000000 | Y73: 1016000000 | Z73: 1195000000 | AA73: 2508000000 | AB73: 1695000000 | AC73: 1506000000 | AD73: 955000000 | AE73: 1465000000 | AF73: 1634000000 | AG73: 449000000 | AH73: 319000000 | AI73: 563000000 | AJ73: 887000000 | AK73: 973000000 | AL73: 1258000000 | AM73: 2027000000 | AN73: 1704000000 | AO73: 969000000 | AP73: 1051000000 | AQ73: 483000000 | AR73: 517000000 | AS73: 833000000 | AT73: 824000000 | AU73: 717000000 | AV73: 633000000 | AW73: 660000000 | AX73: 833000000 | AY73: 695000000 | AZ73: 660000000 | BA73: 326000000 | BB73: 95000000 | BC73: 689000000 | BD73: 653000000 | BE73: 308000000 | BF73: 719000000 | BG73: 430000000 | BH73: 1443000000 | BI73: 1653000000 | BJ73: 2480000000 | BK73: 1637000000 | BL73: 1088000000 | BM73: 1398000000 | BN73: 1299000000 | BO73: 742000000 | BP73: 1152000000 | BQ73: 128000000 | BR73: 697000000
A74: Euro area | B74: EMU | C74: Arms imports (SIPRI trend indicator values) | D74: MS.MIL.MPRT.KD | E74: 4387000000 | F74: 4209000000 | G74: 5011000000 | H74: 7205000000 | I74: 9204000000 | J74: 7436000000 | K74: 5309000000 | L74: 3795000000 | M74: 2967000000 | N74: 4095000000 | O74: 4994000000 | P74: 6631000000 | Q74: 5842000000 | R74: 4878000000 | S74: 5077000000 | T74: 6070000000 | U74: 5360000000 | V74: 4411000000 | W74: 5568000000 | X74: 4193000000 | Y74: 4413000000 | Z74: 4597000000 | AA74: 4524000000 | AB74: 4815000000 | AC74: 4182000000 | AD74: 3090000000 | AE74: 3917000000 | AF74: 2994000000 | AG74: 4823000000 | AH74: 4656000000 | AI74: 4178000000 | AJ74: 4496000000 | AK74: 4643000000 | AL74: 3233000000 | AM74: 3936000000 | AN74: 2519000000 | AO74: 2509000000 | AP74: 2692000000 | AQ74: 3825000000 | AR74: 2799000000 | AS74: 2236000000 | AT74: 1947000000 | AU74: 1552000000 | AV74: 3696000000 | AW74: 2709000000 | AX74: 1696000000 | AY74: 2698000000 | AZ74: 3651000000 | BA74: 2433000000 | BB74: 3213000000 | BC74: 2712000000 | BD74: 1171000000 | BE74: 1061000000 | BF74: 1368000000 | BG74: 925000000 | BH74: 1748000000 | BI74: 1625000000 | BJ74: 1247000000 | BK74: 1015000000 | BL74: 1268000000 | BM74: 1864000000 | BN74: 1908000000 | BO74: 2347000000 | BP74: 2241000000 | BQ74: 3351000000 | BR74: 6081000000
A75: Eritrea | B75: ERI | C75: Arms imports (SIPRI trend indicator values) | D75: MS.MIL.MPRT.KD | AL75: 21000000 | AM75: 20000000 | AN75: 7000000 | AO75: 43000000 | AP75: 53000000 | AQ75: 212000000 | AR75: 31000000 | AS75: 20000000 | AT75: 57000000 | AU75: 18000000 | AV75: 17000000 | AW75: 80000000 | AX75: 99000000 | AZ75: 4000000
A76: Spain | B76: ESP | C76: Arms imports (SIPRI trend indicator values) | D76: MS.MIL.MPRT.KD | E76: 214000000 | F76: 103000000 | G76: 55000000 | H76: 15000000 | I76: 51000000 | J76: 382000000 | K76: 307000000 | L76: 303000000 | M76: 133000000 | N76: 181000000 | O76: 234000000 | P76: 637000000 | Q76: 793000000 | R76: 895000000 | S76: 557000000 | T76: 1161000000 | U76: 831000000 | V76: 312000000 | W76: 432000000 | X76: 650000000 | Y76: 689000000 | Z76: 636000000 | AA76: 512000000 | AB76: 614000000 | AC76: 81000000 | AD76: 327000000 | AE76: 1081000000 | AF76: 1082000000 | AG76: 1954000000 | AH76: 835000000 | AI76: 691000000 | AJ76: 109000000 | AK76: 207000000 | AL76: 299000000 | AM76: 838000000 | AN76: 355000000 | AO76: 395000000 | AP76: 192000000 | AQ76: 82000000 | AR76: 357000000 | AS76: 315000000 | AT76: 140000000 | AU76: 266000000 | AV76: 239000000 | AW76: 288000000 | AX76: 358000000 | AY76: 312000000 | AZ76: 343000000 | BA76: 347000000 | BB76: 228000000 | BC76: 272000000 | BD76: 166000000 | BE76: 219000000 | BF76: 155000000 | BG76: 109000000 | BH76: 152000000 | BI76: 104000000 | BJ76: 82000000 | BK76: 149000000 | BL76: 35000000 | BM76: 70000000 | BN76: 134000000 | BO76: 198000000 | BP76: 159000000 | BQ76: 159000000 | BR76: 237000000
A77: Estonia | B77: EST | C77: Arms imports (SIPRI trend indicator values) | D77: MS.MIL.MPRT.KD | AK77: 2000000 | AL77: 3000000 | AM77: 15000000 | AN77: 17000000 | AO77: 1000000 | AP77: 13000000 | AQ77: 4000000 | AR77: 1000000 | AS77: 27000000 | AU77: 2000000 | AV77: 14000000 | AW77: 11000000 | AX77: 26000000 | AY77: 4000000 | AZ77: 18000000 | BA77: 28000000 | BB77: 42000000 | BC77: 13000000 | BD77: 1000000 | BE77: 2000000 | BF77: 18000000 | BG77: 2000000 | BH77: 18000000 | BI77: 32000000 | BJ77: 36000000 | BK77: 19000000 | BL77: 20000000 | BM77: 25000000 | BN77: 20000000 | BO77: 15000000 | BP77: 23000000 | BQ77: 115000000 | BR77: 204000000
A78: Ethiopia | B78: ETH | C78: Arms imports (SIPRI trend indicator values) | D78: MS.MIL.MPRT.KD | E78: 24000000 | F78: 4000000 | G78: 21000000 | H78: 27000000 | I78: 4000000 | J78: 14000000 | K78: 99000000 | L78: 31000000 | M78: 34000000 | N78: 24000000 | O78: 90000000 | P78: 54000000 | Q78: 53000000 | R78: 5000000 | S78: 36000000 | T78: 58000000 | U78: 113000000 | V78: 1133000000 | W78: 965000000 | X78: 113000000 | Y78: 330000000 | Z78: 328000000 | AA78: 516000000 | AB78: 403000000 | AC78: 228000000 | AD78: 268000000 | AE78: 348000000 | AF78: 239000000 | AG78: 155000000 | AH78: 47000000 | AI78: 2000000 | AJ78: 80000000 | AP78: 69000000 | AQ78: 208000000 | AR78: 152000000 | AS78: 114000000 | AU78: 20000000 | AV78: 174000000 | AW78: 239000000 | BC78: 58000000 | BD78: 76000000 | BE78: 193000000 | BF78: 154000000 | BG78: 33000000 | BH78: 10000000 | BI78: 55000000 | BJ78: 51000000 | BK78: 14000000 | BL78: 76000000 | BM78: 25000000 | BN78: 16000000 | BO78: 45000000 | BP78: 2000000 | BQ78: 48000000 | BR78: 63000000
A79: European Union | B79: EUU | C79: Arms imports (SIPRI trend indicator values) | D79: MS.MIL.MPRT.KD | E79: 6365000000 | F79: 6183000000 | G79: 6408000000 | H79: 9303000000 | I79: 12835000000 | J79: 10564000000 | K79: 7229000000 | L79: 5695000000 | M79: 5022000000 | N79: 6126000000 | O79: 6787000000 | P79: 8894000000 | Q79: 7772000000 | R79: 7151000000 | S79: 7659000000 | T79: 8470000000 | U79: 7737000000 | V79: 6681000000 | W79: 8332000000 | X79: 6765000000 | Y79: 7207000000 | Z79: 6990000000 | AA79: 6483000000 | AB79: 6148000000 | AC79: 5376000000 | AD79: 4746000000 | AE79: 5975000000 | AF79: 4545000000 | AG79: 6255000000 | AH79: 5835000000 | AI79: 5243000000 | AJ79: 4870000000 | AK79: 5062000000 | AL79: 4276000000 | AM79: 4436000000 | AN79: 3013000000 | AO79: 3013000000 | AP79: 3134000000 | AQ79: 4497000000 | AR79: 3415000000 | AS79: 2676000000 | AT79: 2386000000 | AU79: 1981000000 | AV79: 4268000000 | AW79: 3572000000 | AX79: 3040000000 | AY79: 3710000000 | AZ79: 5111000000 | BA79: 3326000000 | BB79: 3644000000 | BC79: 3083000000 | BD79: 1703000000 | BE79: 1658000000 | BF79: 1646000000 | BG79: 1431000000 | BH79: 1963000000 | BI79: 2041000000 | BJ79: 1551000000 | BK79: 1196000000 | BL79: 1573000000 | BM79: 2314000000 | BN79: 2507000000 | BO79: 3588000000 | BP79: 4768000000 | BQ79: 6348000000 | BR79: 9516000000
A80: Fragility, Conflict, and Violence (FCV) situations | B80: FCV | C80: Arms imports (SIPRI trend indicator values) | D80: MS.MIL.MPRT.KD | E80: 464000000 | F80: 366000000 | G80: 575000000 | H80: 586000000 | I80: 723000000 | J80: 1130000000 | K80: 2119000000 | L80: 2345000000 | M80: 2461000000 | N80: 2865000000 | O80: 3172000000 | R80: 8192000000 | S80: 9908000000 | U80: 9106000000 | V80: 12178000000 | W80: 12713000000 | X80: 8061000000 | Y80: 9035000000 | Z80: 9298000000 | AA80: 10551000000 | AB80: 8492000000 | AC80: 9261000000 | AD80: 8157000000 | AE80: 6701000000 | AF80: 6934000000 | AG80: 4952000000 | AH80: 4529000000 | AI80: 4037000000 | AJ80: 3051000000 | AK80: 835000000 | AL80: 1545000000 | BB80: 1465000000 | BC80: 2426000000 | BE80: 2532000000 | BF80: 2084000000 | BG80: 1625000000 | BH80: 2394000000 | BI80: 3136000000 | BJ80: 1709000000 | BK80: 1466000000 | BL80: 1138000000 | BM80: 793000000 | BN80: 687000000 | BO80: 3510000000 | BP80: 4836000000 | BQ80: 6001000000 | BR80: 2695000000
A81: Finland | B81: FIN | C81: Arms imports (SIPRI trend indicator values) | D81: MS.MIL.MPRT.KD | E81: 60000000 | F81: 52000000 | G81: 48000000 | H81: 252000000 | I81: 103000000 | J81: 81000000 | K81: 42000000 | L81: 76000000 | M81: 23000000 | N81: 21000000 | O81: 15000000 | P81: 4000000 | Q81: 26000000 | R81: 13000000 | S81: 172000000 | T81: 129000000 | U81: 74000000 | V81: 12000000 | W81: 105000000 | X81: 47000000 | Y81: 328000000 | Z81: 118000000 | AA81: 132000000 | AB81: 112000000 | AC81: 127000000 | AD81: 203000000 | AE81: 98000000 | AF81: 66000000 | AG81: 141000000 | AH81: 86000000 | AI81: 88000000 | AJ81: 65000000 | AK81: 442000000 | AL81: 406000000 | AM81: 234000000 | AN81: 195000000 | AO81: 552000000 | AP81: 397000000 | AQ81: 560000000 | AR81: 768000000 | AS81: 472000000 | AT81: 7000000 | AU81: 15000000 | AV81: 242000000 | AW81: 67000000 | AX81: 93000000 | AY81: 132000000 | AZ81: 149000000 | BA81: 134000000 | BB81: 37000000 | BC81: 41000000 | BD81: 60000000 | BE81: 87000000 | BF81: 254000000 | BG81: 182000000 | BH81: 268000000 | BI81: 122000000 | BJ81: 47000000 | BK81: 82000000 | BL81: 86000000 | BM81: 96000000 | BN81: 20000000 | BO81: 12000000 | BP81: 37000000 | BQ81: 105000000 | BR81: 51000000
A82: Fiji | B82: FJI | C82: Arms imports (SIPRI trend indicator values) | D82: MS.MIL.MPRT.KD | T82: 8000000 | U82: 4000000 | AI82: 1000000 | AK82: 3000000 | AM82: 6000000 | AN82: 12000000 | BJ82: 1000000 | BM82: 7000000 | BQ82: 16000000
A83: France | B83: FRA | C83: Arms imports (SIPRI trend indicator values) | D83: MS.MIL.MPRT.KD | E83: 526000000 | F83: 321000000 | G83: 122000000 | H83: 162000000 | I83: 1300000000 | J83: 378000000 | K83: 106000000 | L83: 98000000 | M83: 123000000 | N83: 64000000 | O83: 44000000 | P83: 57000000 | Q83: 33000000 | R83: 51000000 | S83: 46000000 | T83: 45000000 | U83: 186000000 | V83: 194000000 | W83: 231000000 | X83: 107000000 | Y83: 70000000 | Z83: 106000000 | AA83: 142000000 | AB83: 108000000 | AC83: 73000000 | AD83: 20000000 | AE83: 100000000 | AF83: 84000000 | AG83: 134000000 | AH83: 107000000 | AI83: 77000000 | AJ83: 963000000 | AK83: 439000000 | AL83: 102000000 | AM83: 84000000 | AN83: 99000000 | AO83: 64000000 | AP83: 223000000 | AQ83: 171000000 | AR83: 105000000 | AS83: 98000000 | AT83: 61000000 | AU83: 38000000 | AV83: 55000000 | AW83: 93000000 | AX83: 2000000 | AY83: 68000000 | AZ83: 75000000 | BA83: 2000000 | BB83: 72000000 | BC83: 103000000 | BD83: 41000000 | BE83: 86000000 | BF83: 104000000 | BG83: 17000000 | BH83: 36000000 | BI83: 38000000 | BJ83: 84000000 | BK83: 201000000 | BL83: 104000000 | BM83: 225000000 | BN83: 105000000 | BO83: 130000000 | BP83: 114000000 | BQ83: 183000000 | BR83: 236000000
A84: Faroe Islands | B84: FRO | C84: Arms imports (SIPRI trend indicator values) | D84: MS.MIL.MPRT.KD
A85: Micronesia, Fed. Sts. | B85: FSM | C85: Arms imports (SIPRI trend indicator values) | D85: MS.MIL.MPRT.KD | AH85: 2000000 | AI85: 14000000 | AP85: 6000000 | BO85: 7000000 | BP85: 7000000
A86: Gabon | B86: GAB | C86: Arms imports (SIPRI trend indicator values) | D86: MS.MIL.MPRT.KD | F86: 3000000 | I86: 3000000 | J86: 0 | K86: 2000000 | M86: 4000000 | N86: 4000000 | O86: 1000000 | P86: 24000000 | R86: 2000000 | S86: 11000000 | T86: 34000000 | U86: 47000000 | V86: 28000000 | W86: 76000000 | Y86: 33000000 | Z86: 36000000 | AA86: 5000000 | AB86: 11000000 | AC86: 100000000 | AD86: 3000000 | AE86: 8000000 | AF86: 10000000 | AG86: 22000000 | AI86: 29000000 | AW86: 7000000 | AY86: 20000000 | AZ86: 18000000 | BC86: 27000000 | BD86: 5000000 | BE86: 1000000 | BF86: 2000000 | BH86: 5000000 | BI86: 3000000 | BL86: 26000000 | BN86: 2000000 | BP86: 16000000 | BQ86: 6000000
A87: United Kingdom | B87: GBR | C87: Arms imports (SIPRI trend indicator values) | D87: MS.MIL.MPRT.KD | E87: 26000000 | F87: 34000000 | G87: 38000000 | H87: 159000000 | I87: 133000000 | J87: 166000000 | K87: 242000000 | L87: 1444000000 | M87: 2348000000 | N87: 2701000000 | O87: 70000000 | P87: 176000000 | Q87: 222000000 | R87: 239000000 | S87: 319000000 | T87: 337000000 | U87: 251000000 | V87: 262000000 | W87: 191000000 | X87: 232000000 | Y87: 557000000 | Z87: 812000000 | AA87: 766000000 | AB87: 292000000 | AC87: 682000000 | AD87: 355000000 | AE87: 273000000 | AF87: 207000000 | AG87: 285000000 | AH87: 209000000 | AI87: 130000000 | AJ87: 953000000 | AK87: 1147000000 | AL87: 796000000 | AM87: 421000000 | AN87: 496000000 | AO87: 568000000 | AP87: 513000000 | AQ87: 770000000 | AR87: 132000000 | AS87: 937000000 | AT87: 1287000000 | AU87: 721000000 | AV87: 770000000 | AW87: 212000000 | AX87: 31000000 | AY87: 375000000 | AZ87: 817000000 | BA87: 575000000 | BB87: 381000000 | BC87: 461000000 | BD87: 347000000 | BE87: 566000000 | BF87: 509000000 | BG87: 217000000 | BH87: 424000000 | BI87: 288000000 | BJ87: 1002000000 | BK87: 463000000 | BL87: 402000000 | BM87: 635000000 | BN87: 886000000 | BO87: 859000000 | BP87: 469000000 | BQ87: 486000000 | BR87: 609000000
A88: Georgia | B88: GEO | C88: Arms imports (SIPRI trend indicator values) | D88: MS.MIL.MPRT.KD | AL88: 4000000 | AP88: 4000000 | AQ88: 28000000 | AR88: 23000000 | AS88: 6000000 | AT88: 85000000 | AV88: 1000000 | AW88: 38000000 | AX88: 95000000 | AY88: 97000000 | AZ88: 161000000 | BA88: 132000000 | BB88: 38000000 | BD88: 2000000 | BE88: 9000000 | BF88: 5000000 | BG88: 1000000 | BJ88: 7000000 | BK88: 41000000 | BL88: 6000000 | BO88: 2000000 | BP88: 0 | BQ88: 15000000
A89: Ghana | B89: GHA | C89: Arms imports (SIPRI trend indicator values) | D89: MS.MIL.MPRT.KD | E89: 12000000 | F89: 107000000 | G89: 20000000 | H89: 6000000 | I89: 40000000 | J89: 40000000 | K89: 24000000 | L89: 1000000 | Q89: 12000000 | R89: 13000000 | S89: 19000000 | T89: 28000000 | U89: 39000000 | W89: 18000000 | X89: 7000000 | Y89: 38000000 | Z89: 48000000 | AD89: 5000000 | AF89: 13000000 | AH89: 2000000 | AI89: 4000000 | AJ89: 1000000 | AM89: 11000000 | AO89: 7000000 | AP89: 5000000 | AR89: 8000000 | AS89: 1000000 | AT89: 12000000 | AU89: 1000000 | AV89: 6000000 | AW89: 37000000 | AX89: 0 | AZ89: 16000000 | BB89: 6000000 | BC89: 2000000 | BD89: 76000000 | BE89: 39000000 | BF89: 52000000 | BG89: 17000000 | BH89: 13000000 | BI89: 22000000 | BK89: 0 | BL89: 2000000 | BM89: 12000000 | BO89: 40000000 | BP89: 8000000 | BQ89: 11000000 | BR89: 5000000
A90: Gibraltar | B90: GIB | C90: Arms imports (SIPRI trend indicator values) | D90: MS.MIL.MPRT.KD
A91: Guinea | B91: GIN | C91: Arms imports (SIPRI trend indicator values) | D91: MS.MIL.MPRT.KD | E91: 33000000 | F91: 2000000 | H91: 0 | I91: 0 | J91: 18000000 | L91: 7000000 | N91: 0 | O91: 1000000 | P91: 4000000 | Q91: 5000000 | R91: 18000000 | S91: 24000000 | T91: 2000000 | U91: 18000000 | V91: 8000000 | W91: 45000000 | X91: 69000000 | Z91: 1000000 | AA91: 1000000 | AB91: 1000000 | AE91: 39000000 | AH91: 40000000 | AI91: 1000000 | AJ91: 1000000 | AQ91: 4000000 | AS91: 26000000 | AT91: 6000000 | AV91: 2000000 | AX91: 1000000 | AZ91: 0 | BC91: 5000000 | BD91: 1000000 | BE91: 4000000 | BG91: 5000000 | BJ91: 2000000 | BK91: 1000000 | BL91: 4000000 | BN91: 1000000 | BP91: 1000000 | BQ91: 6000000 | BR91: 6000000
A92: Gambia, The | B92: GMB | C92: Arms imports (SIPRI trend indicator values) | D92: MS.MIL.MPRT.KD | N92: 0 | Z92: 3000000 | AH92: 12000000 | AW92: 5000000 | BB92: 16000000 | BO92: 1000000 | BP92: 0 | BR92: 1000000
A93: Guinea-Bissau | B93: GNB | C93: Arms imports (SIPRI trend indicator values) | D93: MS.MIL.MPRT.KD | S93: 21000000 | T93: 12000000 | U93: 14000000 | W93: 14000000 | X93: 24000000 | Y93: 2000000 | Z93: 1000000 | AC93: 11000000 | AE93: 35000000 | AG93: 20000000 | AI93: 22000000 | AJ93: 6000000 | AL93: 5000000
A94: Equatorial Guinea | B94: GNQ | C94: Arms imports (SIPRI trend indicator values) | D94: MS.MIL.MPRT.KD | W94: 5000000 | Y94: 1000000 | AA94: 5000000 | AR94: 3000000 | AT94: 7000000 | AW94: 7000000 | AX94: 11000000 | AY94: 7000000 | AZ94: 28000000 | BA94: 30000000 | BB94: 68000000 | BC94: 3000000 | BD94: 56000000 | BE94: 60000000 | BF94: 2000000 | BG94: 92000000 | BK94: 20000000 | BN94: 0 | BQ94: 12000000
A95: Greece | B95: GRC | C95: Arms imports (SIPRI trend indicator values) | D95: MS.MIL.MPRT.KD | E95: 261000000 | F95: 148000000 | G95: 340000000 | H95: 106000000 | I95: 639000000 | J95: 497000000 | K95: 212000000 | L95: 373000000 | M95: 107000000 | N95: 292000000 | O95: 305000000 | P95: 581000000 | Q95: 689000000 | R95: 246000000 | S95: 428000000 | T95: 912000000 | U95: 1288000000 | V95: 980000000 | W95: 1281000000 | X95: 734000000 | Y95: 660000000 | Z95: 951000000 | AA95: 462000000 | AB95: 403000000 | AC95: 366000000 | AD95: 189000000 | AE95: 202000000 | AF95: 36000000 | AG95: 561000000 | AH95: 1248000000 | AI95: 907000000 | AJ95: 487000000 | AK95: 2146000000 | AL95: 892000000 | AM95: 1227000000 | AN95: 874000000 | AO95: 380000000 | AP95: 807000000 | AQ95: 1717000000 | AR95: 837000000 | AS95: 731000000 | AT95: 793000000 | AU95: 402000000 | AV95: 2164000000 | AW95: 1098000000 | AX95: 406000000 | AY95: 719000000 | AZ95: 1665000000 | BA95: 482000000 | BB95: 1216000000 | BC95: 630000000 | BD95: 70000000 | BE95: 19000000 | BF95: 28000000 | BG95: 204000000 | BH95: 728000000 | BI95: 302000000 | BJ95: 51000000 | BK95: 39000000 | BL95: 93000000 | BM95: 92000000 | BN95: 231000000 | BO95: 441000000 | BP95: 404000000 | BQ95: 631000000 | BR95: 574000000
A96: Grenada | B96: GRD | C96: Arms imports (SIPRI trend indicator values) | D96: MS.MIL.MPRT.KD | AA96: 1000000
A97: Greenland | B97: GRL | C97: Arms imports (SIPRI trend indicator values) | D97: MS.MIL.MPRT.KD
A98: Guatemala | B98: GTM | C98: Arms imports (SIPRI trend indicator values) | D98: MS.MIL.MPRT.KD | E98: 16000000 | G98: 1000000 | H98: 7000000 | I98: 8000000 | J98: 5000000 | L98: 1000000 | M98: 16000000 | N98: 1000000 | P98: 46000000 | Q98: 1000000 | R98: 0 | S98: 15000000 | T98: 47000000 | U98: 15000000 | V98: 1000000 | W98: 1000000 | X98: 5000000 | Y98: 8000000 | Z98: 49000000 | AA98: 16000000 | AB98: 1000000 | AC98: 7000000 | AD98: 25000000 | AE98: 2000000 | AH98: 4000000 | AL98: 13000000 | AM98: 4000000 | AN98: 4000000 | AO98: 2000000 | AQ98: 1000000 | BA98: 0 | BE98: 2000000 | BH98: 33000000 | BK98: 4000000 | BL98: 14000000 | BO98: 10000000 | BP98: 6000000
A99: Guam | B99: GUM | C99: Arms imports (SIPRI trend indicator values) | D99: MS.MIL.MPRT.KD
A100: Guyana | B100: GUY | C100: Arms imports (SIPRI trend indicator values) | D100: MS.MIL.MPRT.KD | M100: 0 | P100: 2000000 | S100: 3000000 | T100: 0 | U100: 16000000 | V100: 5000000 | W100: 1000000 | X100: 5000000 | Y100: 4000000 | Z100: 14000000 | AB100: 3000000 | AC100: 7000000 | AD100: 23000000 | AT100: 7000000 | AU100: 3000000 | AW100: 0 | BA100: 0 | BK100: 0 | BL100: 2000000 | BN100: 5000000 | BP100: 5000000 | BQ100: 9000000 | BR100: 5000000
A101: High income | B101: HIC | C101: Arms imports (SIPRI trend indicator values) | D101: MS.MIL.MPRT.KD | E101: 9293000000 | F101: 9081000000 | G101: 9338000000 | H101: 12681000000 | I101: 18042000000 | J101: 15863000000 | K101: 12128000000 | L101: 10950000000 | M101: 11682000000 | N101: 14586000000 | O101: 11035000000 | P101: 14034000000 | Q101: 12075000000 | R101: 13052000000 | S101: 13712000000 | T101: 14853000000 | U101: 15431000000 | V101: 14142000000 | W101: 15771000000 | X101: 13042000000 | Y101: 15195000000 | Z101: 17475000000 | AA101: 15829000000 | AB101: 16113000000 | AC101: 14629000000 | AD101: 13676000000 | AE101: 17141000000 | AF101: 15917000000 | AG101: 16541000000 | AH101: 16776000000 | AI101: 15614000000 | AJ101: 16286000000 | AK101: 16043000000 | AL101: 15982000000 | AM101: 12433000000 | AN101: 12910000000 | AO101: 14206000000 | AP101: 17866000000 | AQ101: 19894000000 | AR101: 14619000000 | AS101: 11125000000 | AT101: 8465000000 | AU101: 7264000000 | AV101: 9560000000 | AW101: 10895000000 | AX101: 10890000000 | AY101: 13689000000 | AZ101: 14355000000 | BA101: 12488000000 | BB101: 12154000000 | BC101: 12201000000 | BD101: 11949000000 | BE101: 9850000000 | BF101: 10472000000 | BG101: 11687000000 | BH101: 13456000000 | BI101: 12853000000 | BJ101: 14394000000 | BK101: 12569000000 | BL101: 14458000000 | BM101: 13607000000 | BN101: 15588000000 | BO101: 19835000000 | BP101: 15014000000 | BQ101: 17932000000 | BR101: 20569000000
A102: Hong Kong SAR, China | B102: HKG | C102: Arms imports (SIPRI trend indicator values) | D102: MS.MIL.MPRT.KD
...

Sheet Exports_Raw
A1: Data Source | B1: World Development Indicators
A3: Last Updated Date | B3: 46303
A5: Country Name | B5: Country Code | C5: Indicator Name | D5: Indicator Code | E5: 1960 | F5: 1961 | G5: 1962 | H5: 1963 | I5: 1964 | J5: 1965 | K5: 1966 | L5: 1967 | M5: 1968 | N5: 1969 | O5: 1970 | P5: 1971 | Q5: 1972 | R5: 1973 | S5: 1974 | T5: 1975 | U5: 1976 | V5: 1977 | W5: 1978 | X5: 1979 | Y5: 1980 | Z5: 1981 | AA5: 1982 | AB5: 1983 | AC5: 1984 | AD5: 1985 | AE5: 1986 | AF5: 1987 | AG5: 1988 | AH5: 1989 | AI5: 1990 | AJ5: 1991 | AK5: 1992 | AL5: 1993 | AM5: 1994 | AN5: 1995 | AO5: 1996 | AP5: 1997 | AQ5: 1998 | AR5: 1999 | AS5: 2000 | AT5: 2001 | AU5: 2002 | AV5: 2003 | AW5: 2004 | AX5: 2005 | AY5: 2006 | AZ5: 2007 | BA5: 2008 | BB5: 2009 | BC5: 2010 | BD5: 2011 | BE5: 2012 | BF5: 2013 | BG5: 2014 | BH5: 2015 | BI5: 2016 | BJ5: 2017 | BK5: 2018 | BL5: 2019 | BM5: 2020 | BN5: 2021 | BO5: 2022 | BP5: 2023 | BQ5: 2024 | BR5: 2025
A6: Aruba | B6: ABW | C6: Arms exports (SIPRI trend indicator values) | D6: MS.MIL.XPRT.KD | AO6: 18000000
A7: Africa Eastern and Southern | B7: AFE | C7: Arms exports (SIPRI trend indicator values) | D7: MS.MIL.XPRT.KD | E7: 27000000 | F7: 33000000 | L7: 9000000 | M7: 9000000 | N7: 13000000 | O7: 2000000 | P7: 7000000 | Q7: 22000000 | R7: 1000000 | S7: 2000000 | T7: 29000000 | U7: 20000000 | Y7: 49000000 | Z7: 62000000 | AA7: 1000000 | AD7: 60000000 | AE7: 29000000 | AF7: 79000000 | AG7: 25000000 | AL7: 56000000 | AU7: 24000000
A8: Afghanistan | B8: AFG | C8: Arms exports (SIPRI trend indicator values) | D8: MS.MIL.XPRT.KD | AK8: 1000000
A9: Africa Western and Central | B9: AFW | C9: Arms exports (SIPRI trend indicator values) | D9: MS.MIL.XPRT.KD | L9: 1000000 | P9: 1000000 | R9: 1000000
A10: Angola | B10: AGO | C10: Arms exports (SIPRI trend indicator values) | D10: MS.MIL.XPRT.KD | X10: 3000000 | Y10: 0 | AU10: 2000000
A11: Albania | B11: ALB | C11: Arms exports (SIPRI trend indicator values) | D11: MS.MIL.XPRT.KD | BD11: 1000000
A12: Andorra | B12: AND | C12: Arms exports (SIPRI trend indicator values) | D12: MS.MIL.XPRT.KD
A13: Arab World | B13: ARB | C13: Arms exports (SIPRI trend indicator values) | D13: MS.MIL.XPRT.KD | E13: 3000000 | F13: 0 | G13: 9000000 | H13: 8000000 | I13: 1000000 | K13: 14000000 | L13: 24000000 | M13: 35000000 | N13: 21000000 | O13: 56000000 | Q13: 2000000 | U13: 4000000 | X13: 454000000 | Z13: 216000000 | AC13: 69000000 | BP13: 183000000
A14: United Arab Emirates | B14: ARE | C14: Arms exports (SIPRI trend indicator values) | D14: MS.MIL.XPRT.KD | S14: 8000000 | AB14: 14000000 | AE14: 22000000 | AF14: 2000000 | AI14: 2000000 | AN14: 28000000 | AO14: 6000000 | AP14: 37000000 | AW14: 3000000 | AX14: 15000000 | AY14: 17000000 | AZ14: 3000000 | BB14: 34000000 | BC14: 39000000 | BD14: 3000000 | BE14: 75000000 | BF14: 115000000 | BG14: 100000000 | BH14: 143000000 | BI14: 111000000 | BJ14: 106000000 | BK14: 120000000 | BL14: 131000000 | BM14: 209000000 | BN14: 57000000 | BO14: 17000000 | BP14: 64000000 | BQ14: 119000000 | BR14: 33000000
A15: Argentina | B15: ARG | C15: Arms exports (SIPRI trend indicator values) | D15: MS.MIL.XPRT.KD | G15: 6000000 | I15: 4000000 | L15: 0 | M15: 8000000 | O15: 0 | Q15: 11000000 | U15: 1000000 | X15: 8000000 | Y15: 1000000 | Z15: 31000000 | AA15: 7000000 | AB15: 5000000 | AF15: 4000000 | AG15: 0 | AI15: 6000000 | AJ15: 0 | AL15: 13000000 | AM15: 5000000 | AN15: 5000000 | AS15: 2000000 | AU15: 2000000 | AY15: 2000000 | BD15: 1000000
A16: Armenia | B16: ARM | C16: Arms exports (SIPRI trend indicator values) | D16: MS.MIL.XPRT.KD | AY16: 4000000
A17: American Samoa | B17: ASM | C17: Arms exports (SIPRI trend indicator values) | D17: MS.MIL.XPRT.KD
A18: Antigua and Barbuda | B18: ATG | C18: Arms exports (SIPRI trend indicator values) | D18: MS.MIL.XPRT.KD
A19: Australia | B19: AUS | C19: Arms exports (SIPRI trend indicator values) | D19: MS.MIL.XPRT.KD | F19: 2000000 | G19: 4000000 | N19: 26000000 | O19: 17000000 | P19: 36000000 | Q19: 6000000 | R19: 72000000 | S19: 92000000 | T19: 131000000 | U19: 113000000 | V19: 62000000 | W19: 21000000 | X19: 22000000 | Y19: 15000000 | Z19: 17000000 | AA19: 26000000 | AB19: 31000000 | AC19: 62000000 | AD19: 10000000 | AE19: 57000000 | AF19: 89000000 | AG19: 12000000 | AH19: 18000000 | AI19: 156000000 | AJ19: 84000000 | AL19: 30000000 | AM19: 24000000 | AN19: 36000000 | AO19: 10000000 | AP19: 14000000 | AQ19: 4000000 | AT19: 43000000 | AU19: 47000000 | AV19: 44000000 | AW19: 2000000 | AX19: 49000000 | AY19: 26000000 | AZ19: 53000000 | BA19: 57000000 | BB19: 86000000 | BC19: 137000000 | BD19: 143000000 | BE19: 45000000 | BF19: 54000000 | BG19: 94000000 | BH19: 79000000 | BI19: 136000000 | BJ19: 101000000 | BK19: 39000000 | BL19: 129000000 | BM19: 406000000 | BN19: 175000000 | BO19: 19000000 | BP19: 81000000 | BQ19: 73000000 | BR19: 108000000
A20: Austria | B20: AUT | C20: Arms exports (SIPRI trend indicator values) | D20: MS.MIL.XPRT.KD | L20: 1000000 | W20: 37000000 | X20: 126000000 | Y20: 54000000 | Z20: 70000000 | AA20: 61000000 | AB20: 58000000 | AC20: 60000000 | AD20: 248000000 | AE20: 40000000 | AF20: 30000000 | AG20: 12000000 | AH20: 12000000 | AI20: 30000000 | AJ20: 20000000 | AK20: 20000000 | AL20: 10000000 | AM20: 17000000 | AO20: 18000000 | AP20: 3000000 | AQ20: 29000000 | AR20: 23000000 | AS20: 23000000 | AT20: 17000000 | AU20: 83000000 | AV20: 2000000 | AW20: 3000000 | AX20: 3000000 | AY20: 62000000 | AZ20: 67000000 | BA20: 14000000 | BB20: 50000000 | BC20: 75000000 | BD20: 62000000 | BE20: 31000000 | BF20: 29000000 | BG20: 16000000 | BH20: 10000000 | BI20: 17000000 | BJ20: 22000000 | BK20: 8000000 | BL20: 3000000 | BM20: 10000000 | BN20: 3000000 | BO20: 3000000 | BP20: 4000000 | BQ20: 23000000 | BR20: 1000000
A21: Azerbaijan | B21: AZE | C21: Arms exports (SIPRI trend indicator values) | D21: MS.MIL.XPRT.KD | BP21: 2000000
A22: Burundi | B22: BDI | C22: Arms exports (SIPRI trend indicator values) | D22: MS.MIL.XPRT.KD
A23: Belgium | B23: BEL | C23: Arms exports (SIPRI trend indicator values) | D23: MS.MIL.XPRT.KD | E23: 3000000 | F23: 0 | G23: 2000000 | H23: 0 | I23: 0 | K23: 12000000 | N23: 5000000 | P23: 0 | X23: 3000000 | Z23: 19000000 | AA23: 41000000 | AB23: 89000000 | AC23: 115000000 | AD23: 4000000 | AE23: 19000000 | AG23: 18000000 | AH23: 36000000 | AI23: 1000000 | AJ23: 1000000 | AM23: 39000000 | AN23: 161000000 | AO23: 61000000 | AP23: 93000000 | AQ23: 46000000 | AR23: 62000000 | AS23: 46000000 | AT23: 37000000 | AU23: 32000000 | AV23: 15000000 | AW23: 47000000 | AX23: 160000000 | AY23: 59000000 | AZ23: 32000000 | BA23: 223000000 | BB23: 242000000 | BC23: 11000000 | BD23: 110000000 | BE23: 21000000 | BF23: 54000000 | BG23: 10000000 | BH23: 12000000 | BI23: 7000000 | BJ23: 17000000 | BK23: 21000000 | BL23: 50000000 | BM23: 19000000 | BN23: 99000000 | BO23: 129000000 | BP23: 41000000 | BQ23: 69000000 | BR23: 86000000
A24: Benin | B24: BEN | C24: Arms exports (SIPRI trend indicator values) | D24: MS.MIL.XPRT.KD
A25: Burkina Faso | B25: BFA | C25: Arms exports (SIPRI trend indicator values) | D25: MS.MIL.XPRT.KD
A26: Bangladesh | B26: BGD | C26: Arms exports (SIPRI trend indicator values) | D26: MS.MIL.XPRT.KD | AC26: 2000000
A27: Bulgaria | B27: BGR | C27: Arms exports (SIPRI trend indicator values) | D27: MS.MIL.XPRT.KD | AB27: 4000000 | AE27: 8000000 | AH27: 8000000 | AI27: 8000000 | AJ27: 44000000 | AK27: 60000000 | AL27: 28000000 | AM27: 56000000 | AN27: 1000000 | AO27: 21000000 | AP27: 8000000 | AQ27: 41000000 | AR27: 172000000 | AS27: 6000000 | AT27: 10000000 | AU27: 37000000 | AV27: 45000000 | AW27: 20000000 | AX27: 87000000 | AY27: 5000000 | AZ27: 9000000 | BA27: 4000000 | BB27: 16000000 | BC27: 4000000 | BD27: 2000000 | BE27: 22000000 | BF27: 23000000 | BG27: 23000000 | BH27: 81000000 | BI27: 83000000 | BJ27: 33000000 | BK27: 14000000 | BL27: 11000000 | BM27: 3000000 | BN27: 7000000 | BO27: 34000000 | BP27: 19000000 | BQ27: 33000000
A28: Bahrain | B28: BHR | C28: Arms exports (SIPRI trend indicator values) | D28: MS.MIL.XPRT.KD | AT28: 2000000
A29: Bahamas, The | B29: BHS | C29: Arms exports (SIPRI trend indicator values) | D29: MS.MIL.XPRT.KD | BH29: 0
A30: Bosnia and Herzegovina | B30: BIH | C30: Arms exports (SIPRI trend indicator values) | D30: MS.MIL.XPRT.KD | AU30: 9000000 | BC30: 0 | BD30: 14000000 | BF30: 3000000 | BO30: 2000000 | BP30: 7000000
A31: Belarus | B31: BLR | C31: Arms exports (SIPRI trend indicator values) | D31: MS.MIL.XPRT.KD | AL31: 8000000 | AN31: 7000000 | AO31: 129000000 | AP31: 402000000 | AQ31: 63000000 | AR31: 454000000 | AS31: 293000000 | AT31: 49000000 | AU31: 64000000 | AV31: 58000000 | AW31: 19000000 | AX31: 53000000 | AY31: 43000000 | AZ31: 5000000 | BA31: 224000000 | BB31: 41000000 | BC31: 161000000 | BD31: 98000000 | BE31: 97000000 | BF31: 269000000 | BG31: 101000000 | BH31: 142000000 | BI31: 152000000 | BJ31: 52000000 | BK31: 86000000 | BL31: 84000000 | BM31: 59000000 | BN31: 111000000 | BO31: 58000000 | BP31: 45000000 | BQ31: 65000000 | BR31: 1000000
A32: Belize | B32: BLZ | C32: Arms exports (SIPRI trend indicator values) | D32: MS.MIL.XPRT.KD
A33: Bermuda | B33: BMU | C33: Arms exports (SIPRI trend indicator values) | D33: MS.MIL.XPRT.KD
A34: Bolivia | B34: BOL | C34: Arms exports (SIPRI trend indicator values) | D34: MS.MIL.XPRT.KD
A35: Brazil | B35: BRA | C35: Arms exports (SIPRI trend indicator values) | D35: MS.MIL.XPRT.KD | E35: 2000000 | F35: 12000000 | N35: 18000000 | P35: 0 | S35: 12000000 | T35: 69000000 | U35: 76000000 | V35: 156000000 | W35: 204000000 | X35: 80000000 | Y35: 160000000 | Z35: 71000000 | AA35: 128000000 | AB35: 204000000 | AC35: 280000000 | AD35: 209000000 | AE35: 140000000 | AF35: 216000000 | AG35: 208000000 | AH35: 53000000 | AI35: 108000000 | AJ35: 129000000 | AK35: 99000000 | AL35: 40000000 | AM35: 54000000 | AN35: 38000000 | AO35: 27000000 | AP35: 27000000 | AQ35: 18000000 | AU35: 21000000 | AW35: 46000000 | AX35: 1000000 | AY35: 44000000 | AZ35: 54000000 | BA35: 93000000 | BB35: 44000000 | BC35: 147000000 | BD35: 32000000 | BE35: 33000000 | BF35: 31000000 | BG35: 31000000 | BH35: 53000000 | BI35: 134000000 | BJ35: 36000000 | BK35: 102000000 | BL35: 21000000 | BM35: 164000000 | BN35: 86000000 | BO35: 10000000 | BP35: 54000000 | BQ35: 112000000 | BR35: 153000000
A36: Barbados | B36: BRB | C36: Arms exports (SIPRI trend indicator values) | D36: MS.MIL.XPRT.KD
A37: Brunei Darussalam | B37: BRN | C37: Arms exports (SIPRI trend indicator values) | D37: MS.MIL.XPRT.KD | BD37: 24000000 | BI37: 12000000
A38: Bhutan | B38: BTN | C38: Arms exports (SIPRI trend indicator values) | D38: MS.MIL.XPRT.KD
A39: Botswana | B39: BWA | C39: Arms exports (SIPRI trend indicator values) | D39: MS.MIL.XPRT.KD
A40: Central African Republic | B40: CAF | C40: Arms exports (SIPRI trend indicator values) | D40: MS.MIL.XPRT.KD
A41: Canada | B41: CAN | C41: Arms exports (SIPRI trend indicator values) | D41: MS.MIL.XPRT.KD | E41: 66000000 | F41: 300000000 | G41: 188000000 | H41: 245000000 | I41: 273000000 | J41: 121000000 | K41: 112000000 | L41: 73000000 | M41: 198000000 | N41: 183000000 | O41: 198000000 | P41: 290000000 | Q41: 323000000 | R41: 118000000 | S41: 90000000 | T41: 59000000 | U41: 259000000 | V41: 138000000 | W41: 177000000 | X41: 163000000 | Y41: 116000000 | Z41: 105000000 | AA41: 237000000 | AB41: 97000000 | AC41: 77000000 | AD41: 83000000 | AE41: 240000000 | AF41: 250000000 | AG41: 124000000 | AH41: 33000000 | AI41: 79000000 | AJ41: 93000000 | AK41: 147000000 | AL41: 152000000 | AM41: 165000000 | AN41: 248000000 | AO41: 168000000 | AP41: 97000000 | AQ41: 39000000 | AR41: 80000000 | AS41: 69000000 | AT41: 124000000 | AU41: 177000000 | AV41: 302000000 | AW41: 289000000 | AX41: 234000000 | AY41: 254000000 | AZ41: 334000000 | BA41: 252000000 | BB41: 198000000 | BC41: 196000000 | BD41: 277000000 | BE41: 258000000 | BF41: 170000000 | BG41: 189000000 | BH41: 298000000 | BI41: 96000000 | BJ41: 63000000 | BK41: 108000000 | BL41: 223000000 | BM41: 123000000 | BN41: 144000000 | BO41: 147000000 | BP41: 276000000 | BQ41: 237000000 | BR41: 312000000
A42: Central Europe and the Baltics | B42: CEB | C42: Arms exports (SIPRI trend indicator values) | D42: MS.MIL.XPRT.KD | E42: 0 | G42: 7000000 | H42: 111000000 | I42: 237000000 | J42: 234000000 | K42: 337000000 | L42: 327000000 | M42: 325000000 | N42: 351000000 | O42: 268000000 | P42: 284000000 | Q42: 294000000 | R42: 212000000 | S42: 258000000 | V42: 404000000 | W42: 368000000 | X42: 291000000 | Y42: 284000000 | Z42: 431000000 | AA42: 325000000 | AB42: 244000000 | AE42: 302000000 | AH42: 53000000 | AI42: 127000000 | AJ42: 112000000 | AM42: 586000000 | AN42: 443000000 | AO42: 276000000 | AP42: 150000000 | AS42: 186000000 | AU42: 223000000 | AX42: 262000000 | AY42: 342000000 | AZ42: 269000000 | BF42: 469000000 | BO42: 1067000000 | BP42: 932000000 | BQ42: 562000000 | BR42: 338000000
A43: Switzerland | B43: CHE | C43: Arms exports (SIPRI trend indicator values) | D43: MS.MIL.XPRT.KD | E43: 435000000 | F43: 493000000 | G43: 534000000 | H43: 351000000 | I43: 394000000 | J43: 484000000 | K43: 367000000 | L43: 261000000 | M43: 88000000 | N43: 106000000 | O43: 18000000 | P43: 42000000 | Q43: 34000000 | R43: 54000000 | S43: 89000000 | T43: 484000000 | U43: 592000000 | V43: 339000000 | W43: 223000000 | X43: 488000000 | Y43: 566000000 | Z43: 559000000 | AA43: 413000000 | AB43: 331000000 | AC43: 529000000 | AD43: 347000000 | AE43: 340000000 | AF43: 319000000 | AG43: 375000000 | AH43: 318000000 | AI43: 475000000 | AJ43: 508000000 | AK43: 457000000 | AL43: 232000000 | AM43: 176000000 | AN43: 144000000 | AO43: 204000000 | AP43: 131000000 | AQ43: 198000000 | AR43: 227000000 | AS43: 140000000 | AT43: 219000000 | AU43: 178000000 | AV43: 207000000 | AW43: 293000000 | AX43: 274000000 | AY43: 320000000 | AZ43: 325000000 | BA43: 506000000 | BB43: 260000000 | BC43: 285000000 | BD43: 349000000 | BE43: 257000000 | BF43: 213000000 | BG43: 352000000 | BH43: 491000000 | BI43: 220000000 | BJ43: 175000000 | BK43: 244000000 | BL43: 222000000 | BM43: 145000000 | BN43: 107000000 | BO43: 181000000 | BP43: 63000000 | BQ43: 11000000 | BR43: 129000000
A44: Channel Islands | B44: CHI | C44: Arms exports (SIPRI trend indicator values) | D44: MS.MIL.XPRT.KD
A45: Chile | B45: CHL | C45: Arms exports (SIPRI trend indicator values) | D45: MS.MIL.XPRT.KD | T45: 0 | W45: 0 | Y45: 0 | Z45: 0 | AB45: 0 | AE45: 3000000 | AF45: 3000000 | AG45: 4000000 | AH45: 4000000 | AJ45: 3000000 | AK45: 8000000 | AQ45: 2000000 | AR45: 1000000 | AS45: 1000000 | AU45: 1000000 | BA45: 100000000 | BG45: 20000000 | BK45: 0 | BO45: 8000000
A46: China | B46: CHN | C46: Arms exports (SIPRI trend indicator values) | D46: MS.MIL.XPRT.KD | E46: 285000000 | F46: 35000000 | G46: 47000000 | H46: 12000000 | I46: 75000000 | J46: 387000000 | K46: 628000000 | L46: 426000000 | M46: 746000000 | N46: 669000000 | O46: 905000000 | P46: 1308000000 | Q46: 1246000000 | R46: 658000000 | S46: 508000000 | T46: 661000000 | U46: 580000000 | V46: 224000000 | W46: 611000000 | X46: 553000000 | Y46: 943000000 | Z46: 707000000 | AA46: 1557000000 | AB46: 1761000000 | AC46: 1935000000 | AD46: 1292000000 | AE46: 1861000000 | AF46: 2600000000 | AG46: 1426000000 | AH46: 1056000000 | AI46: 955000000 | AJ46: 1324000000 | AK46: 672000000 | AL46: 1437000000 | AM46: 1063000000 | AN46: 981000000 | AO46: 764000000 | AP46: 427000000 | AQ46: 349000000 | AR46: 334000000 | AS46: 309000000 | AT46: 510000000 | AU46: 524000000 | AV46: 701000000 | AW46: 408000000 | AX46: 341000000 | AY46: 769000000 | AZ46: 520000000 | BA46: 598000000 | BB46: 1138000000 | BC46: 1531000000 | BD46: 1308000000 | BE46: 1499000000 | BF46: 2100000000 | BG46: 1353000000 | BH46: 1841000000 | BI46: 2480000000 | BJ46: 1643000000 | BK46: 1391000000 | BL46: 1601000000 | BM46: 645000000 | BN46: 1342000000 | BO46: 2323000000 | BP46: 2745000000 | BQ46: 1294000000 | BR46: 880000000
A47: Cote d'Ivoire | B47: CIV | C47: Arms exports (SIPRI trend indicator values) | D47: MS.MIL.XPRT.KD | P47: 1000000
A48: Cameroon | B48: CMR | C48: Arms exports (SIPRI trend indicator values) | D48: MS.MIL.XPRT.KD
A49: Congo, Dem. Rep. | B49: COD | C49: Arms exports (SIPRI trend indicator values) | D49: MS.MIL.XPRT.KD | X49: 1000000 | AP49: 22000000
A50: Congo, Rep. | B50: COG | C50: Arms exports (SIPRI trend indicator values) | D50: MS.MIL.XPRT.KD
A51: Colombia | B51: COL | C51: Arms exports (SIPRI trend indicator values) | D51: MS.MIL.XPRT.KD | AU51: 6000000 | BE51: 0 | BJ51: 10000000 | BL51: 10000000 | BM51: 4000000
A52: Comoros | B52: COM | C52: Arms exports (SIPRI trend indicator values) | D52: MS.MIL.XPRT.KD | Z52: 5000000
A53: Cabo Verde | B53: CPV | C53: Arms exports (SIPRI trend indicator values) | D53: MS.MIL.XPRT.KD
A54: Costa Rica | B54: CRI | C54: Arms exports (SIPRI trend indicator values) | D54: MS.MIL.XPRT.KD | N54: 2000000 | BA54: 0 | BB54: 3000000
A55: Caribbean small states | B55: CSS | C55: Arms exports (SIPRI trend indicator values) | D55: MS.MIL.XPRT.KD
A56: Cuba | B56: CUB | C56: Arms exports (SIPRI trend indicator values) | D56: MS.MIL.XPRT.KD | T56: 1000000 | W56: 12000000 | X56: 10000000 | Y56: 8000000
A57: Curacao | B57: CUW | C57: Arms exports (SIPRI trend indicator values) | D57: MS.MIL.XPRT.KD
A58: Cayman Islands | B58: CYM | C58: Arms exports (SIPRI trend indicator values) | D58: MS.MIL.XPRT.KD
A59: Cyprus | B59: CYP | C59: Arms exports (SIPRI trend indicator values) | D59: MS.MIL.XPRT.KD | AO59: 34000000 | BP59: 40000000
A60: Czechia | B60: CZE | C60: Arms exports (SIPRI trend indicator values) | D60: MS.MIL.XPRT.KD | AL60: 199000000 | AM60: 319000000 | AN60: 146000000 | AO60: 123000000 | AP60: 24000000 | AQ60: 21000000 | AR60: 58000000 | AS60: 83000000 | AT60: 89000000 | AU60: 60000000 | AV60: 65000000 | AW60: 2000000 | AX60: 72000000 | AY60: 44000000 | AZ60: 34000000 | BA60: 34000000 | BB60: 24000000 | BC60: 5000000 | BD60: 10000000 | BE60: 8000000 | BF60: 41000000 | BG60: 26000000 | BH60: 151000000 | BI60: 153000000 | BJ60: 89000000 | BK60: 92000000 | BL60: 19000000 | BM60: 26000000 | BN60: 6000000 | BO60: 168000000 | BP60: 113000000 | BQ60: 189000000 | BR60: 137000000
A61: Germany | B61: DEU | C61: Arms exports (SIPRI trend indicator values) | D61: MS.MIL.XPRT.KD | E61: 156000000 | F61: 12000000 | G61: 146000000 | H61: 133000000 | I61: 437000000 | J61: 327000000 | K61: 711000000 | L61: 758000000 | M61: 588000000 | N61: 882000000 | O61: 1584000000 | P61: 1356000000 | Q61: 1359000000 | R61: 222000000 | S61: 1187000000 | T61: 1424000000 | U61: 1656000000 | V61: 1925000000 | W61: 1603000000 | X61: 1427000000 | Y61: 1597000000 | Z61: 1903000000 | AA61: 1510000000 | AB61: 2213000000 | AC61: 2929000000 | AD61: 1327000000 | AE61: 1349000000 | AF61: 908000000 | AG61: 1383000000 | AH61: 1258000000 | AI61: 1820000000 | AJ61: 2407000000 | AK61: 1517000000 | AL61: 1545000000 | AM61: 2908000000 | AN61: 1525000000 | AO61: 1949000000 | AP61: 951000000 | AQ61: 1840000000 | AR61: 1937000000 | AS61: 1672000000 | AT61: 851000000 | AU61: 889000000 | AV61: 1632000000 | AW61: 1090000000 | AX61: 2083000000 | AY61: 2482000000 | AZ61: 3291000000 | BA61: 2378000000 | BB61: 2207000000 | BC61: 2364000000 | BD61: 1203000000 | BE61: 715000000 | BF61: 721000000 | BG61: 1830000000 | BH61: 1823000000 | BI61: 2512000000 | BJ61: 1826000000 | BK61: 1098000000 | BL61: 978000000 | BM61: 1153000000 | BN61: 852000000 | BO61: 1508000000 | BP61: 2547000000 | BQ61: 2108000000 | BR61: 1696000000
A62: Djibouti | B62: DJI | C62: Arms exports (SIPRI trend indicator values) | D62: MS.MIL.XPRT.KD
A63: Dominica | B63: DMA | C63: Arms exports (SIPRI trend indicator values) | D63: MS.MIL.XPRT.KD
A64: Denmark | B64: DNK | C64: Arms exports (SIPRI trend indicator values) | D64: MS.MIL.XPRT.KD | E64: 20000000 | I64: 60000000 | J64: 12000000 | L64: 128000000 | M64: 24000000 | T64: 24000000 | Y64: 18000000 | Z64: 29000000 | AA64: 64000000 | AB64: 115000000 | AF64: 117000000 | AG64: 36000000 | AI64: 80000000 | AL64: 182000000 | AM64: 268000000 | AN64: 34000000 | AO64: 13000000 | AR64: 3000000 | AS64: 18000000 | AU64: 10000000 | AV64: 2000000 | AY64: 5000000 | AZ64: 6000000 | BA64: 8000000 | BB64: 10000000 | BC64: 8000000 | BD64: 26000000 | BE64: 26000000 | BF64: 8000000 | BG64: 19000000 | BH64: 22000000 | BI64: 21000000 | BJ64: 13000000 | BK64: 25000000 | BL64: 2000000 | BN64: 29000000 | BO64: 83000000 | BP64: 46000000 | BQ64: 189000000 | BR64: 165000000
A65: Dominican Republic | B65: DOM | C65: Arms exports (SIPRI trend indicator values) | D65: MS.MIL.XPRT.KD | BJ65: 4000000 | BO65: 0
A66: Algeria | B66: DZA | C66: Arms exports (SIPRI trend indicator values) | D66: MS.MIL.XPRT.KD | M66: 6000000 | Y66: 6000000 | AB66: 12000000 | AC66: 12000000
A67: East Asia & Pacific (excluding high income) | B67: EAP | C67: Arms exports (SIPRI trend indicator values) | D67: MS.MIL.XPRT.KD | E67: 285000000 | F67: 35000000 | G67: 47000000 | H67: 19000000 | I67: 75000000 | J67: 387000000 | K67: 628000000 | L67: 426000000 | M67: 746000000 | N67: 669000000 | O67: 917000000 | AN67: 1041000000 | AR67: 441000000 | AV67: 837000000 | AW67: 484000000 | AX67: 365000000 | AY67: 886000000 | AZ67: 539000000 | BA67: 614000000 | BB67: 1161000000 | BC67: 1538000000 | BD67: 1312000000 | BE67: 1499000000 | BF67: 2115000000 | BG67: 1369000000 | BH67: 1841000000 | BI67: 2567000000 | BJ67: 1741000000 | BK67: 1416000000 | BL67: 1613000000 | BM67: 645000000 | BN67: 1364000000 | BO67: 2323000000 | BP67: 2754000000 | BQ67: 1540000000 | BR67: 924000000
A68: Early-demographic dividend | B68: EAR | C68: Arms exports (SIPRI trend indicator values) | D68: MS.MIL.XPRT.KD | E68: 27000000 | F68: 33000000 | L68: 106000000 | M68: 108000000 | N68: 92000000 | Q68: 178000000
A69: East Asia & Pacific | B69: EAS | C69: Arms exports (SIPRI trend indicator values) | D69: MS.MIL.XPRT.KD | E69: 286000000 | F69: 98000000 | G69: 151000000 | H69: 27000000 | I69: 89000000 | L69: 439000000 | X69: 784000000 | AH69: 1331000000 | AI69: 1269000000 | AO69: 1003000000 | AP69: 581000000 | BI69: 3235000000 | BJ69: 2546000000 | BN69: 2150000000 | BP69: 3554000000 | BR69: 3163000000
A70: Europe & Central Asia (excluding high income) | B70: ECA | C70: Arms exports (SIPRI trend indicator values) | D70: MS.MIL.XPRT.KD | Y70: 23000000 | Z70: 11000000 | AN70: 249000000 | AO70: 387000000 | AP70: 1200000000 | AQ70: 782000000 | AR70: 1666000000 | AS70: 1831000000 | AT70: 684000000 | AU70: 557000000 | AV70: 773000000 | AW70: 393000000 | AX70: 400000000 | AY70: 751000000 | AZ70: 884000000 | BA70: 832000000 | BB70: 792000000 | BC70: 1017000000 | BD70: 1002000000 | BE70: 1758000000 | BF70: 1116000000 | BG70: 909000000 | BH70: 789000000 | BI70: 1038000000 | BJ70: 646000000 | BK70: 682000000 | BL70: 558000000 | BM70: 498000000 | BN70: 841000000 | BP70: 840000000 | BR70: 733000000
A71: Europe & Central Asia | B71: ECS | C71: Arms exports (SIPRI trend indicator values) | D71: MS.MIL.XPRT.KD | E71: 3963000000 | F71: 3172000000 | G71: 3093000000 | H71: 3531000000 | I71: 4770000000 | J71: 4358000000 | K71: 5360000000 | L71: 5467000000 | M71: 4945000000 | N71: 5034000000 | O71: 5137000000 | P71: 7663000000 | Q71: 7722000000 | R71: 6833000000 | S71: 6686000000 | T71: 7976000000 | U71: 8224000000 | V71: 8655000000 | W71: 8901000000 | X71: 8884000000 | Y71: 10024000000 | Z71: 12066000000 | AA71: 11500000000 | AB71: 11091000000 | AC71: 11426000000 | AD71: 9687000000 | AE71: 8124000000 | AF71: 8557000000 | AG71: 8443000000 | AH71: 9089000000 | AI71: 7217000000 | AJ71: 6990000000 | AK71: 8235000000 | AL71: 9413000000 | AM71: 9468000000 | AN71: 9926000000 | AO71: 11289000000 | AP71: 13327000000 | AQ71: 11188000000 | AR71: 13088000000 | AS71: 11901000000 | AT71: 11383000000 | AU71: 11162000000 | AV71: 11668000000 | AW71: 12565000000 | AX71: 13079000000 | AY71: 14825000000 | AZ71: 16544000000 | BA71: 15106000000 | BB71: 14299000000 | BC71: 14002000000 | BD71: 17938000000 | BE71: 15958000000 | BF71: 16194000000 | BG71: 14916000000 | BH71: 15059000000 | BI71: 16524000000 | BJ71: 15643000000 | BK71: 13921000000 | BL71: 13048000000 | BM71: 11175000000 | BN71: 11929000000 | BO71: 14609000000 | BP71: 12816000000 | BQ71: 12104000000 | BR71: 12815000000
A72: Ecuador | B72: ECU | C72: Arms exports (SIPRI trend indicator values) | D72: MS.MIL.XPRT.KD | BG72: 6000000 | BK72: 2000000
A73: Egypt, Arab Rep. | B73: EGY | C73: Arms exports (SIPRI trend indicator values) | D73: MS.MIL.XPRT.KD | E73: 0 | F73: 0 | G73: 7000000 | H73: 8000000 | I73: 1000000 | K73: 14000000 | L73: 15000000 | M73: 26000000 | N73: 15000000 | O73: 39000000 | T73: 16000000 | V73: 51000000 | W73: 78000000 | X73: 32000000 | Y73: 29000000 | Z73: 71000000 | AA73: 81000000 | AB73: 71000000 | AC73: 37000000 | AD73: 5000000 | AE73: 19000000 | AF73: 76000000 | AG73: 81000000 | AH73: 81000000 | AI73: 25000000 | AK73: 15000000 | AL73: 28000000 | AM73: 17000000 | AN73: 12000000 | AO73: 5000000 | AP73: 5000000 | BG73: 7000000 | BH73: 21000000 | BL73: 8000000 | BN73: 41000000 | BO73: 41000000 | BP73: 4000000 | BQ73: 2000000
A74: Euro area | B74: EMU | C74: Arms exports (SIPRI trend indicator values) | D74: MS.MIL.XPRT.KD | E74: 1245000000 | F74: 1232000000 | G74: 1406000000 | H74: 1757000000 | I74: 2510000000 | J74: 2033000000 | K74: 3099000000 | L74: 2653000000 | M74: 2692000000 | N74: 2886000000 | O74: 3711000000 | P74: 4440000000 | Q74: 4518000000 | R74: 3751000000 | S74: 4015000000 | T74: 4841000000 | U74: 4578000000 | V74: 5636000000 | W74: 5962000000 | X74: 6166000000 | Y74: 7289000000 | Z74: 8315000000 | AA74: 8014000000 | AB74: 7715000000 | AC74: 7876000000 | AD74: 6711000000 | AE74: 5156000000 | AF74: 3975000000 | AG74: 4675000000 | AH74: 4695000000 | AI74: 4390000000 | AJ74: 4568000000 | AK74: 3569000000 | AL74: 3659000000 | AM74: 5054000000 | AN74: 3628000000 | AO74: 4897000000 | AP74: 5992000000 | AQ74: 6329000000 | AR74: 4940000000 | AS74: 3307000000 | AT74: 2785000000 | AU74: 3212000000 | AV74: 3872000000 | AW74: 3900000000 | AX74: 5499000000 | AY74: 6878000000 | AZ74: 8236000000 | BA74: 6255000000 | BB74: 6519000000 | BC74: 4673000000 | BD74: 6029000000 | BE74: 4242000000 | BF74: 4536000000 | BG74: 6088000000 | BH74: 6332000000 | BI74: 6659000000 | BJ74: 7040000000 | BK74: 4834000000 | BL74: 5829000000 | BM74: 5871000000 | BN74: 7567000000 | BO74: 8135000000 | BP74: 7644000000 | BQ74: 7045000000 | BR74: 8167000000
A75: Eritrea | B75: ERI | C75: Arms exports (SIPRI trend indicator values) | D75: MS.MIL.XPRT.KD | AQ75: 2000000 | AR75: 0 | AY75: 0
A76: Spain | B76: ESP | C76: Arms exports (SIPRI trend indicator values) | D76: MS.MIL.XPRT.KD | E76: 2000000 | F76: 8000000 | G76: 10000000 | H76: 10000000 | I76: 12000000 | J76: 33000000 | K76: 26000000 | L76: 12000000 | M76: 12000000 | N76: 10000000 | O76: 70000000 | P76: 140000000 | Q76: 18000000 | R76: 18000000 | S76: 82000000 | T76: 272000000 | U76: 46000000 | V76: 25000000 | W76: 38000000 | X76: 18000000 | Y76: 10000000 | Z76: 135000000 | AA76: 263000000 | AB76: 367000000 | AC76: 244000000 | AD76: 92000000 | AE76: 197000000 | AF76: 152000000 | AG76: 136000000 | AH76: 167000000 | AI76: 116000000 | AJ76: 103000000 | AK76: 70000000 | AL76: 103000000 | AM76: 253000000 | AN76: 88000000 | AO76: 112000000 | AP76: 605000000 | AQ76: 174000000 | AR76: 46000000 | AS76: 47000000 | AT76: 8000000 | AU76: 18000000 | AV76: 99000000 | AW76: 54000000 | AX76: 113000000 | AY76: 898000000 | AZ76: 628000000 | BA76: 626000000 | BB76: 984000000 | BC76: 273000000 | BD76: 997000000 | BE76: 266000000 | BF76: 450000000 | BG76: 962000000 | BH76: 982000000 | BI76: 481000000 | BJ76: 820000000 | BK76: 705000000 | BL76: 318000000 | BM76: 1005000000 | BN76: 676000000 | BO76: 1014000000 | BP76: 912000000 | BQ76: 606000000 | BR76: 341000000
A77: Estonia | B77: EST | C77: Arms exports (SIPRI trend indicator values) | D77: MS.MIL.XPRT.KD | AO77: 8000000 | BH77: 1000000 | BO77: 9000000 | BP77: 13000000 | BQ77: 2000000
A78: Ethiopia | B78: ETH | C78: Arms exports (SIPRI trend indicator values) | D78: MS.MIL.XPRT.KD | AD78: 35000000 | AF78: 51000000 | AP78: 17000000
A79: European Union | B79: EUU | C79: Arms exports (SIPRI trend indicator values) | D79: MS.MIL.XPRT.KD | E79: 1303000000 | F79: 1278000000 | G79: 1457000000 | H79: 1881000000 | I79: 2829000000 | J79: 2311000000 | K79: 3492000000 | L79: 3163000000 | M79: 3101000000 | N79: 3273000000 | O79: 4137000000 | P79: 5271000000 | Q79: 4975000000 | R79: 3978000000 | S79: 4348000000 | T79: 5258000000 | U79: 5104000000 | V79: 6115000000 | W79: 6385000000 | X79: 6718000000 | Y79: 7748000000 | Z79: 8902000000 | AA79: 8523000000 | AB79: 8188000000 | AC79: 8368000000 | AD79: 7156000000 | AE79: 5770000000 | AF79: 4581000000 | AG79: 5507000000 | AH79: 5141000000 | AI79: 4813000000 | AJ79: 4791000000 | AK79: 3788000000 | AL79: 4180000000 | AM79: 5914000000 | AN79: 4230000000 | AO79: 5439000000 | AP79: 6175000000 | AQ79: 6685000000 | AR79: 5468000000 | AS79: 3813000000 | AT79: 3847000000 | AU79: 3536000000 | AV79: 4562000000 | AW79: 4246000000 | AX79: 6210000000 | AY79: 7601000000 | AZ79: 8812000000 | BA79: 6831000000 | BB79: 7019000000 | BC79: 5327000000 | BD79: 6731000000 | BE79: 4743000000 | BF79: 5372000000 | BG79: 6506000000 | BH79: 6685000000 | BI79: 7086000000 | BJ79: 7225000000 | BK79: 5097000000 | BL79: 5981000000 | BM79: 6160000000 | BN79: 7843000000 | BO79: 9177000000 | BP79: 8753000000 | BQ79: 8107000000 | BR79: 8895000000
A80: Fragility, Conflict, and Violence (FCV) situations | B80: FCV | C80: Arms exports (SIPRI trend indicator values) | D80: MS.MIL.XPRT.KD | E80: 3000000 | G80: 3000000 | L80: 30000000 | O80: 40000000 | P80: 6000000 | Q80: 106000000 | AA80: 348000000 | AB80: 111000000 | AH80: 30000000 | AI80: 39000000 | AO80: 226000000 | AP80: 615000000 | AS80: 1424000000
A81: Finland | B81: FIN | C81: Arms exports (SIPRI trend indicator values) | D81: MS.MIL.XPRT.KD | E81: 75000000 | F81: 5000000 | G81: 5000000 | J81: 3000000 | K81: 67000000 | L81: 39000000 | M81: 39000000 | N81: 39000000 | O81: 37000000 | P81: 40000000 | Q81: 30000000 | S81: 63000000 | T81: 63000000 | W81: 63000000 | X81: 63000000 | AA81: 15000000 | AG81: 1000000 | AJ81: 18000000 | AK81: 9000000 | AL81: 12000000 | AM81: 20000000 | AN81: 25000000 | AO81: 3000000 | AP81: 1000000 | AQ81: 17000000 | AR81: 18000000 | AS81: 12000000 | AT81: 29000000 | AU81: 35000000 | AV81: 35000000 | AW81: 28000000 | AX81: 41000000 | AY81: 124000000 | AZ81: 63000000 | BA81: 100000000 | BB81: 68000000 | BC81: 73000000 | BD81: 70000000 | BE81: 105000000 | BF81: 76000000 | BG81: 104000000 | BH81: 29000000 | BI81: 61000000 | BJ81: 32000000 | BK81: 43000000 | BL81: 29000000 | BM81: 16000000 | BN81: 18000000 | BO81: 42000000 | BP81: 51000000 | BQ81: 20000000 | BR81: 115000000
A82: Fiji | B82: FJI | C82: Arms exports (SIPRI trend indicator values) | D82: MS.MIL.XPRT.KD | AC82: 10000000
A83: France | B83: FRA | C83: Arms exports (SIPRI trend indicator values) | D83: MS.MIL.XPRT.KD | E83: 866000000 | F83: 856000000 | G83: 912000000 | H83: 1330000000 | I83: 1574000000 | J83: 1333000000 | K83: 1896000000 | L83: 1602000000 | M83: 1504000000 | N83: 1518000000 | O83: 1735000000 | P83: 2363000000 | Q83: 2694000000 | R83: 2974000000 | S83: 2180000000 | T83: 2321000000 | U83: 2039000000 | V83: 2737000000 | W83: 3317000000 | X83: 2970000000 | Y83: 3851000000 | Z83: 3683000000 | AA83: 3789000000 | AB83: 3414000000 | AC83: 2932000000 | AD83: 3992000000 | AE83: 2962000000 | AF83: 1752000000 | AG83: 1960000000 | AH83: 2269000000 | AI83: 1799000000 | AJ83: 1166000000 | AK83: 1246000000 | AL83: 971000000 | AM83: 858000000 | AN83: 969000000 | AO83: 1839000000 | AP83: 3176000000 | AQ83: 3098000000 | AR83: 1683000000 | AS83: 966000000 | AT83: 1311000000 | AU83: 1375000000 | AV83: 1348000000 | AW83: 2117000000 | AX83: 1645000000 | AY83: 1484000000 | AZ83: 2145000000 | BA83: 1872000000 | BB83: 1845000000 | BC83: 888000000 | BD83: 2079000000 | BE83: 1338000000 | BF83: 1870000000 | BG83: 1763000000 | BH83: 2229000000 | BI83: 2193000000 | BJ83: 2336000000 | BK83: 1867000000 | BL83: 3753000000 | BM83: 2290000000 | BN83: 3904000000 | BO83: 3156000000 | BP83: 2175000000 | BQ83: 2472000000 | BR83: 3367000000
A84: Faroe Islands | B84: FRO | C84: Arms exports (SIPRI trend indicator values) | D84: MS.MIL.XPRT.KD
A85: Micronesia, Fed. Sts. | B85: FSM | C85: Arms exports (SIPRI trend indicator values) | D85: MS.MIL.XPRT.KD
A86: Gabon | B86: GAB | C86: Arms exports (SIPRI trend indicator values) | D86: MS.MIL.XPRT.KD | R86: 1000000
A87: United Kingdom | B87: GBR | C87: Arms exports (SIPRI trend indicator values) | D87: MS.MIL.XPRT.KD | E87: 2187000000 | F87: 1401000000 | G87: 1065000000 | H87: 1244000000 | I87: 1408000000 | J87: 1498000000 | K87: 1421000000 | L87: 1879000000 | M87: 1679000000 | N87: 1615000000 | O87: 982000000 | P87: 2346000000 | Q87: 2684000000 | R87: 2791000000 | S87: 2249000000 | T87: 2228000000 | U87: 2522000000 | V87: 2195000000 | W87: 2206000000 | X87: 1543000000 | Y87: 1566000000 | Z87: 2356000000 | AA87: 2515000000 | AB87: 2537000000 | AC87: 2529000000 | AD87: 2142000000 | AE87: 1985000000 | AF87: 3603000000 | AG87: 2527000000 | AH87: 3503000000 | AI87: 1844000000 | AJ87: 1525000000 | AK87: 1093000000 | AL87: 1381000000 | AM87: 1526000000 | AN87: 1460000000 | AO87: 1616000000 | AP87: 2363000000 | AQ87: 1400000000 | AR87: 1315000000 | AS87: 1619000000 | AT87: 1352000000 | AU87: 1078000000 | AV87: 769000000 | AW87: 1231000000 | AX87: 990000000 | AY87: 957000000 | AZ87: 924000000 | BA87: 931000000 | BB87: 1071000000 | BC87: 1146000000 | BD87: 1001000000 | BE87: 813000000 | BF87: 1509000000 | BG87: 1658000000 | BH87: 1183000000 | BI87: 1344000000 | BJ87: 1104000000 | BK87: 682000000 | BL87: 886000000 | BM87: 652000000 | BN87: 639000000 | BO87: 1740000000 | BP87: 1320000000 | BQ87: 884000000 | BR87: 702000000
A88: Georgia | B88: GEO | C88: Arms exports (SIPRI trend indicator values) | D88: MS.MIL.XPRT.KD | AR88: 46000000 | AS88: 69000000 | AU88: 69000000 | AW88: 16000000 | BI88: 6000000 | BJ88: 7000000
A89: Ghana | B89: GHA | C89: Arms exports (SIPRI trend indicator values) | D89: MS.MIL.XPRT.KD | X89: 6000000 | AX89: 19000000
A90: Gibraltar | B90: GIB | C90: Arms exports (SIPRI trend indicator values) | D90: MS.MIL.XPRT.KD
A91: Guinea | B91: GIN | C91: Arms exports (SIPRI trend indicator values) | D91: MS.MIL.XPRT.KD
A92: Gambia, The | B92: GMB | C92: Arms exports (SIPRI trend indicator values) | D92: MS.MIL.XPRT.KD
A93: Guinea-Bissau | B93: GNB | C93: Arms exports (SIPRI trend indicator values) | D93: MS.MIL.XPRT.KD
A94: Equatorial Guinea | B94: GNQ | C94: Arms exports (SIPRI trend indicator values) | D94: MS.MIL.XPRT.KD
A95: Greece | B95: GRC | C95: Arms exports (SIPRI trend indicator values) | D95: MS.MIL.XPRT.KD | I95: 7000000 | J95: 1000000 | AK95: 15000000 | AL95: 10000000 | AM95: 18000000 | AO95: 19000000 | AP95: 31000000 | AQ95: 9000000 | AR95: 3000000 | AS95: 2000000 | AT95: 2000000 | AV95: 6000000 | AW95: 22000000 | AX95: 13000000 | AY95: 23000000 | BJ95: 30000000 | BO95: 7000000 | BP95: 7000000 | BQ95: 20000000 | BR95: 2000000
A96: Grenada | B96: GRD | C96: Arms exports (SIPRI trend indicator values) | D96: MS.MIL.XPRT.KD
A97: Greenland | B97: GRL | C97: Arms exports (SIPRI trend indicator values) | D97: MS.MIL.XPRT.KD
A98: Guatemala | B98: GTM | C98: Arms exports (SIPRI trend indicator values) | D98: MS.MIL.XPRT.KD
A99: Guam | B99: GUM | C99: Arms exports (SIPRI trend indicator values) | D99: MS.MIL.XPRT.KD
A100: Guyana | B100: GUY | C100: Arms exports (SIPRI trend indicator values) | D100: MS.MIL.XPRT.KD | U100: 2000000
A101: High income | B101: HIC | C101: Arms exports (SIPRI trend indicator values) | D101: MS.MIL.XPRT.KD | E101: 10163000000 | F101: 9822000000 | G101: 9512000000 | H101: 13209000000 | I101: 17552000000 | J101: 16513000000 | K101: 14467000000 | L101: 13042000000 | M101: 13821000000 | N101: 16956000000 | O101: 13723000000 | P101: 19639000000 | Q101: 19066000000 | R101: 19082000000 | S101: 19721000000 | T101: 23637000000 | U101: 24392000000 | V101: 23398000000 | W101: 22872000000 | X101: 19261000000 | Y101: 21302000000 | Z101: 26200000000 | AA101: 26056000000 | AB101: 25465000000 | AC101: 23858000000 | AD101: 20854000000 | AE101: 20560000000 | AF101: 21303000000 | AG101: 20754000000 | AH101: 20875000000 | AI101: 18383000000 | AJ101: 20116000000 | AK101: 22817000000 | AL101: 23929000000 | AM101: 21352000000 | AN101: 21576000000 | AO101: 22415000000 | AP101: 27114000000 | AQ101: 26667000000 | AR101: 23249000000 | AS101: 18275000000 | AT101: 17162000000 | AU101: 16239000000 | AV101: 17439000000 | AW101: 20084000000 | AX101: 20332000000 | AY101: 22497000000 | AZ101: 24851000000 | BA101: 22271000000 | BB101: 22073000000 | BC101: 22616000000 | BD101: 27417000000 | BE101: 24384000000 | BF101: 23958000000 | BG101: 24503000000 | BH101: 25862000000 | BI101: 27514000000 | BJ101: 28574000000 | BK101: 24979000000 | BL101: 24545000000 | BM101: 22356000000 | BN101: 24375000000 | BO101: 29811000000 | BP101: 25365000000 | BQ101: 27951000000 | BR101: 31271000000
A102: Hong Kong SAR, China | B102: HKG | C102: Arms exports (SIPRI trend indicator values) | D102: MS.MIL.XPRT.KD
...

Sheet Imports_Clean
A1: Country Name | B1: Country Code | C1: Year | D1: Imports_TIV
A2: Africa Eastern and Southern | B2: AFE | C2: 2000 | D2: 522000000
A3: Africa Eastern and Southern | B3: AFE | C3: 2001 | D3: 403000000
A4: Africa Eastern and Southern | B4: AFE | C4: 2005 | D4: 598000000
A5: Africa Eastern and Southern | B5: AFE | C5: 2006 | D5: 1035000000
A6: Africa Eastern and Southern | B6: AFE | C6: 2007 | D6: 1081000000
A7: Africa Eastern and Southern | B7: AFE | C7: 2008 | D7: 768000000
A8: Africa Eastern and Southern | B8: AFE | C8: 2009 | D8: 420000000
A9: Africa Eastern and Southern | B9: AFE | C9: 2011 | D9: 1131000000
A10: Africa Eastern and Southern | B10: AFE | C10: 2012 | D10: 988000000
A11: Africa Eastern and Southern | B11: AFE | C11: 2013 | D11: 563000000
A12: Africa Eastern and Southern | B12: AFE | C12: 2014 | D12: 308000000
A13: Africa Eastern and Southern | B13: AFE | C13: 2015 | D13: 330000000
... A3833: Zimbabwe | B3833: ZWE | C3833: 2023 | D3833: 20000000

Sheet Clean_Data
A1: Country_Name | B1: Country_Code | C1: Year | D1: Exports_TIV | E1: Imports_TIV | F1: Region | G1: Income_Group | H1: Net_Trade_TIV | I1: Total_Volume_TIV
A2: Africa Western and Central | B2: AFW | C2: 2024 | D2: 0 | E2: 433000000 | F2: =_xlfn.LET(_xlpm.r, _xlfn.XLOOKUP(Clean_Data[[#This Row],[Country_Code]], Metadata_Country!$A:$A, Metadata_Country!$B:$B, "Unknown"), IF(OR(_xlpm.r=0, _xlpm.r=""), "Regional Aggregate", _xlpm.r)) -> Regional Aggregate | G2: =_xlfn.LET(_xlpm.ig, _xlfn.XLOOKUP(Clean_Data[[#This Row],[Country_Code]], Metadata_Country!$A:$A, Metadata_Country!$C:$C, "Unknown"), IF(OR(_xlpm.ig=0, _xlpm.ig=""), "Regional Aggregate", _xlpm.ig)) -> Regional Aggregate | H2: =Clean_Data[[#This Row],[Exports_TIV]] - Clean_Data[[#This Row],[Imports_TIV]] -> -433000000 | I2: =Clean_Data[[#This Row],[Exports_TIV]] + Clean_Data[[#This Row],[Imports_TIV]] -> 433000000
A3: Albania | B3: ALB | C3: 2024 | D3: 0 | E3: 38000000 | F3: =_xlfn.LET(_xlpm.r, _xlfn.XLOOKUP(Clean_Data[[#This Row],[Country_Code]], Metadata_Country!$A:$A, Metadata_Country!$B:$B, "Unknown"), IF(OR(_xlpm.r=0, _xlpm.r=""), "Regional Aggregate", _xlpm.r)) -> Europe & Central Asia | G3: =_xlfn.LET(_xlpm.ig, _xlfn.XLOOKUP(Clean_Data[[#This Row],[Country_Code]], Metadata_Country!$A:$A, Metadata_Country!$C:$C, "Unknown"), IF(OR(_xlpm.ig=0, _xlpm.ig=""), "Regional Aggregate", _xlpm.ig)) -> Upper middle income | H3: =Clean_Data[[#This Row],[Exports_TIV]] - Clean_Data[[#This Row],[Imports_TIV]] -> -38000000 | I3: =Clean_Data[[#This Row],[Exports_TIV]] + Clean_Data[[#This Row],[Imports_TIV]] -> 38000000
A4: Algeria | B4: DZA | C4: 2024 | D4: 0 | E4: 205000000 | F4: =_xlfn.LET(_xlpm.r, _xlfn.XLOOKUP(Clean_Data[[#This Row],[Country_Code]], Metadata_Country!$A:$A, Metadata_Country!$B:$B, "Unknown"), IF(OR(_xlpm.r=0, _xlpm.r=""), "Regional Aggregate", _xlpm.r)) -> Middle East & North Africa | G4: =_xlfn.LET(_xlpm.ig, _xlfn.XLOOKUP(Clean_Data[[#This Row],[Country_Code]], Metadata_Country!$A:$A, Metadata_Country!$C:$C, "Unknown"), IF(OR(_xlpm.ig=0, _xlpm.ig=""), "Regional Aggregate", _xlpm.ig)) -> Upper middle income | H4: =Clean_Data[[#This Row],[Exports_TIV]] - Clean_Data[[#This Row],[Imports_TIV]] -> -205000000 | I4: =Clean_Data[[#This Row],[Exports_TIV]] + Clean_Data[[#This Row],[Imports_TIV]] -> 205000000
A5: Angola | B5: AGO | C5: 2024 | D5: 0 | E5: 16000000 | F5: =_xlfn.LET(_xlpm.r, _xlfn.XLOOKUP(Clean_Data[[#This Row],[Country_Code]], Metadata_Country!$A:$A, Metadata_Country!$B:$B, "Unknown"), IF(OR(_xlpm.r=0, _xlpm.r=""), "Regional Aggregate", _xlpm.r)) -> Sub-Saharan Africa | G5: =_xlfn.LET(_xlpm.ig, _xlfn.XLOOKUP(Clean_Data[[#This Row],[Country_Code]], Metadata_Country!$A:$A, Metadata_Country!$C:$C, "Unknown"), IF(OR(_xlpm.ig=0, _xlpm.ig=""), "Regional Aggregate", _xlpm.ig)) -> Lower middle income | H5: =Clean_Data[[#This Row],[Exports_TIV]] - Clean_Data[[#This Row],[Imports_TIV]] -> -16000000 | I5: =Clean_Data[[#This Row],[Exports_TIV]] + Clean_Data[[#This Row],[Imports_TIV]] -> 16000000
A6: Arab World | B6: ARB | C6: 2024 | D6: 0 | E6: 5605000000 | F6: =_xlfn.LET(_xlpm.r, _xlfn.XLOOKUP(Clean_Data[[#This Row],[Country_Code]], Metadata_Country!$A:$A, Metadata_Country!$B:$B, "Unknown"), IF(OR(_xlpm.r=0, _xlpm.r=""), "Regional Aggregate", _xlpm.r)) -> Regional Aggregate | G6: =_xlfn.LET(_xlpm.ig, _xlfn.XLOOKUP(Clean_Data[[#This Row],[Country_Code]], Metadata_Country!$A:$A, Metadata_Country!$C:$C, "Unknown"), IF(OR(_xlpm.ig=0, _xlpm.ig=""), "Regional Aggregate", _xlpm.ig)) -> Regional Aggregate | H6: =Clean_Data[[#This Row],[Exports_TIV]] - Clean_Data[[#This Row],[Imports_TIV]] -> -5605000000 | I6: =Clean_Data[[#This Row],[Exports_TIV]] + Clean_Data[[#This Row],[Imports_TIV]] -> 5605000000
A7: Argentina | B7: ARG | C7: 2024 | D7: 0 | E7: 45000000 | F7: =_xlfn.LET(_xlpm.r, _xlfn.XLOOKUP(Clean_Data[[#This Row],[Country_Code]], Metadata_Country!$A:$A, Metadata_Country!$B:$B, "Unknown"), IF(OR(_xlpm.r=0, _xlpm.r=""), "Regional Aggregate", _xlpm.r)) -> Latin America & Caribbean | G7: =_xlfn.LET(_xlpm.ig, _xlfn.XLOOKUP(Clean_Data[[#This Row],[Country_Code]], Metadata_Country!$A:$A, Metadata_Country!$C:$C, "Unknown"), IF(OR(_xlpm.ig=0, _xlpm.ig=""), "Regional Aggregate", _xlpm.ig)) -> Upper middle income | H7: =Clean_Data[[#This Row],[Exports_TIV]] - Clean_Data[[#This Row],[Imports_TIV]] -> -45000000 | I7: =Clean_Data[[#This Row],[Exports_TIV]] + Clean_Data[[#This Row],[Imports_TIV]] -> 45000000
A8: Armenia | B8: ARM | C8: 2024 | D8: 0 | E8: 32000000 | F8: =_xlfn.LET(_xlpm.r, _xlfn.XLOOKUP(Clean_Data[[#This Row],[Country_Code]], Metadata_Country!$A:$A, Metadata_Country!$B:$B, "Unknown"), IF(OR(_xlpm.r=0, _xlpm.r=""), "Regional Aggregate", _xlpm.r)) -> Europe & Central Asia | G8: =_xlfn.LET(_xlpm.ig, _xlfn.XLOOKUP(Clean_Data[[#This Row],[Country_Code]], Metadata_Country!$A:$A, Metadata_Country!$C:$C, "Unknown"), IF(OR(_xlpm.ig=0, _xlpm.ig=""), "Regional Aggregate", _xlpm.ig)) -> Upper middle income | H8: =Clean_Data[[#This Row],[Exports_TIV]] - Clean_Data[[#This Row],[Imports_TIV]] -> -32000000 | I8: =Clean_Data[[#This Row],[Exports_TIV]] + Clean_Data[[#This Row],[Imports_TIV]] -> 32000000
A9: Australia | B9: AUS | C9: 2024 | D9: 73000000 | E9: 1077000000 | F9: =_xlfn.LET(_xlpm.r, _xlfn.XLOOKUP(Clean_Data[[#This Row],[Country_Code]], Metadata_Country!$A:$A, Metadata_Country!$B:$B, "Unknown"), IF(OR(_xlpm.r=0, _xlpm.r=""), "Regional Aggregate", _xlpm.r)) -> East Asia & Pacific | G9: =_xlfn.LET(_xlpm.ig, _xlfn.XLOOKUP(Clean_Data[[#This Row],[Country_Code]], Metadata_Country!$A:$A, Metadata_Country!$C:$C, "Unknown"), IF(OR(_xlpm.ig=0, _xlpm.ig=""), "Regional Aggregate", _xlpm.ig)) -> High income | H9: =Clean_Data[[#This Row],[Exports_TIV]] - Clean_Data[[#This Row],[Imports_TIV]] -> -1004000000 | I9: =Clean_Data[[#This Row],[Exports_TIV]] + Clean_Data[[#This Row],[Imports_TIV]] -> 1150000000
A10: Austria | B10: AUT | C10: 2024 | D10: 23000000 | E10: 13000000 | F10: =_xlfn.LET(_xlpm.r, _xlfn.XLOOKUP(Clean_Data[[#This Row],[Country_Code]], Metadata_Country!$A:$A, Metadata_Country!$B:$B, "Unknown"), IF(OR(_xlpm.r=0, _xlpm.r=""), "Regional Aggregate", _xlpm.r)) -> Europe & Central Asia | G10: =_xlfn.LET(_xlpm.ig, _xlfn.XLOOKUP(Clean_Data[[#This Row],[Country_Code]], Metadata_Country!$A:$A, Metadata_Country!$C:$C, "Unknown"), IF(OR(_xlpm.ig=0, _xlpm.ig=""), "Regional Aggregate", _xlpm.ig)) -> High income | H10: =Clean_Data[[#This Row],[Exports_TIV]] - Clean_Data[[#This Row],[Imports_TIV]] -> 10000000 | I10: =Clean_Data[[#This Row],[Exports_TIV]] + Clean_Data[[#This Row],[Imports_TIV]] -> 36000000
A11: Azerbaijan | B11: AZE | C11: 2024 | D11: 0 | E11: 75000000 | F11: =_xlfn.LET(_xlpm.r, _xlfn.XLOOKUP(Clean_Data[[#This Row],[Country_Code]], Metadata_Country!$A:$A, Metadata_Country!$B:$B, "Unknown"), IF(OR(_xlpm.r=0, _xlpm.r=""), "Regional Aggregate", _xlpm.r)) -> Europe & Central Asia | G11: =_xlfn.LET(_xlpm.ig, _xlfn.XLOOKUP(Clean_Data[[#This Row],[Country_Code]], Metadata_Country!$A:$A, Metadata_Country!$C:$C, "Unknown"), IF(OR(_xlpm.ig=0, _xlpm.ig=""), "Regional Aggregate", _xlpm.ig)) -> Upper middle income | H11: =Clean_Data[[#This Row],[Exports_TIV]] - Clean_Data[[#This Row],[Imports_TIV]] -> -75000000 | I11: =Clean_Data[[#This Row],[Exports_TIV]] + Clean_Data[[#This Row],[Imports_TIV]] -> 75000000
A12: Bahrain | B12: BHR | C12: 2024 | D12: 0 | E12: 850000000 | F12: =_xlfn.LET(_xlpm.r, _xlfn.XLOOKUP(Clean_Data[[#This Row],[Country_Code]], Metadata_Country!$A:$A, Metadata_Country!$B:$B, "Unknown"), IF(OR(_xlpm.r=0, _xlpm.r=""), "Regional Aggregate", _xlpm.r)) -> Middle East & North Africa | G12: =_xlfn.LET(_xlpm.ig, _xlfn.XLOOKUP(Clean_Data[[#This Row],[Country_Code]], Metadata_Country!$A:$A, Metadata_Country!$C:$C, "Unknown"), IF(OR(_xlpm.ig=0, _xlpm.ig=""), "Regional Aggregate", _xlpm.ig)) -> High income | H12: =Clean_Data[[#This Row],[Exports_TIV]] - Clean_Data[[#This Row],[Imports_TIV]] -> -850000000 | I12: =Clean_Data[[#This Row],[Exports_TIV]] + Clean_Data[[#This Row],[Imports_TIV]] -> 850000000
A13: Bangladesh | B13: BGD | C13: 2024 | D13: 0 | E13: 70000000 | F13: =_xlfn.LET(_xlpm.r, _xlfn.XLOOKUP(Clean_Data[[#This Row],[Country_Code]], Metadata_Country!$A:$A, Metadata_Country!$B:$B, "Unknown"), IF(OR(_xlpm.r=0, _xlpm.r=""), "Regional Aggregate", _xlpm.r)) -> South Asia | G13: =_xlfn.LET(_xlpm.ig, _xlfn.XLOOKUP(Clean_Data[[#This Row],[Country_Code]], Metadata_Country!$A:$A, Metadata_Country!$C:$C, "Unknown"), IF(OR(_xlpm.ig=0, _xlpm.ig=""), "Regional Aggregate", _xlpm.ig)) -> Lower middle income | H13: =Clean_Data[[#This Row],[Exports_TIV]] - Clean_Data[[#This Row],[Imports_TIV]] -> -70000000 | I13: =Clean_Data[[#This Row],[Exports_TIV]] + Clean_Data[[#This Row],[Imports_TIV]] -> 70000000
... A3986: Zimbabwe | B3986: ZWE | C3986: 2000 | D3986: 0 | E3986: 8000000 | F3986: =_xlfn.LET(_xlpm.r, _xlfn.XLOOKUP(Clean_Data[[#This Row],[Country_Code]], Metadata_Country!$A:$A, Metadata_Country!$B:$B, "Unknown"), IF(OR(_xlpm.r=0, _xlpm.r=""), "Regional Aggregate", _xlpm.r)) -> Sub-Saharan Africa | G3986: =_xlfn.LET(_xlpm.ig, _xlfn.XLOOKUP(Clean_Data[[#This Row],[Country_Code]], Metadata_Country!$A:$A, Metadata_Country!$C:$C, "Unknown"), IF(OR(_xlpm.ig=0, _xlpm.ig=""), "Regional Aggregate", _xlpm.ig)) -> Lower middle income | H3986: =Clean_Data[[#This Row],[Exports_TIV]] - Clean_Data[[#This Row],[Imports_TIV]] -> -8000000 | I3986: =Clean_Data[[#This Row],[Exports_TIV]] + Clean_Data[[#This Row],[Imports_TIV]] -> 8000000

Sheet Analysis
B2: Global Arms Transfers & Defense Alignment (2000–2024)
B3: Source: World Bank WDI / SIPRI TIV Database | Master Dataset Analysis
B5: METRIC | C5: VALUE (TIV) | E5: Rank | F5: Exporter Country | G5: ISO-3 | H5: Cumulative Exports (TIV) | I5: Global Share (%) | K5: Rank | L5: Importer Country | M5: ISO-3 | N5: Cumulative Imports (TIV) | O5: Global Share (%)
B6: Total Global Trade Volume (National) | C6: =SUMIFS(Clean_Data[Total_Volume_TIV], Clean_Data[Region], "<>Regional Aggregate") -> 1282812000000 | E6: {=_xlfn.SEQUENCE(10)} -> 1 | F6: {=_xlfn.LET( _xlpm.countries, _xlfn.UNIQUE(_xlfn._xlws.FILTER(Clean_Data[Country_Name], Clean_Data[Region]<>"Regional Aggregate")), _xlpm.exports, _xlfn.MAP(_xlpm.countries, _xlfn.LAMBDA(_xlpm.c, SUMIFS(Clean_Data[Exports_TIV], Clean_Data[Country_Name], _xlpm.c))), _xlpm.codes, _xlfn.MAP(_xlpm.countries, _xlfn.LAMBDA(_xlpm.c, _xlfn.XLOOKUP(_xlpm.c, Clean_Data[Country_Name], Clean_Data[Country_Code]))), _xlpm.table, _xlfn.HSTACK(_xlpm.countries, _xlpm.codes, _xlpm.exports), _xlfn.TAKE(_xlfn._xlws.SORT(_xlpm.table, 3, -1), 10) )} -> United States | G6: USA | H6: 222364000000 | I6: {=INDEX(_xlfn.ANCHORARRAY(F6), , 3) / $C$7} -> 0.34403884 | K6: {=_xlfn.SEQUENCE(10)} -> 1 | L6: {=_xlfn.LET( _xlpm.countries, _xlfn.UNIQUE(_xlfn._xlws.FILTER(Clean_Data[Country_Name], Clean_Data[Region]<>"Regional Aggregate")), _xlpm.imports, _xlfn.MAP(_xlpm.countries, _xlfn.LAMBDA(_xlpm.c, SUMIFS(Clean_Data[Imports_TIV], Clean_Data[Country_Name], _xlpm.c))), _xlpm.codes, _xlfn.MAP(_xlpm.countries, _xlfn.LAMBDA(_xlpm.c, _xlfn.XLOOKUP(_xlpm.c, Clean_Data[Country_Name], Clean_Data[Country_Code]))), _xlpm.table, _xlfn.HSTACK(_xlpm.countries, _xlpm.codes, _xlpm.imports), _xlfn.TAKE(_xlfn._xlws.SORT(_xlpm.table, 3, -1), 10) )} -> India | M6: IND | N6: 62908000000 | O6: {=INDEX(_xlfn.ANCHORARRAY(L6), , 3) / $C$8} -> 0.098837666
B7: Total Global Exports (National) | C7: =SUMIFS(Clean_Data[Exports_TIV], Clean_Data[Region], "<>Regional Aggregate") -> 646334000000 | E7: 2 | F7: Russian Federation | G7: RUS | H7: 134441000000 | I7: 0.20800546 | K7: 2 | L7: China | M7: CHN | N7: 40927000000 | O7: 0.064302301
B8: Total Global Imports (National) | C8: =SUMIFS(Clean_Data[Imports_TIV], Clean_Data[Region], "<>Regional Aggregate") -> 636478000000 | E8: 3 | F8: France | G8: FRA | H8: 50421000000 | I8: 0.07801075 | K8: 3 | L8: Saudi Arabia | M8: SAU | N8: 37196000000 | O8: 0.058440355
B9: Net Arms Exporter Surplus / Deficit | C9: =C7 - C8 -> 9856000000 | E9: 4 | F9: Germany | G9: DEU | H9: 41813000000 | I9: 0.064692558 | K9: 4 | L9: Korea, Rep. | M9: KOR | N9: 24721000000 | O9: 0.038840306
B10: Distinct Sovereign Entities Tracked | C10: {=COUNTA(_xlfn.UNIQUE(_xlfn._xlws.FILTER(Clean_Data[Country_Code], Clean_Data[Region]<>"Regional Aggregate")))} -> 181 | E10: 5 | F10: China | G10: CHN | H10: 30914000000 | I10: 0.04782976 | K10: 5 | L10: United Arab Emirates | M10: ARE | N10: 24693000000 | O10: 0.038796313
B11: Timeline Period | C11: =MIN(Clean_Data[Year]) & " – " & MAX(Clean_Data[Year]) -> 2000 – 2024 | E11: 6 | F11: United Kingdom | G11: GBR | H11: 27483000000 | I11: 0.042521359 | K11: 6 | L11: Australia | M11: AUS | N11: 23363000000 | O11: 0.036706689
E12: 7 | F12: Italy | G12: ITA | H12: 18116000000 | I12: 0.028028852 | K12: 7 | L12: Pakistan | M12: PAK | N12: 22867000000 | O12: 0.0359274
E13: 8 | F13: Israel | G13: ISR | H13: 16890000000 | I13: 0.026132 | K13: 8 | L13: Egypt, Arab Rep. | M13: EGY | N13: 22095000000 | O13: 0.034714476
E14: 9 | F14: Spain | G14: ESP | H14: 13942000000 | I14: 0.021570891 | K14: 9 | L14: United States | M14: USA | N14: 18178000000 | O14: 0.028560296
E15: 10 | F15: Netherlands | G15: NLD | H15: 12579000000 | I15: 0.019462074 | K15: 10 | L15: Algeria | M15: DZA | N15: 17187000000 | O15: 0.02700329
B20: Region | C20: Exports (TIV) | D20: Imports (TIV) | E20: Net Trade (TIV) | F20: Trade Orientation
B21: {=_xlfn.LET( _xlpm.regs, _xlfn._xlws.SORT(_xlfn.UNIQUE(_xlfn._xlws.FILTER(Clean_Data[Region], (Clean_Data[Region]<>"Regional Aggregate")*(Clean_Data[Region]<>"Unknown")*(Clean_Data[Region]<>"")))), _xlpm.regs )} -> East Asia & Pacific | C21: {=_xlfn.MAP(_xlfn.ANCHORARRAY(B21), _xlfn.LAMBDA(_xlpm.r, SUMIFS(Clean_Data[Exports_TIV], Clean_Data[Region], _xlpm.r)))} -> 44039000000 | D21: {=_xlfn.MAP(_xlfn.ANCHORARRAY(B21), _xlfn.LAMBDA(_xlpm.r, SUMIFS(Clean_Data[Imports_TIV], Clean_Data[Region], _xlpm.r)))} -> 154429000000 | E21: {=_xlfn.ANCHORARRAY(C21) -_xlfn.ANCHORARRAY( D21)} -> -110390000000 | F21: {=_xlfn.MAP(_xlfn.ANCHORARRAY(E21), _xlfn.LAMBDA(_xlpm.val, IF(_xlpm.val > 0, "Net Exporter (Supplier)", "Net Importer (Dependent)")))} -> Net Importer (Dependent)
B22: Europe & Central Asia | C22: 348368000000 | D22: 140914000000 | E22: 207454000000 | F22: Net Exporter (Supplier)
B23: Latin America & Caribbean | C23: 1604000000 | D23: 27613000000 | E23: -26009000000 | F23: Net Importer (Dependent)
B24: Middle East & North Africa | C24: 21385000000 | D24: 199652000000 | E24: -178267000000 | F24: Net Importer (Dependent)
B25: North America | C25: 227402000000 | D25: 25127000000 | E25: 202275000000 | F25: Net Exporter (Supplier)
B26: South Asia | C26: 804000000 | D26: 69341000000 | E26: -68537000000 | F26: Net Importer (Dependent)
B27: Sub-Saharan Africa | C27: 2732000000 | D27: 19402000000 | E27: -16670000000 | F27: Net Importer (Dependent)
B32: ANNUAL EXPORT TRENDS: TOP 5 GLOBAL SUPPLIERS (2000–2024)
B34: Year | C34: United States | D34: Russian Federation | E34: France | F34: Germany | G34: China | H34: Top 5 Combined (TIV)
B35: {=_xlfn.SEQUENCE(25, 1, 2000, 1)} -> 2000 | C35: {=_xlfn.MAP(_xlfn.ANCHORARRAY(B35), _xlfn.LAMBDA(_xlpm.y, SUMIFS(Clean_Data[Exports_TIV], Clean_Data[Country_Code], "USA", Clean_Data[Year], _xlpm.y)))} -> 7678000000 | D35: {=_xlfn.MAP(_xlfn.ANCHORARRAY(B35), _xlfn.LAMBDA(_xlpm.y, SUMIFS(Clean_Data[Exports_TIV], Clean_Data[Country_Code], "RUS", Clean_Data[Year], _xlpm.y)))} -> 4496000000 | E35: {=_xlfn.MAP(_xlfn.ANCHORARRAY(B35), _xlfn.LAMBDA(_xlpm.y, SUMIFS(Clean_Data[Exports_TIV], Clean_Data[Country_Code], "FRA", Clean_Data[Year], _xlpm.y)))} -> 966000000 | F35: {=_xlfn.MAP(_xlfn.ANCHORARRAY(B35), _xlfn.LAMBDA(_xlpm.y, SUMIFS(Clean_Data[Exports_TIV], Clean_Data[Country_Code], "DEU", Clean_Data[Year], _xlpm.y)))} -> 1672000000 | G35: {=_xlfn.MAP(_xlfn.ANCHORARRAY(B35), _xlfn.LAMBDA(_xlpm.y, SUMIFS(Clean_Data[Exports_TIV], Clean_Data[Country_Code], "CHN", Clean_Data[Year], _xlpm.y)))} -> 309000000 | H35: {=_xlfn.BYROW(_xlfn.HSTACK(_xlfn.ANCHORARRAY(C35),_xlfn.ANCHORARRAY( D35),_xlfn.ANCHORARRAY( E35),_xlfn.ANCHORARRAY( F35),_xlfn.ANCHORARRAY( G35)), _xlfn.LAMBDA(_xlpm.r, SUM(_xlpm.r)))} -> 15121000000
B36: 2001 | C36: 5591000000 | D36: 5250000000 | E36: 1311000000 | F36: 851000000 | G36: 510000000 | H36: 13513000000
B37: 2002 | C37: 4872000000 | D37: 5735000000 | E37: 1375000000 | F37: 889000000 | G37: 524000000 | H37: 13395000000
B38: 2003 | C38: 5684000000 | D38: 5266000000 | E38: 1348000000 | F38: 1632000000 | G38: 701000000 | H38: 14631000000
B39: 2004 | C39: 6869000000 | D39: 6353000000 | E39: 2117000000 | F39: 1090000000 | G39: 408000000 | H39: 16837000000
B40: 2005 | C40: 6724000000 | D40: 5199000000 | E40: 1645000000 | F40: 2083000000 | G40: 341000000 | H40: 15992000000
B41: 2006 | C41: 7497000000 | D41: 5182000000 | E41: 1484000000 | F41: 2482000000 | G41: 769000000 | H41: 17414000000
B42: 2007 | C42: 7870000000 | D42: 5596000000 | E42: 2145000000 | F42: 3291000000 | G42: 520000000 | H42: 19422000000
B43: 2008 | C43: 7089000000 | D43: 5998000000 | E43: 1872000000 | F43: 2378000000 | G43: 598000000 | H43: 17935000000
B44: 2009 | C44: 7151000000 | D44: 5126000000 | E44: 1845000000 | F44: 2207000000 | G44: 1138000000 | H44: 17467000000
B45: 2010 | C45: 8354000000 | D45: 6227000000 | E45: 888000000 | F45: 2364000000 | G45: 1531000000 | H45: 19364000000
B46: 2011 | C46: 9041000000 | D46: 8793000000 | E46: 2079000000 | F46: 1203000000 | G46: 1308000000 | H46: 22424000000
B47: 2012 | C47: 8965000000 | D47: 8335000000 | E47: 1338000000 | F47: 715000000 | G47: 1499000000 | H47: 20852000000
... B59: 2024 | C59: 13651000000 | D59: 1994000000 | E59: 2472000000 | F59: 2108000000 | G59: 1294000000 | H59: 21519000000

Sheet Dashboard
B2: Global Defense Trade: Trajectories & Strategic Alignment (2000–2024)
B3: World Bank / SIPRI TIV Trend Visualizations

Sheet Pivot_Table
A1: Region | B1: (Multiple Items)
B3: Column Labels
B4: 2000 | D4: 2001 | F4: 2002 | H4: 2003 | J4: 2004 | L4: 2005 | N4: 2006 | P4: 2007 | R4: 2008 | T4: 2009 | V4: 2010 | X4: 2011 | Z4: 2012 | AB4: 2013 | AD4: 2014 | AF4: 2015 | AH4: 2016 | AJ4: 2017 | AL4: 2018 | AN4: 2019 | AP4: 2020 | AR4: 2021 | AT4: 2022 | AV4: 2023 | AX4: 2024 | AZ4: Total Net Trade (TIV) | BA4: Total Total Volume (TIV)
A5: Row Labels | B5: Net Trade (TIV) | C5: Total Volume (TIV) | D5: Net Trade (TIV) | E5: Total Volume (TIV) | F5: Net Trade (TIV) | G5: Total Volume (TIV) | H5: Net Trade (TIV) | I5: Total Volume (TIV) | J5: Net Trade (TIV) | K5: Total Volume (TIV) | L5: Net Trade (TIV) | M5: Total Volume (TIV) | N5: Net Trade (TIV) | O5: Total Volume (TIV) | P5: Net Trade (TIV) | Q5: Total Volume (TIV) | R5: Net Trade (TIV) | S5: Total Volume (TIV) | T5: Net Trade (TIV) | U5: Total Volume (TIV) | V5: Net Trade (TIV) | W5: Total Volume (TIV) | X5: Net Trade (TIV) | Y5: Total Volume (TIV) | Z5: Net Trade (TIV) | AA5: Total Volume (TIV) | AB5: Net Trade (TIV) | AC5: Total Volume (TIV) | AD5: Net Trade (TIV) | AE5: Total Volume (TIV) | AF5: Net Trade (TIV) | AG5: Total Volume (TIV) | AH5: Net Trade (TIV) | AI5: Total Volume (TIV) | AJ5: Net Trade (TIV) | AK5: Total Volume (TIV) | AL5: Net Trade (TIV) | AM5: Total Volume (TIV) | AN5: Net Trade (TIV) | AO5: Total Volume (TIV) | AP5: Net Trade (TIV) | AQ5: Total Volume (TIV) | AR5: Net Trade (TIV) | AS5: Total Volume (TIV) | AT5: Net Trade (TIV) | AU5: Total Volume (TIV) | AV5: Net Trade (TIV) | AW5: Total Volume (TIV) | AX5: Net Trade (TIV) | AY5: Total Volume (TIV)
A6: High income | B6: 7742000000 | C6: 28808000000 | D6: 9033000000 | E6: 25279000000 | F6: 9266000000 | G6: 23212000000 | H6: 7991000000 | I6: 26887000000 | J6: 9505000000 | K6: 30663000000 | L6: 10137000000 | M6: 30527000000 | N6: 9311000000 | O6: 35683000000 | P6: 10509000000 | Q6: 39193000000 | R6: 9794000000 | S6: 34748000000 | T6: 9939000000 | U6: 34175000000 | V6: 10486000000 | W6: 34746000000 | X6: 15641000000 | Y6: 39193000000 | Z6: 14943000000 | AA6: 33821000000 | AB6: 14100000000 | AC6: 33816000000 | AD6: 13898000000 | AE6: 35108000000 | AF6: 12937000000 | AG6: 38779000000 | AH6: 14752000000 | AI6: 40272000000 | AJ6: 14665000000 | AK6: 42479000000 | AL6: 12502000000 | AM6: 37456000000 | AN6: 10140000000 | AO6: 38946000000 | AP6: 8858000000 | AQ6: 35850000000 | AR6: 8942000000 | AS6: 39802000000 | AT6: 10138000000 | AU6: 49484000000 | AV6: 10556000000 | AW6: 40174000000 | AX6: 10386000000 | AY6: 45516000000 | AZ6: 276171000000 | BA6: 894617000000
A7: Low income | B7: -489000000 | C7: 571000000 | D7: -304000000 | E7: 410000000 | F7: -706000000 | G7: 1006000000 | H7: -434000000 | I7: 692000000 | J7: -893000000 | K7: 977000000 | L7: -642000000 | M7: 672000000 | N7: -307000000 | O7: 343000000 | P7: -272000000 | Q7: 302000000 | R7: -812000000 | S7: 842000000 | T7: -777000000 | U7: 889000000 | V7: -1504000000 | W7: 1578000000 | X7: -1990000000 | Y7: 1990000000 | Z7: -1657000000 | AA7: 1657000000 | AB7: -1215000000 | AC7: 1237000000 | AD7: -576000000 | AE7: 578000000 | AF7: -411000000 | AG7: 411000000 | AH7: -492000000 | AI7: 500000000 | AJ7: -485000000 | AK7: 485000000 | AL7: -649000000 | AM7: 649000000 | AN7: -670000000 | AO7: 670000000 | AP7: -504000000 | AQ7: 504000000 | AR7: -362000000 | AS7: 362000000 | AT7: -283000000 | AU7: 283000000 | AV7: -295000000 | AW7: 313000000 | AX7: -10000000 | AY7: 432000000 | AZ7: -16739000000 | BA7: 18353000000
A8: Lower middle income | B8: -2764000000 | C8: 2816000000 | D8: -3072000000 | E8: 3084000000 | F8: -3829000000 | G8: 3947000000 | H8: -4146000000 | I8: 4858000000 | J8: -3607000000 | K8: 3941000000 | L8: -2995000000 | M8: 3131000000 | N8: -3523000000 | O8: 3647000000 | P8: -4875000000 | Q8: 4957000000 | R8: -4004000000 | S8: 4070000000 | T8: -3774000000 | U8: 4326000000 | V8: -6812000000 | W8: 7240000000 | X8: -8267000000 | Y8: 8691000000 | Z8: -8764000000 | AA8: 8764000000 | AB8: -9697000000 | AC8: 9733000000 | AD8: -6250000000 | AE8: 6344000000 | AF8: -6492000000 | AG8: 6694000000 | AH8: -6895000000 | AI8: 7141000000 | AJ8: -7654000000 | AK8: 7782000000 | AL8: -6201000000 | AM8: 6301000000 | AN8: -6564000000 | AO8: 6622000000 | AP8: -5383000000 | AQ8: 5689000000 | AR8: -6862000000 | AS8: 7202000000 | AT8: -6382000000 | AU8: 6530000000 | AV8: -6191000000 | AW8: 6385000000 | AX8: -3638000000 | AY8: 3962000000 | AZ8: -138641000000 | BA8: 143857000000
A9: Upper middle income | B9: -3860000000 | C9: 8186000000 | D9: -5108000000 | E9: 7624000000 | F9: -4444000000 | G9: 6876000000 | H9: -3308000000 | I9: 5732000000 | J9: -4702000000 | K9: 6640000000 | L9: -5801000000 | M9: 7645000000 | N9: -4849000000 | O9: 8741000000 | P9: -5351000000 | Q9: 8561000000 | R9: -4985000000 | S9: 8513000000 | T9: -4924000000 | U9: 8988000000 | V9: -2097000000 | W9: 7965000000 | X9: -5216000000 | Y9: 9798000000 | Z9: -4106000000 | AA9: 11184000000 | AB9: -2545000000 | AC9: 9361000000 | AD9: -5921000000 | AE9: 11023000000 | AF9: -5462000000 | AG9: 10958000000 | AH9: -7195000000 | AI9: 14847000000 | AJ9: -5991000000 | AK9: 11263000000 | AL9: -5502000000 | AM9: 10164000000 | AN9: -2721000000 | AO9: 7621000000 | AP9: -2173000000 | AQ9: 5259000000 | AR9: -1348000000 | AS9: 6368000000 | AT9: -3087000000 | AU9: 9831000000 | AV9: -3975000000 | AW9: 11825000000 | AX9: -6264000000 | AY9: 11012000000 | AZ9: -110935000000 | BA9: 225985000000
A10: Grand Total | B10: 629000000 | C10: 40381000000 | D10: 549000000 | E10: 36397000000 | F10: 287000000 | G10: 35041000000 | H10: 103000000 | I10: 38169000000 | J10: 303000000 | K10: 42221000000 | L10: 699000000 | M10: 41975000000 | N10: 632000000 | O10: 48414000000 | P10: 11000000 | Q10: 53013000000 | R10: -7000000 | S10: 48173000000 | T10: 464000000 | U10: 48378000000 | V10: 73000000 | W10: 51529000000 | X10: 168000000 | Y10: 59672000000 | Z10: 416000000 | AA10: 55426000000 | AB10: 643000000 | AC10: 54147000000 | AD10: 1151000000 | AE10: 53053000000 | AF10: 572000000 | AG10: 56842000000 | AH10: 170000000 | AI10: 62760000000 | AJ10: 535000000 | AK10: 62009000000 | AL10: 150000000 | AM10: 54570000000 | AN10: 185000000 | AO10: 53859000000 | AP10: 798000000 | AQ10: 47302000000 | AR10: 370000000 | AS10: 53734000000 | AT10: 386000000 | AU10: 66128000000 | AV10: 95000000 | AW10: 58697000000 | AX10: 474000000 | AY10: 60922000000 | AZ10: 9856000000 | BA10: 1282812000000

Sheet Data_Dictionary
B2: Project: Global Arms Transfers & Defense Alignment (2000–2024)
B5: Dataset / Series Name | C5: Organization | D5: Indicator Code | E5: Direct Source URL / Portal
B6: Arms Exports (SIPRI Trend Indicator Values) | C6: World Bank / SIPRI | D6: MS.MIL.XPRT.KD | E6: =HYPERLINK("https://data.worldbank.org/indicator/MS.MIL.XPRT.KD", "World Bank: Arms Exports (TIV)") -> World Bank: Arms Exports (TIV)
B7: Arms Imports (SIPRI Trend Indicator Values) | C7: World Bank / SIPRI | D7: MS.MIL.MPRT.KD | E7: =HYPERLINK("https://data.worldbank.org/indicator/MS.MIL.MPRT.KD", "World Bank: Arms Imports (TIV)") -> World Bank: Arms Imports (TIV)
B8: SIPRI Arms Transfers Database Methodology | C8: Stockholm International Peace Research Institute (SIPRI) | D8: TIV Methodology | E8: =HYPERLINK("https://www.sipri.org/databases/armstransfers/sources-and-methods", "SIPRI: Sources & Methods") -> SIPRI: Sources & Methods
B9: World Development Indicators (WDI) Metadata | C9: World Bank | D9: Country & Lending Groups | E9: =HYPERLINK("https://datahelpdesk.worldbank.org/knowledgebase/articles/906519", "World Bank: Classification Metadata") -> World Bank: Classification Metadata

Sheet Metadata_Country
A1: Country Code | B1: Region | C1: IncomeGroup | D1: SpecialNotes | E1: TableName
A2: ABW | B2: Latin America & Caribbean | C2: High income | E2: Aruba
A3: AFE | D3: 26 countries, stretching from the Red Sea in the North to the Cape of Good Hope in the South (https://www.worldbank.org/en/region/afr/eastern-and-southern-africa) | E3: Africa Eastern and Southern
A4: AFG | B4: Middle East & North Africa | C4: Low income | D4: The reporting period for national accounts data is designated as either calendar year basis (CY) or fiscal year basis (FY). For this country, it is fiscal year-based (fiscal year-end: March 20). Also, an estimate (PA.NUS.ATLS) of the exchange rate covers the same period and thus differs from the official exchange rate (CY). In addition, the World Bank systematically assesses the appropriateness of official exchange rates as conversion factors. In this country, multiple or dual exchange rate activity exists and must be accounted for appropriately in underlying statistics. An alternative estimate (“alternative conversion factor” - PA.NUS.ATLS) is thus calculated as a weighted average of the different exchange rates in use in the country. Doing so better reflects economic reality and leads to more accurate cross-country comparisons and country classifications by income level. For this country, this applies to the period 1960-2006. Alternative conversion factors are used in the Atlas methodology and elsewhere in World Development Indicators as single-year conversion factors. | E4: Afghanistan
A5: AFW | D5: 22 countries, stretching from the westernmost point of Africa, across the equator, and partly along the Atlantic Ocean till the Republic of Congo in the South (https://www.worldbank.org/en/region/afr/western-and-central-africa) | E5: Africa Western and Central
A6: AGO | B6: Sub-Saharan Africa | C6: Lower middle income | D6: The World Bank systematically assesses the appropriateness of official exchange rates as conversion factors. In this country, multiple or dual exchange rate activity exists and must be accounted for appropriately in underlying statistics. An alternative estimate (“alternative conversion factor” - PA.NUS.ATLS) is thus calculated as a weighted average of the different exchange rates in use in the country. Doing so better reflects economic reality and leads to more accurate cross-country comparisons and country classifications by income level. For this country, this applies to the period 1994-2025. Alternative conversion factors are used in the Atlas methodology and elsewhere in World Development Indicators as single-year conversion factors. | E6: Angola
A7: ALB | B7: Europe & Central Asia | C7: Upper middle income | E7: Albania
A8: AND | B8: Europe & Central Asia | C8: High income | E8: Andorra
A9: ARB | D9: Arab World aggregate. Arab World is composed of members of the League of Arab States. | E9: Arab World
A10: ARE | B10: Middle East & North Africa | C10: High income | E10: United Arab Emirates
A11: ARG | B11: Latin America & Caribbean | C11: Upper middle income | D11: Due to the limitations of the Atlas method in classifying countries experiencing persistent high inflation, this economy remains classified as upper-middle-income. The World Bank systematically assesses the appropriateness of official exchange rates as conversion factors. In this country, multiple or dual exchange rate activity exists and must be accounted for appropriately in underlying statistics. An alternative estimate (“alternative conversion factor” - PA.NUS.ATLS) is thus calculated as a weighted average of the different exchange rates in use in the country. Doing so better reflects economic reality and leads to more accurate cross-country comparisons and country classifications by income level. For this country, this applies to the period 1971-2018. Alternative conversion factors are used in the Atlas methodology and elsewhere in World Development Indicators as single-year conversion factors. | E11: Argentina
A12: ARM | B12: Europe & Central Asia | C12: Upper middle income | E12: Armenia
A13: ASM | B13: East Asia & Pacific | C13: High income | E13: American Samoa
A14: ATG | B14: Latin America & Caribbean | C14: High income | E14: Antigua and Barbuda
A15: AUS | B15: East Asia & Pacific | C15: High income | D15: The reporting period for national accounts data is designated as either calendar year basis (CY) or fiscal year basis (FY). For this country, it is fiscal year-based (fiscal year-end: June 30). Also, an estimate (PA.NUS.ATLS) of the exchange rate covers the same period and thus differs from the official exchange rate (CY). | E15: Australia
A16: AUT | B16: Europe & Central Asia | C16: High income | D16: A simple multiplier is used to convert the national currencies of EMU members to euros. The following irrevocable euro conversion rate was adopted by the EU Council on January 1, 1999: 1 euro = 13.7603 Austrian schilling. Please note that historical data before 1999 are not actual euros and are not comparable or suitable for aggregation across countries. | E16: Austria
A17: AZE | B17: Europe & Central Asia | C17: Upper middle income | E17: Azerbaijan
A18: BDI | B18: Sub-Saharan Africa | C18: Low income | D18: The World Bank systematically assesses the appropriateness of official exchange rates as conversion factors. In this country, multiple or dual exchange rate activity exists and must be accounted for appropriately in underlying statistics. An alternative estimate (“alternative conversion factor” - PA.NUS.ATLS) is thus calculated as a weighted average of the different exchange rates in use in the country. Doing so better reflects economic reality and leads to more accurate cross-country comparisons and country classifications by income level. For this country, this applies to the period 1983-2025. Alternative conversion factors are used in the Atlas methodology and elsewhere in World Development Indicators as single-year conversion factors. | E18: Burundi
A19: BEL | B19: Europe & Central Asia | C19: High income | D19: A simple multiplier is used to convert the national currencies of EMU members to euros. The following irrevocable euro conversion rate was adopted by the EU Council on January 1, 1999: 1 euro = 40.3399 Belgian franc. Please note that historical data before 1999 are not actual euros and are not comparable or suitable for aggregation across countries. | E19: Belgium
A20: BEN | B20: Sub-Saharan Africa | C20: Lower middle income | E20: Benin
A21: BFA | B21: Sub-Saharan Africa | C21: Low income | E21: Burkina Faso
A22: BGD | B22: South Asia | C22: Lower middle income | D22: The reporting period for national accounts data is designated as either calendar year basis (CY) or fiscal year basis (FY). For this country, it is fiscal year-based (fiscal year-end: June 30). Also, an estimate (PA.NUS.ATLS) of the exchange rate covers the same period and thus differs from the official exchange rate (CY). | E22: Bangladesh
A23: BGR | B23: Europe & Central Asia | C23: High income | D23: A simple multiplier is used to convert the national currencies of EMU members to euros. The following irrevocable euro conversion rate entered into force on January 1, 2026: 1 euro = 1.95583 Bulgarian Lev. Please note that historical data are not actual euros and are not comparable or suitable for aggregation across countries. | E23: Bulgaria
A24: BHR | B24: Middle East & North Africa | C24: High income | E24: Bahrain
A25: BHS | B25: Latin America & Caribbean | C25: High income | E25: Bahamas, The
A26: BIH | B26: Europe & Central Asia | C26: Upper middle income | E26: Bosnia and Herzegovina
A27: BLR | B27: Europe & Central Asia | C27: Upper middle income | D27: Data before 2015 were adjusted to reflect the new denomination effective from July 1, 2016 (BYN), a decrease of 10,000 times (1 BYN = 10,000 BYR) | E27: Belarus
A28: BLZ | B28: Latin America & Caribbean | C28: Upper middle income | E28: Belize
A29: BMU | B29: North America | C29: High income | E29: Bermuda
A30: BOL | B30: Latin America & Caribbean | C30: Lower middle income | E30: Bolivia
A31: BRA | B31: Latin America & Caribbean | C31: Upper middle income | E31: Brazil
A32: BRB | B32: Latin America & Caribbean | C32: High income | E32: Barbados
A33: BRN | B33: East Asia & Pacific | C33: High income | E33: Brunei Darussalam
A34: BTN | B34: South Asia | C34: Lower middle income | E34: Bhutan
A35: BWA | B35: Sub-Saharan Africa | C35: Upper middle income | E35: Botswana
A36: CAF | B36: Sub-Saharan Africa | C36: Low income | E36: Central African Republic
A37: CAN | B37: North America | C37: High income | D37: Fiscal year end: March 31; reporting period for national accounts data: CY. | E37: Canada
A38: CEB | D38: Central Europe and the Baltics aggregate. | E38: Central Europe and the Baltics
A39: CHE | B39: Europe & Central Asia | C39: High income | E39: Switzerland
A40: CHI | B40: Europe & Central Asia | C40: High income | E40: Channel Islands
A41: CHL | B41: Latin America & Caribbean | C41: High income | E41: Chile
A42: CHN | B42: East Asia & Pacific | C42: Upper middle income | D42: On 1 July 1997 China resumed its exercise of sovereignty over Hong Kong, and on 20 December 1999, China resumed its exercise of sovereignty over Macao. Unless otherwise noted, data for China do not include data for Hong Kong SAR, China; Macao SAR, China; or Taiwan, China. The World Bank systematically assesses the appropriateness of official exchange rates as conversion factors. In this country, multiple or dual exchange rate activity exists and must be accounted for appropriately in underlying statistics. An alternative estimate (“alternative conversion factor” - PA.NUS.ATLS) is thus calculated as a weighted average of the different exchange rates in use in the country. Doing so better reflects economic reality and leads to more accurate cross-country comparisons and country classifications by income level. For this country, this applies to the period 1978-1993. Alternative conversion factors are used in the Atlas methodology and elsewhere in World Development Indicators as single-year conversion factors. | E42: China
A43: CIV | B43: Sub-Saharan Africa | C43: Lower middle income | E43: Côte d'Ivoire
A44: CMR | B44: Sub-Saharan Africa | C44: Lower middle income | E44: Cameroon
A45: COD | B45: Sub-Saharan Africa | C45: Low income | D45: The World Bank systematically assesses the appropriateness of official exchange rates as conversion factors. In this country, multiple or dual exchange rate activity exists and must be accounted for appropriately in underlying statistics. An alternative estimate (“alternative conversion factor” - PA.NUS.ATLS) is thus calculated as a weighted average of the different exchange rates in use in the country. Doing so better reflects economic reality and leads to more accurate cross-country comparisons and country classifications by income level. For this country, this applies to the period 1999-2004. Alternative conversion factors are used in the Atlas methodology and elsewhere in World Development Indicators as single-year conversion factors. | E45: Congo, Dem. Rep.
A46: COG | B46: Sub-Saharan Africa | C46: Lower middle income | E46: Congo, Rep.
A47: COL | B47: Latin America & Caribbean | C47: Upper middle income | E47: Colombia
A48: COM | B48: Sub-Saharan Africa | C48: Lower middle income | E48: Comoros
A49: CPV | B49: Sub-Saharan Africa | C49: Upper middle income | E49: Cabo Verde
A50: CRI | B50: Latin America & Caribbean | C50: High income | E50: Costa Rica
A51: CSS | D51: Caribbean small states aggregate. | E51: Caribbean small states
A52: CUB | B52: Latin America & Caribbean | C52: Upper middle income | E52: Cuba
A53: CUW | B53: Latin America & Caribbean | C53: High income | E53: Curaçao
A54: CYM | B54: Latin America & Caribbean | C54: High income | E54: Cayman Islands
A55: CYP | B55: Europe & Central Asia | C55: High income | D55: A simple multiplier is used to convert the national currencies of EMU members to euros. The following irrevocable euro conversion rate entered into force on January 1, 2008: 1 euro = 0.585274 Cyprus pounds. Please note that historical data are not actual euros and are not comparable or suitable for aggregation across countries. | E55: Cyprus
A56: CZE | B56: Europe & Central Asia | C56: High income | E56: Czechia
A57: DEU | B57: Europe & Central Asia | C57: High income | D57: A simple multiplier is used to convert the national currencies of EMU members to euros. The following irrevocable euro conversion rate was adopted by the EU Council on January 1, 1999: 1 euro = 1.95583 Deutsche Mark. Please note that historical data before 1999 are not actual euros and are not comparable or suitable for aggregation across countries. GDP data before 1991 are calculated by applying backward GDP growth rates of the former Federal Republic of Germany starting from the first official GDP value for the unified Germany (1991). | E57: Germany
A58: DJI | B58: Middle East & North Africa | C58: Lower middle income | E58: Djibouti
A59: DMA | B59: Latin America & Caribbean | C59: Upper middle income | E59: Dominica
A60: DNK | B60: Europe & Central Asia | C60: High income | E60: Denmark
A61: DOM | B61: Latin America & Caribbean | C61: Upper middle income | E61: Dominican Republic
A62: DZA | B62: Middle East & North Africa | C62: Upper middle income | E62: Algeria
A63: EAP | E63: East Asia & Pacific (excluding high income)
A64: EAR | D64: Early-dividend countries are mostly lower-middle-income countries further along the fertility transition. Fertility rates have fallen below four births per woman and the working-age share of the population is likely rising considerably. | E64: Early-demographic dividend
A65: EAS | D65: East Asia and Pacific regional aggregate (includes all income levels). | E65: East Asia & Pacific
A66: ECA | E66: Europe & Central Asia (excluding high income)
A67: ECS | D67: Europe and Central Asia regional aggregate (includes all income levels). | E67: Europe & Central Asia
A68: ECU | B68: Latin America & Caribbean | C68: Upper middle income | E68: Ecuador
A69: EGY | B69: Middle East & North Africa | C69: Lower middle income | D69: The reporting period for national accounts data is designated as either calendar year basis (CY) or fiscal year basis (FY). For this country, it is fiscal year-based (fiscal year-end: June 30) for the years 1980 and after. The data from 1973 to 1979 refer to the calendar year data. Also, an estimate (PA.NUS.ATLS) of the exchange rate covers the same period and thus differs from the official exchange rate (CY). In addition, the World Bank systematically assesses the appropriateness of official exchange rates as conversion factors. In this country, multiple or dual exchange rate activity exists and must be accounted for appropriately in underlying statistics. An alternative estimate (“alternative conversion factor” - PA.NUS.ATLS) is thus calculated as a weighted average of the different exchange rates in use in the country. Doing so better reflects economic reality and leads to more accurate cross-country comparisons and country classifications by income level. For this country, this applies to the period 1965-2021. Alternative conversion factors are used in the Atlas methodology and elsewhere in World Development Indicators as single-year conversion factors. The national accounts data for Egypt has been updated to reflect local constant prices in the year 2022, moving from the previous reference of 2017. | E69: Egypt, Arab Rep.
A70: EMU | D70: Euro area aggregate. | E70: Euro area
A71: ERI | B71: Sub-Saharan Africa | C71: Low income | D71: The World Bank systematically assesses the appropriateness of official exchange rates as conversion factors. In this country, multiple or dual exchange rate activity exists and must be accounted for appropriately in underlying statistics. An alternative estimate (“alternative conversion factor” - PA.NUS.ATLS) is thus calculated as a weighted average of the different exchange rates in use in the country. Doing so better reflects economic reality and leads to more accurate cross-country comparisons and country classifications by income level. For this country, this applies to the period 1992-1997. Alternative conversion factors are used in the Atlas methodology and elsewhere in World Development Indicators as single-year conversion factors. | E71: Eritrea
A72: ESP | B72: Europe & Central Asia | C72: High income | D72: A simple multiplier is used to convert the national currencies of EMU members to euros. The following irrevocable euro conversion rate was adopted by the EU Council on January 1, 1999: 1 euro = 166.386 Spanish peseta. Please note that historical data before 1999 are not actual euros and are not comparable or suitable for aggregation across countries. | E72: Spain
A73: EST | B73: Europe & Central Asia | C73: High income | D73: The following irrevocable euro conversion rate entered into force on January 1, 2011: 1 euro = 15.6466 Estonian kroon. Please note that historical data are not actual euros and are not comparable or suitable for aggregation across countries. | E73: Estonia
A74: ETH | B74: Sub-Saharan Africa | C74: Low income | D74: The reporting period for national accounts data is designated as either calendar year basis (CY) or fiscal year basis (FY). For this country, it is fiscal year-based (fiscal year-end: July 7). Also, an estimate (PA.NUS.ATLS) of the exchange rate covers the same period and thus differs from the official exchange rate (CY). The World Bank systematically assesses the appropriateness of official exchange rates as conversion factors. In this country, multiple or dual exchange rate activity exists and must be accounted for appropriately in underlying statistics. An alternative estimate (“alternative conversion factor” - PA.NUS.ATLS) is thus calculated by using an inflation-adjustment method. Doing so better reflects economic reality and leads to more accurate cross-country comparisons and country classifications by income level. For this country, this applies to the period 2015-2024. Alternative conversion factors are used in the Atlas methodology and elsewhere in World Development Indicators as single-year conversion factors. | E74: Ethiopia
A75: EUU | D75: European Union aggregate. | E75: European Union
A76: FCV | D76: Fragility, Conflict, and Violence (FCV) situations has replaced the previous FCS (Fragile and Conflict-Affected Situations) terminology. Until FY2027, a single Harmonized List of Fragile Situations combined "conflict" and "institutional" fragility. As of July 2026, the public FCV list includes countries where at least 20% of the population lives in areas with high conflict-related fatalities during a reference period. Along with a separted institutional fragility list, more information is available at: https://www.worldbank.org/en/topic/fragilityconflictviolence/brief/classification-of-fragile-and-conflict-affected-situations. | E76: Fragility, Conflict, and Violence (FCV) situations
A77: FIN | B77: Europe & Central Asia | C77: High income | D77: A simple multiplier is used to convert the national currencies of EMU members to euros. The following irrevocable euro conversion rate was adopted by the EU Council on January 1, 1999: 1 euro = 5.94573 Finnish markka. Please note that historical data before 1999 are not actual euros and are not comparable or suitable for aggregation across countries. | E77: Finland
A78: FJI | B78: East Asia & Pacific | C78: Upper middle income | E78: Fiji
A79: FRA | B79: Europe & Central Asia | C79: High income | D79: The following irrevocable euro conversion rate was adopted by the EU Council on January 1, 1999: 1 euro = 6.55957 French franc. Please note that historical data before 1999 are not actual euros and are not comparable or suitable for aggregation across countries. | E79: France
A80: FRO | B80: Europe & Central Asia | C80: High income | E80: Faroe Islands
A81: FSM | B81: East Asia & Pacific | C81: Upper middle income | D81: Fiscal year ends on September 30; reporting period for national accounts data: FY. The source for national accounts data is the Pacific and Virgin Islands Training Initiative. | E81: Micronesia, Fed. Sts.
A82: GAB | B82: Sub-Saharan Africa | C82: Upper middle income | E82: Gabon
A83: GBR | B83: Europe & Central Asia | C83: High income | E83: United Kingdom
A84: GEO | B84: Europe & Central Asia | C84: Upper middle income | D84: Includes self-governed areas only, which mostly exclude Abkhazia and South Ossetia, but small areas in Abkhazia and South Ossetia are included before 2008 or 2009 because of the changes in self-governed areas. | E84: Georgia
A85: GHA | B85: Sub-Saharan Africa | C85: Lower middle income | D85: The World Bank systematically assesses the appropriateness of official exchange rates as conversion factors. In this country, multiple or dual exchange rate activity exists and must be accounted for appropriately in underlying statistics. An alternative estimate (“alternative conversion factor” - PA.NUS.ATLS) is thus calculated as a weighted average of the different exchange rates in use in the country. Doing so better reflects economic reality and leads to more accurate cross-country comparisons and country classifications by income level. For this country, this applies to the period 1974-1987. Alternative conversion factors are used in the Atlas methodology and elsewhere in World Development Indicators as single-year conversion factors. | E85: Ghana
A86: GIB | B86: Europe & Central Asia | C86: High income | D86: The DEC conversion is not reported when national accounts data are unavailable. | E86: Gibraltar
A87: GIN | B87: Sub-Saharan Africa | C87: Lower middle income | E87: Guinea
A88: GMB | B88: Sub-Saharan Africa | C88: Low income | E88: Gambia, The
A89: GNB | B89: Sub-Saharan Africa | C89: Low income | E89: Guinea-Bissau
A90: GNQ | B90: Sub-Saharan Africa | C90: Upper middle income | E90: Equatorial Guinea
A91: GRC | B91: Europe & Central Asia | C91: High income | D91: A simple multiplier is used to convert the national currencies of EMU members to euros. The following irrevocable euro conversion rate was adopted by the EU Council on January 1, 1999: 1 euro = 340.75 Greek drachma. Please note that historical data before 1999 are not actual euros and are not comparable or suitable for aggregation across countries. | E91: Greece
A92: GRD | B92: Latin America & Caribbean | C92: Upper middle income | E92: Grenada
A93: GRL | B93: Europe & Central Asia | C93: High income | E93: Greenland
A94: GTM | B94: Latin America & Caribbean | C94: Upper middle income | D94: The World Bank systematically assesses the appropriateness of official exchange rates as conversion factors. In this country, multiple or dual exchange rate activity exists and must be accounted for appropriately in underlying statistics. An alternative estimate (“alternative conversion factor” - PA.NUS.ATLS) is thus calculated as a weighted average of the different exchange rates in use in the country. Doing so better reflects economic reality and leads to more accurate cross-country comparisons and country classifications by income level. For this country, this applies to the period 1985-2003. Alternative conversion factors are used in the Atlas methodology and elsewhere in World Development Indicators as single-year conversion factors. | E94: Guatemala
A95: GUM | B95: East Asia & Pacific | C95: High income | E95: Guam
A96: GUY | B96: Latin America & Caribbean | C96: High income | E96: Guyana
A97: HIC | D97: For FY27 (July 1, 2026–June 30, 2027), income groups are defined using 2025 GNI per capita (Atlas method): low income (LIC) ($1,175 or less); lower middle income (LMC) ($1,176–$4,635); upper middle income (UMC) ($4,636–$14,375); and high income (HIC) (above $14,375). “Low- and middle-income (LMY)” economies include low-, lower middle-, and upper middle-income groups, while “middle-income (MIC)” economies include lower middle- and upper middle-income groups. | E97: High income
A98: HKG | B98: East Asia & Pacific | C98: High income | D98: On 1 July 1997 China resumed its exercise of sovereignty over Hong Kong. Unless otherwise noted, data for China do not include data for Hong Kong SAR, China; Macao SAR, China; or Taiwan, China. Agriculture value added includes mining and quarrying. | E98: Hong Kong SAR, China
A99: HND | B99: Latin America & Caribbean | C99: Lower middle income | D99: The World Bank systematically assesses the appropriateness of official exchange rates as conversion factors. In this country, multiple or dual exchange rate activity exists and must be accounted for appropriately in underlying statistics. An alternative estimate (“alternative conversion factor” - PA.NUS.ATLS) is thus calculated as a weighted average of the different exchange rates in use in the country. Doing so better reflects economic reality and leads to more accurate cross-country comparisons and country classifications by income level. For this country, this applies to the period 1988-1989. Alternative conversion factors are used in the Atlas methodology and elsewhere in World Development Indicators as single-year conversion factors. | E99: Honduras
A100: HPC | D100: The Heavily Indebted Poor Countries (HIPC) Initiative, launched in 1996 by the IMF and World Bank, aims to reduce the external debt burdens of the most indebted poor countries. Most participants have completed the program, receiving a total of $76 billion in debt-service relief. For more information, visit https://www.imf.org/en/About/Factsheets/Sheets/2016/08/01/16/11/Debt-Relief-Under-the-Heavily-Indebted-Poor-Countries-Initiative. Data presented are aggregates for HIPC countries. | E100: Heavily indebted poor countries (HIPC)
...

Sheet Metadata_Indicator
A1: INDICATOR_CODE | B1: INDICATOR_NAME | C1: SOURCE_NOTE | D1: SOURCE_ORGANIZATION
A2: MS.MIL.MPRT.KD | B2: Arms imports (SIPRI trend indicator values) | C2: Arms transfers (imports) cover the volume of transfers of major arms through sales and gifts, and those made through manufacturing licenses. Data cover major conventional weapons such as aircraft, armored vehicles, artillery, radar systems, missiles, and ships. Figures are SIPRI Trend Indicator Values (TIVs). A '0' indicates that the volume of deliveries is between 0 and 0.5 million SIPRI TIV. | D2: Arms Transfers Programme, Stockholm International Peace Research Institute (SIPRI), uri: https://armstransfers.sipri.org/ArmsTransfer/
